Workbook

Sheet Instructions
D1: EJEMPLO | N1: BS USD rate
C2: FB Revenue Report | D2: Vacio | E2: Protocol | F2: Sponsor | G2: Allentown / Argentina | H2: Custom 2 | K2: Vacio | L2: Line description | M2: YYYY | N2: MM | O2: CURRENCY | P2: 40 % (sin hadling) | R2: 40 % (sin hadling) | S2: Vacio | T2: Not Applicable (solo para Allentown) | V2: no cambia | W2: no cambia
D3: grpcode | E3: el4 | F3: el4_name | G3: el4_sname | H3: name | I3: el2 | J3: el2_name | K3: el3 | L3: el3_name | M3: yr | N3: period | O3: curcode | P3: LOC AMT | Q3: Rate | R3: USD AMT | S3: cmpcode | T3: Discount Flag
A6: Selectable Table | B6: CUSTOMER | C6: Enter grpcode Name
B7: INVOICE_. | C7: Enter Invoice Number (FB/Manual Inv /CN)
A8: blank | B8: FISHER_JOB | C8: Enter Fisher Job Number GPM
B9: PROTOCOL | C9: Enter Protocol Number
B10: yr | C10: Enter Year
B11: period | C11: Enter Period Number
A12: Selectable Table | B12: PRODUCT | C12: Select Category of Revenue
B13: SUB-PRODUCT | C13: Enter Service
B14: DocValue | C14: Enter Total with VAT (Include Surcharge)
B15: DOC_CURRENCY | C15: Enter Currency Invoice
B16: USD Value | C16: Enter Total with VAT in SD Exchange Rate Balance sheet
B17: FISHER_LOC | C17: Enter Site
B18: PO. | C18: Enter PO Number (ONLY)
B19: doccode | C19: NA
B20: el4_name | C20: Enter Sponsor Name
B21: Home Currency | C21: Enter Total with VAT in SD Exchange Rate Balance sheet
B22: docdate | C22: Enter Billing Date
B23: ref1 | C23: NA
A24: Selectable Table | B24: el2 | C24: Enter Revenue Code
A25: Selectable Table | B25: el2_name | C25: Enter Revenue Code
B26: el3 | C26: NA
A29: Include :
A30: 1 | B30: Allentown Invoices 40% (Excluding handling fee)
A31: 2 | B31: Fisherbook Billing_ Local Clients
A32: 3 | B32: Manual Invoices / Rebill
A33: 4 | B33: Credit Notes
A34: 5 | B34: PTC Duties Adjustemnts
A35: 6 | B35: Surcharge lines
A36: 7 | B36: Revenue Adjustments (FX, per category or last 15days estimation)
A37: 8 | B37: Revenue Adjustments (Local Adj /Duty Adj/GNRE Adj)
A38: 9 | B38: Adjustment 606
A40: Don't Include:
A41: a. | B41: Allentown Invoices Full Amount
A42: b. | B42: Manual Invoices / Rebill Transfer Pricing
A43: c. | B43: Credit Notes Transfer Pricing
A49: Porque es importante?
A50: Informacion a equipo comercial para calculo rebate
A51: Generacion de reporte por cliente para McCloskey, Breanna L.
A52: Información útil para consolidación con Americas y otras regiones

Sheet Arg
A1: Vacio | B1: Protocol | C1: Element 4 short name | D1: Allentown / Argentina | E1: Custom 2 | H1: Vacio | I1: Line description | J1: YYYY | K1: MM | L1: CURRENCY | M1: 40 % (sin hadling) | O1: 40 % (sin hadling) | P1: Vacio | Q1: Not Applicable (solo para Allentown) | R1: Vacio | S1: Vacio
A2: grpcode | B2: el4 | C2: el4_name | D2: el4_sname | E2: name | F2: el2 | G2: el2_name | H2: el3 | I2: el3_name | J2: yr | K2: period | L2: curcode | M2: LOC AMT | N2: Rate | O2: USD AMT | P2: cmpcode | Q2: Discount Flag | R2: _ | S2: x
B3: Transfer Pricing 05-2026 | C3: Allentown | D3: Allentown | E3: Total Distribution | F3: 40700 | G3: Revenues - Third Parties | I3: Transfer Pricing | J3: 2026 | K3: 5 | L3: USD | M3: 632795.23 | N3: 1 | O3: =M3*N3 -> 632795.23 | P3: BSArgentina | Q3: Not Applicable | R3: =+VLOOKUP(E3,'Selectable Table'!B:C,2,0) -> Distribution | V3: Row Labels | W3: Sum of LOC AMT | Y3: HFM | Z3: DIF
B4: Transfer Pricing 05-2026 | C4: Allentown | D4: Allentown | E4: Total Duty | F4: 40700 | G4: Revenues - Third Parties | I4: Transfer Pricing | J4: 2026 | K4: 5 | L4: USD | M4: 939471.61 | N4: 1 | O4: =M4*N4 -> 939471.61 | P4: BSArgentina | Q4: Not Applicable | R4: =+VLOOKUP(E4,'Selectable Table'!B:C,2,0) -> Duties | V4: Total Distribution | W4: 691858 | Y4: 691858 | Z4: =Y4-W4 -> 0
B5: Transfer Pricing 05-2026 | C5: Allentown | D5: Allentown | E5: Total Freight | F5: 40700 | G5: Revenues - Third Parties | I5: Transfer Pricing | J5: 2026 | K5: 5 | L5: USD | M5: 553076.9 | N5: 1 | O5: =M5*N5 -> 553076.9 | P5: BSArgentina | Q5: Not Applicable | R5: =+VLOOKUP(E5,'Selectable Table'!B:C,2,0) -> Freight | V5: Total Duty | W5: -498649 | Y5: -498649 | Z5: =Y5-W5 -> 0
B6: Transfer Pricing 05-2026 | C6: Allentown | D6: Allentown | E6: Total Packaging | F6: 40700 | G6: Revenues - Third Parties | I6: Transfer Pricing | J6: 2026 | K6: 5 | L6: USD | M6: 11523.532 | N6: 1 | O6: =M6*N6 -> 11523.532 | P6: BSArgentina | Q6: Not Applicable | R6: =+VLOOKUP(E6,'Selectable Table'!B:C,2,0) -> Packaging | V6: Total Freight | W6: 529642 | Y6: 529642 | Z6: =Y6-W6 -> 0
B7: Transfer Pricing 05-2026 | C7: Allentown | D7: Allentown | E7: Total Return Drug | F7: 40700 | G7: Revenues - Third Parties | I7: Transfer Pricing | J7: 2026 | K7: 5 | L7: USD | M7: 53437.632 | N7: 1 | O7: =M7*N7 -> 53437.632 | P7: BSArgentina | Q7: Not Applicable | R7: =+VLOOKUP(E7,'Selectable Table'!B:C,2,0) -> ReturnDrug | V7: Total Packaging | W7: 36028 | Y7: 36028 | Z7: =Y7-W7 -> 0
B8: Transfer Pricing 05-2026 | C8: Allentown | D8: Allentown | E8: Total Storage | F8: 40700 | G8: Revenues - Third Parties | I8: Transfer Pricing | J8: 2026 | K8: 5 | L8: USD | M8: 399083.04 | N8: 1 | O8: =M8*N8 -> 399083.04 | P8: BSArgentina | Q8: Not Applicable | R8: =+VLOOKUP(E8,'Selectable Table'!B:C,2,0) -> Storage | V8: Total Return Drug | W8: 75325 | Y8: 75325 | Z8: =Y8-W8 -> 0
B9: Materiales pool Janssen | C9: Janssen | D9: Argentina | E9: Total Storage | F9: 40700 | G9: Revenues - Third Parties | I9: Non-Drug Storage Ambient (per Pallet) | J9: 2026 | K9: 5 | L9: USD | M9: 727.7774 | N9: 1 | O9: =M9*N9 -> 727.7774 | P9: BSArgentina | R9: =+VLOOKUP(E9,'Selectable Table'!B:C,2,0) -> Storage | V9: Total Storage | W9: 508279 | Y9: 508279 | Z9: =Y9-W9 -> 0
B10: 64091742PCR3001_anc_returns | C10: Janssen | D10: Argentina | E10: Total Storage | F10: 40700 | G10: Revenues - Third Parties | I10: Storage of Returns (per Pallet) | J10: 2026 | K10: 5 | L10: USD | M10: 262.00913 | N10: 1 | O10: =M10*N10 -> 262.00913 | P10: BSArgentina | R10: =+VLOOKUP(E10,'Selectable Table'!B:C,2,0) -> Storage | V10: Grand Total | W10: 1342483 | Y10: =SUM(Y4:Y9) -> 1342483 | Z10: =W10-Y10 -> 0
B11: 56021927PCR3011_Anc_Returns | C11: Janssen | D11: Argentina | E11: Total Storage | F11: 40700 | G11: Revenues - Third Parties | I11: Non-Drug Storage Ambient (per Pallet) | J11: 2026 | K11: 5 | L11: USD | M11: 181.94435 | N11: 1 | O11: =M11*N11 -> 181.94435 | P11: BSArgentina | R11: =+VLOOKUP(E11,'Selectable Table'!B:C,2,0) -> Storage
B12: 56021927PCR3011_Anc_Returns | C12: Janssen | D12: Argentina | E12: Total Storage | F12: 40700 | G12: Revenues - Third Parties | I12: Storage of Returns (per Pallet) | J12: 2026 | K12: 5 | L12: USD | M12: 87.336375 | N12: 1 | O12: =M12*N12 -> 87.336375 | P12: BSArgentina | R12: =+VLOOKUP(E12,'Selectable Table'!B:C,2,0) -> Storage
B13: CNTO1959UCO3001_Anc_Returns | C13: Janssen | D13: Argentina | E13: Total Storage | F13: 40700 | G13: Revenues - Third Parties | I13: Non-Drug Storage Ambient (per Pallet) | J13: 2026 | K13: 5 | L13: USD | M13: 1091.6661 | N13: 1 | O13: =M13*N13 -> 1091.6661 | P13: BSArgentina | R13: =+VLOOKUP(E13,'Selectable Table'!B:C,2,0) -> Storage | V13: Antes del ajuste:
B14: CNTO1959UCO3001_Anc_Returns | C14: Janssen | D14: Argentina | E14: Total Storage | F14: 40700 | G14: Revenues - Third Parties | I14: Storage of Returns (per Pallet) | J14: 2026 | K14: 5 | L14: USD | M14: 436.68187 | N14: 1 | O14: =M14*N14 -> 436.68187 | P14: BSArgentina | R14: =+VLOOKUP(E14,'Selectable Table'!B:C,2,0) -> Storage
B15: AC-055-315_anc_returns | C15: Janssen | D15: Argentina | E15: Total Storage | F15: 40700 | G15: Revenues - Third Parties | I15: Non-Drug Storage Ambient (per Pallet) | J15: 2026 | K15: 5 | L15: USD | M15: 181.94435 | N15: 1 | O15: =M15*N15 -> 181.94435 | P15: BSArgentina | R15: =+VLOOKUP(E15,'Selectable Table'!B:C,2,0) -> Storage
B16: AC-055-315_anc_returns | C16: Janssen | D16: Argentina | E16: Total Storage | F16: 40700 | G16: Revenues - Third Parties | I16: Storage Ambient (per Pallet) | J16: 2026 | K16: 5 | L16: USD | M16: 545.83305 | N16: 1 | O16: =M16*N16 -> 545.83305 | P16: BSArgentina | R16: =+VLOOKUP(E16,'Selectable Table'!B:C,2,0) -> Storage
B17: AC-055-315_anc_returns | C17: Janssen | D17: Argentina | E17: Total Storage | F17: 40700 | G17: Revenues - Third Parties | I17: Storage of Returns (per Pallet) | J17: 2026 | K17: 5 | L17: USD | M17: 611.35463 | N17: 1 | O17: =M17*N17 -> 611.35463 | P17: BSArgentina | R17: =+VLOOKUP(E17,'Selectable Table'!B:C,2,0) -> Storage
B18: 67652000PCR3002_anc_returns | C18: Janssen | D18: Argentina | E18: Total Freight | F18: 40700 | G18: Revenues - Third Parties | I18: Freight - Returns | J18: 2026 | K18: 5 | L18: USD | M18: 333.03 | N18: 1 | O18: =M18*N18 -> 333.03 | P18: BSArgentina | R18: =+VLOOKUP(E18,'Selectable Table'!B:C,2,0) -> Freight
B19: 67652000PCR3002_anc_returns | C19: Janssen | D19: Argentina | E19: Total Storage | F19: 40700 | G19: Revenues - Third Parties | I19: Storage of Returns (per Pallet) | J19: 2026 | K19: 5 | L19: USD | M19: 786.02738 | N19: 1 | O19: =M19*N19 -> 786.02738 | P19: BSArgentina | R19: =+VLOOKUP(E19,'Selectable Table'!B:C,2,0) -> Storage
B20: 73841937NSC3003_Anc_Returns | C20: Janssen | D20: Argentina | E20: Total Freight | F20: 40700 | G20: Revenues - Third Parties | I20: Freight - Returns | J20: 2026 | K20: 5 | L20: USD | M20: 752.04 | N20: 1 | O20: =M20*N20 -> 752.04 | P20: BSArgentina | R20: =+VLOOKUP(E20,'Selectable Table'!B:C,2,0) -> Freight
B21: 73841937NSC3003_Anc_Returns | C21: Janssen | D21: Argentina | E21: Total Storage | F21: 40700 | G21: Revenues - Third Parties | I21: Non-Drug Storage Ambient (per Pallet) | J21: 2026 | K21: 5 | L21: USD | M21: 181.94435 | N21: 1 | O21: =M21*N21 -> 181.94435 | P21: BSArgentina | R21: =+VLOOKUP(E21,'Selectable Table'!B:C,2,0) -> Storage
B22: 73841937NSC3003_Anc_Returns | C22: Janssen | D22: Argentina | E22: Total Return Drug | F22: 40700 | G22: Revenues - Third Parties | I22: Reconciliation of Returns (per Hour) | J22: 2026 | K22: 5 | L22: USD | M22: 50.944075 | N22: 1 | O22: =M22*N22 -> 50.944075 | P22: BSArgentina | R22: =+VLOOKUP(E22,'Selectable Table'!B:C,2,0) -> ReturnDrug
B23: 73841937NSC3003_Anc_Returns | C23: Janssen | D23: Argentina | E23: Total Return Drug | F23: 40700 | G23: Revenues - Third Parties | I23: Returns Receipt (per Receipt) | J23: 2026 | K23: 5 | L23: USD | M23: 133.72713 | N23: 1 | O23: =M23*N23 -> 133.72713 | P23: BSArgentina | R23: =+VLOOKUP(E23,'Selectable Table'!B:C,2,0) -> ReturnDrug
B24: 73841937NSC3003_Anc_Returns | C24: Janssen | D24: Argentina | E24: Total Storage | F24: 40700 | G24: Revenues - Third Parties | I24: Storage of Returns (per Pallet) | J24: 2026 | K24: 5 | L24: USD | M24: 611.35463 | N24: 1 | O24: =M24*N24 -> 611.35463 | P24: BSArgentina | R24: =+VLOOKUP(E24,'Selectable Table'!B:C,2,0) -> Storage
B25: CNTO1959PSA4002_Anc_Returns | C25: Janssen | D25: Argentina | E25: Total Freight | F25: 40700 | G25: Revenues - Third Parties | I25: Freight - Returns | J25: 2026 | K25: 5 | L25: USD | M25: 191.15 | N25: 1 | O25: =M25*N25 -> 191.15 | P25: BSArgentina | R25: =+VLOOKUP(E25,'Selectable Table'!B:C,2,0) -> Freight
... B434: PHRI.COLT-HF | C434: Site Management Organization Argentina SA | D434: Argentina | E434: Total Storage | F434: 40700 | G434: Revenues - Third Parties | I434: Storage of Labels Ambient (per Pallet) | J434: 2026 | K434: 5 | L434: USD | M434: 1011.84 | N434: 1 | O434: =M434*N434 -> 1011.84 | P434: BSArgentina | R434: =+VLOOKUP(E434,'Selectable Table'!B:C,2,0) -> Storage
B435: PHRI.COLT-HF | C435: Site Management Organization Argentina SA | D435: Argentina | E435: Total Return Drug | F435: 40700 | G435: Revenues - Third Parties | I435: Destruction (per Kg) | J435: 2026 | K435: 5 | L435: USD | M435: -106.65 | N435: 1 | O435: =M435*N435 -> -106.65 | P435: BSArgentina | R435: =+VLOOKUP(E435,'Selectable Table'!B:C,2,0) -> ReturnDrug | T435: CN NO TP
B436: PHRI.COLT-HF | C436: Site Management Organization Argentina SA | D436: Argentina | E436: Total Return Drug | F436: 40700 | G436: Revenues - Third Parties | I436: Destruction Setup Fee | J436: 2026 | K436: 5 | L436: USD | M436: -1360.1 | N436: 1 | O436: =M436*N436 -> -1360.1 | P436: BSArgentina | R436: =+VLOOKUP(E436,'Selectable Table'!B:C,2,0) -> ReturnDrug | T436: CN NO TP
B437: PHRI.COLT-HF | C437: Site Management Organization Argentina SA | D437: Argentina | E437: Total Storage | F437: 40700 | G437: Revenues - Third Parties | I437: Non-Drug Storage Ambient (per Shelf) | J437: 2026 | K437: 5 | L437: USD | M437: -95 | N437: 1 | O437: =M437*N437 -> -95 | P437: BSArgentina | R437: =+VLOOKUP(E437,'Selectable Table'!B:C,2,0) -> Storage | T437: CN NO TP
B438: PHRI.COLT-HF | C438: Site Management Organization Argentina SA | D438: Argentina | E438: Total Distribution | F438: 40700 | G438: Revenues - Third Parties | I438: Project Management Fee | J438: 2026 | K438: 5 | L438: USD | M438: -450 | N438: 1 | O438: =M438*N438 -> -450 | P438: BSArgentina | R438: =+VLOOKUP(E438,'Selectable Table'!B:C,2,0) -> Distribution | T438: CN NO TP
B439: PHRI.COLT-HF | C439: Site Management Organization Argentina SA | D439: Argentina | E439: Total Distribution | F439: 40700 | G439: Revenues - Third Parties | I439: Receipt of Labels (per Receipt_ID) | J439: 2026 | K439: 5 | L439: USD | M439: -296.4 | N439: 1 | O439: =M439*N439 -> -296.4 | P439: BSArgentina | R439: =+VLOOKUP(E439,'Selectable Table'!B:C,2,0) -> Distribution | T439: CN NO TP
B440: PHRI.COLT-HF | C440: Site Management Organization Argentina SA | D440: Argentina | E440: Total Storage | F440: 40700 | G440: Revenues - Third Parties | I440: Storage Ambient (per Pallet) | J440: 2026 | K440: 5 | L440: USD | M440: -3243.1 | N440: 1 | O440: =M440*N440 -> -3243.1 | P440: BSArgentina | R440: =+VLOOKUP(E440,'Selectable Table'!B:C,2,0) -> Storage | T440: CN NO TP
B441: PHRI.COLT-HF | C441: Site Management Organization Argentina SA | D441: Argentina | E441: Total Storage | F441: 40700 | G441: Revenues - Third Parties | I441: Storage of Labels Ambient (per Pallet) | J441: 2026 | K441: 5 | L441: USD | M441: -1349.12 | N441: 1 | O441: =M441*N441 -> -1349.12 | P441: BSArgentina | R441: =+VLOOKUP(E441,'Selectable Table'!B:C,2,0) -> Storage | T441: CN NO TP
B442: PHRI.COLT-HF | C442: Site Management Organization Argentina SA | D442: Argentina | E442: Total Return Drug | F442: 40700 | G442: Revenues - Third Parties | I442: Destruction (per Kg) | J442: 2026 | K442: 5 | L442: USD | M442: 106.65 | N442: 1 | O442: =M442*N442 -> 106.65 | P442: BSArgentina | R442: =+VLOOKUP(E442,'Selectable Table'!B:C,2,0) -> ReturnDrug | T442: RB NO TP
B443: PHRI.COLT-HF | C443: Site Management Organization Argentina SA | D443: Argentina | E443: Total Return Drug | F443: 40700 | G443: Revenues - Third Parties | I443: Destruction Setup Fee | J443: 2026 | K443: 5 | L443: USD | M443: 1360.1 | N443: 1 | O443: =M443*N443 -> 1360.1 | P443: BSArgentina | R443: =+VLOOKUP(E443,'Selectable Table'!B:C,2,0) -> ReturnDrug | T443: RB NO TP
B444: PHRI.COLT-HF | C444: Site Management Organization Argentina SA | D444: Argentina | E444: Total Storage | F444: 40700 | G444: Revenues - Third Parties | I444: Non-Drug Storage Ambient (per Shelf) | J444: 2026 | K444: 5 | L444: USD | M444: 95 | N444: 1 | O444: =M444*N444 -> 95 | P444: BSArgentina | R444: =+VLOOKUP(E444,'Selectable Table'!B:C,2,0) -> Storage | T444: RB NO TP
B445: PHRI.COLT-HF | C445: Site Management Organization Argentina SA | D445: Argentina | E445: Total Distribution | F445: 40700 | G445: Revenues - Third Parties | I445: Project Management Fee | J445: 2026 | K445: 5 | L445: USD | M445: 450 | N445: 1 | O445: =M445*N445 -> 450 | P445: BSArgentina | R445: =+VLOOKUP(E445,'Selectable Table'!B:C,2,0) -> Distribution | T445: RB NO TP
B446: PHRI.COLT-HF | C446: Site Management Organization Argentina SA | D446: Argentina | E446: Total Storage | F446: 40700 | G446: Revenues - Third Parties | I446: Storage Ambient (per Pallet) | J446: 2026 | K446: 5 | L446: USD | M446: 3243.1 | N446: 1 | O446: =M446*N446 -> 3243.1 | P446: BSArgentina | R446: =+VLOOKUP(E446,'Selectable Table'!B:C,2,0) -> Storage | T446: RB NO TP
... B488: MK-2400-001 (Local) | C488: Merck Sharp and Dohme LLC | D488: Argentina | E488: Total Storage | F488: 40700 | G488: Revenues - Third Parties | I488: Storage Ambient (per Pallet) | J488: 2026 | K488: 5 | L488: USD | M488: 286.89 | N488: 1 | O488: =M488*N488 -> 286.89 | P488: BSArgentina | R488: =+VLOOKUP(E488,'Selectable Table'!B:C,2,0) -> Storage | T488: Ajuste manual
B489: I8F-MC-GPJA (CAM) | C489: Eli Lilly & Co. | D489: Argentina | E489: Total Freight | F489: 40700 | G489: Revenues - Third Parties | I489: Annual Rebate | J489: 2026 | K489: 5 | L489: USD | M489: 0 | N489: 1 | O489: =M489*N489 -> 0 | P489: BSArgentina | R489: =+VLOOKUP(E489,'Selectable Table'!B:C,2,0) -> Freight
B490: GG917 Psych Bundle (CAM) | C490: Eli Lilly & Co. | D490: Argentina | E490: Total Duty | F490: 40700 | G490: Revenues - Third Parties | I490: PTC Duties | J490: 2026 | K490: 5 | L490: USD | M490: 0 | N490: 1 | O490: =M490*N490 -> 0 | P490: BSArgentina | R490: =+VLOOKUP(E490,'Selectable Table'!B:C,2,0) -> Duties
B491: J6M-MC-JSGD (CAM) | C491: Eli Lilly & Co. | D491: Argentina | E491: Total Duty | F491: 40700 | G491: Revenues - Third Parties | I491: PTC Duties | J491: 2026 | K491: 5 | L491: USD | M491: -978.405 | N491: 1 | O491: =M491*N491 -> -978.405 | P491: BSArgentina | R491: =+VLOOKUP(E491,'Selectable Table'!B:C,2,0) -> Duties
B492: J3R-MC-YDAF (CAM) | C492: Eli Lilly & Co. | D492: Argentina | E492: Total Duty | F492: 40700 | G492: Revenues - Third Parties | I492: PTC Duties | J492: 2026 | K492: 5 | L492: USD | M492: 0 | N492: 1 | O492: =M492*N492 -> 0 | P492: BSArgentina | R492: =+VLOOKUP(E492,'Selectable Table'!B:C,2,0) -> Duties
B493: J2A-MC-GZPR (CAM) | C493: Eli Lilly & Co. | D493: Argentina | E493: Total Duty | F493: 40700 | G493: Revenues - Third Parties | I493: PTC Duties | J493: 2026 | K493: 5 | L493: USD | M493: -12376.815 | N493: 1 | O493: =M493*N493 -> -12376.815 | P493: BSArgentina | R493: =+VLOOKUP(E493,'Selectable Table'!B:C,2,0) -> Duties
B494: Lilly Admin and one-time costs | C494: Eli Lilly & Co. | D494: Argentina | E494: Total Duty | F494: 40700 | G494: Revenues - Third Parties | I494: PTC Duties | J494: 2026 | K494: 5 | L494: USD | M494: 0 | N494: 1 | O494: =M494*N494 -> 0 | P494: BSArgentina | R494: =+VLOOKUP(E494,'Selectable Table'!B:C,2,0) -> Duties
B495: J2G-OX-Y049 | C495: Eli Lilly & Co. | D495: Argentina | E495: Total Duty | F495: 40700 | G495: Revenues - Third Parties | I495: PTC Duties | J495: 2026 | K495: 5 | L495: USD | M495: -11999.223 | N495: 1 | O495: =M495*N495 -> -11999.223 | P495: BSArgentina | R495: =+VLOOKUP(E495,'Selectable Table'!B:C,2,0) -> Duties
B496: J2J-OX-JZLC | C496: Eli Lilly & Co. | D496: Argentina | E496: Total Duty | F496: 40700 | G496: Revenues - Third Parties | I496: PTC Duties | J496: 2026 | K496: 5 | L496: USD | M496: -1094.8561 | N496: 1 | O496: =M496*N496 -> -1094.8561 | P496: BSArgentina | R496: =+VLOOKUP(E496,'Selectable Table'!B:C,2,0) -> Duties
B497: I8F-MC-GPIJ | C497: Eli Lilly & Co. | D497: Argentina | E497: Total Duty | F497: 40700 | G497: Revenues - Third Parties | I497: PTC Duties | J497: 2026 | K497: 5 | L497: USD | M497: -13342.445 | N497: 1 | O497: =M497*N497 -> -13342.445 | P497: BSArgentina | R497: =+VLOOKUP(E497,'Selectable Table'!B:C,2,0) -> Duties
B498: J2J-MC-JZLH | C498: Eli Lilly & Co. | D498: Argentina | E498: Total Duty | F498: 40700 | G498: Revenues - Third Parties | I498: PTC Duties | J498: 2026 | K498: 5 | L498: USD | M498: -24881.039 | N498: 1 | O498: =M498*N498 -> -24881.039 | P498: BSArgentina | R498: =+VLOOKUP(E498,'Selectable Table'!B:C,2,0) -> Duties
B499: J1I-MC-GZBO | C499: Eli Lilly & Co. | D499: Argentina | E499: Total Duty | F499: 40700 | G499: Revenues - Third Parties | I499: PTC Duties | J499: 2026 | K499: 5 | L499: USD | M499: -1160.2215 | N499: 1 | O499: =M499*N499 -> -1160.2215 | P499: BSArgentina | R499: =+VLOOKUP(E499,'Selectable Table'!B:C,2,0) -> Duties
B500: J3L-MC-EZEF | C500: Eli Lilly & Co. | D500: Argentina | E500: Total Duty | F500: 40700 | G500: Revenues - Third Parties | I500: PTC Duties | J500: 2026 | K500: 5 | L500: USD | M500: -42528.055 | N500: 1 | O500: =M500*N500 -> -42528.055 | P500: BSArgentina | R500: =+VLOOKUP(E500,'Selectable Table'!B:C,2,0) -> Duties
... B526: D702FC00001 | C526: Astra Zeneca | D526: Argentina | E526: Total Duty | F526: 40700 | G526: Revenues - Third Parties | I526: PTC Duties | J526: 2026 | K526: 5 | L526: USD | M526: -10988.54 | N526: 1 | O526: =M526*N526 -> -10988.54 | P526: BSArgentina | R526: =+VLOOKUP(E526,'Selectable Table'!B:C,2,0) -> Duties
B527: 20190341 | C527: Amgen, Inc. | D527: Argentina | E527: Total Duty | F527: 40700 | G527: Revenues - Third Parties | I527: PTC Duties | J527: 2026 | K527: 5 | L527: USD | M527: -1355.4547 | N527: 1 | O527: =M527*N527 -> -1355.4547 | P527: BSArgentina | R527: =+VLOOKUP(E527,'Selectable Table'!B:C,2,0) -> Duties
B528: 20230016 | C528: Amgen, Inc. | D528: Argentina | E528: Total Duty | F528: 40700 | G528: Revenues - Third Parties | I528: PTC Duties | J528: 2026 | K528: 5 | L528: USD | M528: -14053.61 | N528: 1 | O528: =M528*N528 -> -14053.61 | P528: BSArgentina | R528: =+VLOOKUP(E528,'Selectable Table'!B:C,2,0) -> Duties
B529: 20200041 | C529: Amgen, Inc. | D529: Argentina | E529: Total Duty | F529: 40700 | G529: Revenues - Third Parties | I529: PTC Duties | J529: 2026 | K529: 5 | L529: USD | M529: -9383.4789 | N529: 1 | O529: =M529*N529 -> -9383.4789 | P529: BSArgentina | R529: =+VLOOKUP(E529,'Selectable Table'!B:C,2,0) -> Duties
B530: 20210081 | C530: Amgen, Inc. | D530: Argentina | E530: Total Duty | F530: 40700 | G530: Revenues - Third Parties | I530: PTC Duties | J530: 2026 | K530: 5 | L530: USD | M530: -1174.3523 | N530: 1 | O530: =M530*N530 -> -1174.3523 | P530: BSArgentina | R530: =+VLOOKUP(E530,'Selectable Table'!B:C,2,0) -> Duties
B531: 20210181 | C531: Amgen, Inc. | D531: Argentina | E531: Total Duty | F531: 40700 | G531: Revenues - Third Parties | I531: PTC Duties | J531: 2026 | K531: 5 | L531: USD | M531: -256619.42 | N531: 1 | O531: =M531*N531 -> -256619.42 | P531: BSArgentina | R531: =+VLOOKUP(E531,'Selectable Table'!B:C,2,0) -> Duties
B532: 20220196 | C532: Amgen, Inc. | D532: Argentina | E532: Total Duty | F532: 40700 | G532: Revenues - Third Parties | I532: PTC Duties | J532: 2026 | K532: 5 | L532: USD | M532: -12851.857 | N532: 1 | O532: =M532*N532 -> -12851.857 | P532: BSArgentina | R532: =+VLOOKUP(E532,'Selectable Table'!B:C,2,0) -> Duties
B533: 20210184 | C533: Amgen, Inc. | D533: Argentina | E533: Total Duty | F533: 40700 | G533: Revenues - Third Parties | I533: PTC Duties | J533: 2026 | K533: 5 | L533: USD | M533: -103865.69 | N533: 1 | O533: =M533*N533 -> -103865.69 | P533: BSArgentina | R533: =+VLOOKUP(E533,'Selectable Table'!B:C,2,0) -> Duties
B534: 20240236 | C534: Amgen, Inc. | D534: Argentina | E534: Total Duty | F534: 40700 | G534: Revenues - Third Parties | I534: PTC Duties | J534: 2026 | K534: 5 | L534: USD | M534: -33796.13 | N534: 1 | O534: =M534*N534 -> -33796.13 | P534: BSArgentina | R534: =+VLOOKUP(E534,'Selectable Table'!B:C,2,0) -> Duties
B535: Others | C535: Deferred Revenue | D535: Argentina | E535: Total Duty | F535: 40700 | G535: Revenues - Third Parties | I535: PTC Duties | J535: 2026 | K535: 5 | L535: USD | M535: -2464.5222 | N535: 1 | O535: =M535*N535 -> -2464.5222 | P535: BSArgentina | R535: =+VLOOKUP(E535,'Selectable Table'!B:C,2,0) -> Duties
B536: Others | C536: Deferred Revenue | D536: Argentina | E536: Total Duty | F536: 40700 | G536: Revenues - Third Parties | I536: PTC Duties - Reverse | J536: 2026 | K536: 5 | L536: USD | M536: -665000 | N536: 1 | O536: =M536*N536 -> -665000 | P536: BSArgentina | R536: =+VLOOKUP(E536,'Selectable Table'!B:C,2,0) -> Duties
B537: Others | C537: Deferred Revenue | D537: Argentina | E537: Total Freight | F537: 40700 | G537: Revenues - Third Parties | I537: Adjustment due to services rendered between 16/03 - 31/03 | J537: 2026 | K537: 5 | L537: USD | M537: -388113.46 | N537: 1 | O537: =M537*N537 -> -388113.46 | P537: BSArgentina | R537: =+VLOOKUP(E537,'Selectable Table'!B:C,2,0) -> Freight
B538: Others | C538: Deferred Revenue | D538: Argentina | E538: Total Distribution | F538: 40700 | G538: Revenues - Third Parties | I538: Adjustment due to services rendered between 16/03 - 31/03 | J538: 2026 | K538: 5 | L538: USD | M538: -147607.56 | N538: 1 | O538: =M538*N538 -> -147607.56 | P538: BSArgentina | R538: =+VLOOKUP(E538,'Selectable Table'!B:C,2,0) -> Distribution
B539: Others | C539: Deferred Revenue | D539: Argentina | E539: Total Freight | F539: 40700 | G539: Revenues - Third Parties | I539: Adjustment Estimated Revenue of the month 16/03 - 15/04 | J539: 2026 | K539: 5 | L539: USD | M539: -1400513 | N539: 1 | O539: =M539*N539 -> -1400513 | P539: BSArgentina | R539: =+VLOOKUP(E539,'Selectable Table'!B:C,2,0) -> Freight
B540: Others | C540: Deferred Revenue | D540: Argentina | E540: Total Duty | F540: 40700 | G540: Revenues - Third Parties | I540: PTC Duties (AMGEN) | J540: 2026 | K540: 5 | L540: USD | M540: 0 | N540: 1 | O540: =M540*N540 -> 0 | P540: BSArgentina | R540: =+VLOOKUP(E540,'Selectable Table'!B:C,2,0) -> Duties
B541: Others | C541: Deferred Revenue | D541: Argentina | E541: Total Freight | F541: 40700 | G541: Revenues - Third Parties | I541: Estimated Revenue from 16/04 - 30/04 | J541: 2026 | K541: 5 | L541: USD | M541: 333351.2 | N541: 1 | O541: =M541*N541 -> 333351.2 | P541: BSArgentina | R541: =+VLOOKUP(E541,'Selectable Table'!B:C,2,0) -> Freight
B542: Others | C542: Deferred Revenue | D542: Argentina | E542: Total Distribution | F542: 40700 | G542: Revenues - Third Parties | I542: Estimated Revenue from 16/04 - 30/04 | J542: 2026 | K542: 5 | L542: USD | M542: 150775.72 | N542: 1 | O542: =M542*N542 -> 150775.72 | P542: BSArgentina | R542: =+VLOOKUP(E542,'Selectable Table'!B:C,2,0) -> Distribution
B543: Others | C543: Deferred Revenue | D543: Argentina | E543: Total Freight | F543: 40700 | G543: Revenues - Third Parties | I543: Estimated Revenue of the month from 16/04 - 15/05 | J543: 2026 | K543: 5 | L543: USD | M543: 1379027.7 | N543: 1 | O543: =M543*N543 -> 1379027.7 | P543: BSArgentina | R543: =+VLOOKUP(E543,'Selectable Table'!B:C,2,0) -> Freight
B544: Others | C544: Deferred Revenue | D544: Argentina | E544: Total Storage | F544: 40700 | G544: Revenues - Third Parties | I544: Provision NC Pfizer Storage | J544: 2026 | K544: 5 | L544: USD | M544: 0 | N544: 1 | O544: =M544*N544 -> 0 | P544: BSArgentina | R544: =+VLOOKUP(E544,'Selectable Table'!B:C,2,0) -> Storage
B545: Others | C545: Others | D545: Argentina | E545: Total Storage | F545: 40700 | G545: Revenues - Third Parties | I545: Storage | J545: 2026 | K545: 5 | L545: USD | M545: 0 | N545: 1 | O545: =M545*N545 -> 0 | P545: BSArgentina | R545: =+VLOOKUP(E545,'Selectable Table'!B:C,2,0) -> Storage
B546: Others | C546: Others | D546: Argentina | E546: Total Distribution | F546: 40700 | G546: Revenues - Third Parties | I546: Distribution | J546: 2026 | K546: 5 | L546: USD | M546: 0 | N546: 1 | O546: =M546*N546 -> 0 | P546: BSArgentina | R546: =+VLOOKUP(E546,'Selectable Table'!B:C,2,0) -> Distribution
... B557: Others | C557: Others | D557: Argentina | E557: Total Return Drug | F557: 40700 | G557: Revenues - Third Parties | I557: FX Translation | J557: 2026 | K557: 5 | L557: USD | M557: 2447.4262 | N557: 1 | O557: =M557*N557 -> 2447.4262 | P557: BSArgentina | R557: =+VLOOKUP(E557,'Selectable Table'!B:C,2,0) -> ReturnDrug
B558: Others | C558: Others | D558: Argentina | E558: Total Distribution | F558: 40700 | G558: Revenues - Third Parties | I558: FX Translation | J558: 2026 | K558: 5 | L558: USD | M558: 471.39703 | N558: 1 | O558: =M558*N558 -> 471.39703 | P558: BSArgentina | R558: =+VLOOKUP(E558,'Selectable Table'!B:C,2,0) -> Distribution | T558: AJUSTES
B559: Others | C559: Others | D559: Argentina | E559: Total Duty | F559: 40700 | G559: Revenues - Third Parties | I559: FX Translation | J559: 2026 | K559: 5 | L559: USD | M559: -57.914116 | N559: 1 | O559: =M559*N559 -> -57.914116 | P559: BSArgentina | R559: =+VLOOKUP(E559,'Selectable Table'!B:C,2,0) -> Duties | T559: AJUSTES
B560: Others | C560: Others | D560: Argentina | E560: Total Freight | F560: 40700 | G560: Revenues - Third Parties | I560: FX Translation | J560: 2026 | K560: 5 | L560: USD | M560: 1647.4871 | N560: 1 | O560: =M560*N560 -> 1647.4871 | P560: BSArgentina | R560: =+VLOOKUP(E560,'Selectable Table'!B:C,2,0) -> Freight | T560: AJUSTES
B561: Others | C561: Others | D561: Argentina | E561: Total Packaging | F561: 40700 | G561: Revenues - Third Parties | I561: FX Translation | J561: 2026 | K561: 5 | L561: USD | M561: 0.7449656 | N561: 1 | O561: =M561*N561 -> 0.7449656 | P561: BSArgentina | R561: =+VLOOKUP(E561,'Selectable Table'!B:C,2,0) -> Packaging | T561: AJUSTES
B562: Others | C562: Others | D562: Argentina | E562: Total Return Drug | F562: 40700 | G562: Revenues - Third Parties | I562: FX Translation | J562: 2026 | K562: 5 | L562: USD | M562: -1340.9318 | N562: 1 | O562: =M562*N562 -> -1340.9318 | P562: BSArgentina | R562: =+VLOOKUP(E562,'Selectable Table'!B:C,2,0) -> ReturnDrug | T562: AJUSTES
B563: Others | C563: Others | D563: Argentina | E563: Total Storage | F563: 40700 | G563: Revenues - Third Parties | I563: FX Translation | J563: 2026 | K563: 5 | L563: USD | M563: 448.40059 | N563: 1 | O563: =M563*N563 -> 448.40059 | P563: BSArgentina | R563: =+VLOOKUP(E563,'Selectable Table'!B:C,2,0) -> Storage | T563: AJUSTES
O564: =SUM(O3:O563) -> 1342483

Sheet Bra TP
A1: Vacio | B1: Protocol | C1: Element 4 short name | D1: Allentown / Argentina | E1: Custom 2 | H1: Vacio | I1: Line description | J1: YYYY | K1: MM | L1: CURRENCY | M1: 40 % (sin hadling) | O1: 40 % (sin hadling) | P1: Vacio | Q1: Not Applicable (solo para Allentown) | R1: Vacio | S1: Vacio | Y1: LocalAdj- Duties | Z1: ICO+NONICO
A2: grpcode | B2: el4 | C2: el4_name | D2: el4_sname | E2: name | F2: el2 | G2: el2_name | H2: el3 | I2: el3_name | J2: yr | K2: period | L2: curcode | M2: LOC AMT | N2: Rate | O2: USD AMT | P2: cmpcode | Q2: Discount Flag | R2: _ | S2: x
B3: EMN30-64007957MMY3003 - Azidus | C3: Azidus Brasil Pesquisa Científica | D3: Brazil | E3: Duties | I3: PTC Duties | M3: -11829.375 | O3: -11829.375 | P3: BSBRAZILTP | Q3: Not Applicable
B4: Bayer - Importer of Record Services | C4: Bayer AG (No consolidate) | D4: Brazil | E4: Duties | I4: PTC Duties | M4: -51624.855 | O4: -51624.855 | P4: BSBRAZILTP | Q4: Not Applicable
B5: J3R-MC-YDAL (CAM) | C5: Eli Lilly & Co. | D5: Brazil | E5: Duties | I5: PTC Duties | M5: -3111.4067 | O5: -3111.4067 | P5: BSBRAZILTP | Q5: Not Applicable
B6: J3R-MC-YDAO (CAM) | C6: Eli Lilly & Co. | D6: Brazil | E6: Duties | I6: PTC Duties | M6: -2251.0131 | O6: -2251.0131 | P6: BSBRAZILTP | Q6: Not Applicable
B7: Lilly Admin and one-time costs | C7: Eli Lilly & Co. | D7: Brazil | E7: Duties | I7: PTC Duties | M7: -411.37841 | O7: -411.37841 | P7: BSBRAZILTP | Q7: Not Applicable
B8: 42756493BLC3001 | C8: Janssen | D8: Brazil | E8: Duties | I8: PTC Duties | M8: -4020.2542 | O8: -4020.2542 | P8: BSBRAZILTP | Q8: Not Applicable
B9: 39039039THR3001 | C9: Janssen | D9: Brazil | E9: Duties | I9: PTC Duties | M9: -167.03421 | O9: -167.03421 | P9: BSBRAZILTP | Q9: Not Applicable
B10: J2G-MC-JZJB | C10: Eli Lilly & Co. | D10: Brazil | E10: Duties | I10: PTC Duties | M10: -71332.26 | O10: -71332.26 | P10: BSBRAZILTP | Q10: Not Applicable
B11: I8F-MC-GPGN | C11: Eli Lilly & Co. | D11: Brazil | E11: Duties | I11: PTC Duties | M11: -4990.8416 | O11: -4990.8416 | P11: BSBRAZILTP | Q11: Not Applicable
B12: 67652000PCR3002 | C12: Janssen | D12: Brazil | E12: Duties | I12: PTC Duties | M12: -978.88072 | O12: -978.88072 | P12: BSBRAZILTP | Q12: Not Applicable
B13: J2G-MC-JZJX | C13: Eli Lilly & Co. | D13: Brazil | E13: Duties | I13: PTC Duties | M13: -20455.044 | O13: -20455.044 | P13: BSBRAZILTP | Q13: Not Applicable
B14: I8F-MC-GPI1 | C14: Eli Lilly & Co. | D14: Brazil | E14: Duties | I14: PTC Duties | M14: -1941.8632 | O14: -1941.8632 | P14: BSBRAZILTP | Q14: Not Applicable
... B42: D926NC00001 | C42: Astra Zeneca | D42: Brazil | E42: Duties | I42: PTC Duties | M42: -1423.6512 | O42: -1423.6512 | P42: BSBRAZILTP | Q42: Not Applicable
B43: 20190360 | C43: Amgen, Inc. | D43: Brazil | E43: Duties | I43: PTC Duties | M43: -1954.3925 | O43: -1954.3925 | P43: BSBRAZILTP | Q43: Not Applicable
B44: D7020C00001 | C44: MedImmune Inc | D44: Brazil | E44: Duties | I44: PTC Duties | M44: -2074.644 | O44: -2074.644 | P44: BSBRAZILTP | Q44: Not Applicable
B45: D3466C00001 | C45: Astra Zeneca | D45: Brazil | E45: Duties | I45: PTC Duties | M45: -951.91133 | O45: -951.91133 | P45: BSBRAZILTP | Q45: Not Applicable
B46: Temperature Monitor-Global Pooling | C46: Astra Zeneca | D46: Brazil | E46: Duties | I46: PTC Duties | M46: -3786.9723 | O46: -3786.9723 | P46: BSBRAZILTP | Q46: Not Applicable
B47: D8535C00001 | C47: Astra Zeneca | D47: Brazil | E47: Duties | I47: PTC Duties | M47: -13046.734 | O47: -13046.734 | P47: BSBRAZILTP | Q47: Not Applicable
B48: D926QC00001 | C48: Astra Zeneca | D48: Brazil | E48: Duties | I48: PTC Duties | M48: -304.36061 | O48: -304.36061 | P48: BSBRAZILTP | Q48: Not Applicable
B49: 20200041 | C49: Amgen, Inc. | D49: Brazil | E49: Duties | I49: PTC Duties | M49: -2020.4439 | O49: -2020.4439 | P49: BSBRAZILTP | Q49: Not Applicable
B50: D781PC00001 | C50: Astra Zeneca | D50: Brazil | E50: Duties | I50: PTC Duties | M50: -3326.7951 | O50: -3326.7951 | P50: BSBRAZILTP | Q50: Not Applicable
B51: 20230167 | C51: Amgen, Inc. | D51: Brazil | E51: Duties | I51: PTC Duties | M51: -17933.864 | O51: -17933.864 | P51: BSBRAZILTP | Q51: Not Applicable
B52: D516NC00001 | C52: Astra Zeneca | D52: Brazil | E52: Duties | I52: PTC Duties | M52: -1378.2534 | O52: -1378.2534 | P52: BSBRAZILTP | Q52: Not Applicable
B53: D7029C00001 | C53: Astra Zeneca | D53: Brazil | E53: Duties | I53: PTC Duties | M53: -282.23355 | O53: -282.23355 | P53: BSBRAZILTP | Q53: Not Applicable
B54: 20240178 | C54: Amgen, Inc. | D54: Brazil | E54: Duties | I54: PTC Duties | M54: -1592.6469 | O54: -1592.6469 | P54: BSBRAZILTP | Q54: Not Applicable
B55: 20220196 | C55: Amgen, Inc. | D55: Brazil | E55: Duties | I55: PTC Duties | M55: -57156.5 | O55: -57156.5 | P55: BSBRAZILTP | Q55: Not Applicable
B56: 20240236 | C56: Amgen, Inc. | D56: Brazil | E56: Duties | I56: PTC Duties | M56: -101341.14 | O56: -101341.14 | P56: BSBRAZILTP | Q56: Not Applicable
B57: 20240202 | C57: Amgen, Inc. | D57: Brazil | E57: Duties | I57: PTC Duties | M57: -121293.41 | O57: -121293.41 | P57: BSBRAZILTP | Q57: Not Applicable
B58: 20240113 | C58: Amgen, Inc. | D58: Brazil | E58: Duties | I58: PTC Duties | M58: -4109.7782 | O58: -4109.7782 | P58: BSBRAZILTP | Q58: Not Applicable
B59: GRN163LMYF3001 | C59: Geron Corporation | D59: Brazil | E59: Duties | I59: PTC Duties | M59: -10945.41 | O59: -10945.41 | P59: BSBRAZILTP | Q59: Not Applicable
B60: KRT-232-101 | C60: Kartos Therapeutics Inc | D60: Brazil | E60: Duties | I60: PTC Duties | M60: -193.8339 | O60: -193.8339 | P60: BSBRAZILTP | Q60: Not Applicable
B61: LP352-301 | C61: Longboard Pharmaceuticals | D61: Brazil | E61: Duties | I61: PTC Duties | M61: -3539.7063 | O61: -3539.7063 | P61: BSBRAZILTP | Q61: Not Applicable
B62: LP352-302 | C62: Longboard Pharmaceuticals | D62: Brazil | E62: Duties | I62: PTC Duties | M62: -3245.5531 | O62: -3245.5531 | P62: BSBRAZILTP | Q62: Not Applicable
B63: D9640C00003 | C63: MedImmune Inc | D63: Brazil | E63: Duties | I63: PTC Duties | M63: -2324.5528 | O63: -2324.5528 | P63: BSBRAZILTP | Q63: Not Applicable
B64: V940-011 (Local) | C64: Merck Sharp and Dohme LLC | D64: Brazil | E64: Duties | I64: PTC Duties | M64: -251.67887 | O64: -251.67887 | P64: BSBRAZILTP | Q64: Not Applicable
B65: MK-7962-038 (Local) | C65: Merck Sharp and Dohme LLC | D65: Brazil | E65: Duties | I65: PTC Duties | M65: -633.92047 | O65: -633.92047 | P65: BSBRAZILTP | Q65: Not Applicable
B66: MK-8748-003 (Local) | C66: Merck Sharp and Dohme LLC | D66: Brazil | E66: Duties | I66: PTC Duties | M66: -1026.5794 | O66: -1026.5794 | P66: BSBRAZILTP | Q66: Not Applicable
B67: BGB-43395-101 | C67: BeOne | D67: Brazil | E67: Freight | I67: Freight - Returns | M67: -752.97211 | O67: -752.97211 | P67: BSBRAZILTP | Q67: Not Applicable
B68: I8F-MC-GPIJ (CAM) | C68: Eli Lilly & Co. | D68: Brazil | E68: Freight | I68: Freight - Shipments | M68: -191.40751 | O68: -191.40751 | P68: BSBRAZILTP | Q68: Not Applicable
B69: J2A-MC-GZGP (CAM) | C69: Eli Lilly & Co. | D69: Brazil | E69: Freight | I69: Freight - Shipments | M69: -1.3012603 | O69: -1.3012603 | P69: BSBRAZILTP | Q69: Not Applicable
B70: J3L-MC-EZEF (CAM) | C70: Eli Lilly & Co. | D70: Brazil | E70: Freight | I70: Freight - Shipments | M70: -27.056242 | O70: -27.056242 | P70: BSBRAZILTP | Q70: Not Applicable
... B108: XL092-304 | C108: Exelixis, Inc. | D108: Brazil | E108: Freight | I108: Freight - Shipments | M108: -1331.1957 | O108: -1331.1957 | P108: BSBRAZILTP | Q108: Not Applicable
B109: 996 | C109: IQVIA | D109: Brazil | E109: Freight | I109: Freight - Shipments | M109: -1399.7862 | O109: -1399.7862 | P109: BSBRAZILTP | Q109: Not Applicable
B110: 64007957MMY3005 | C110: Janssen | D110: Brazil | E110: Freight | I110: Freight - Shipments | M110: -10850.081 | O110: -10850.081 | P110: BSBRAZILTP | Q110: Not Applicable
B111: 61186372PANSC2001 | C111: Janssen | D111: Brazil | E111: Freight | I111: Freight - Shipments | M111: -95.727079 | O111: -95.727079 | P111: BSBRAZILTP | Q111: Not Applicable
B112: 70033093STR3001 | C112: Janssen | D112: Brazil | E112: Freight | I112: Freight - Shipments | M112: -1033.0873 | O112: -1033.0873 | P112: BSBRAZILTP | Q112: Not Applicable
B113: J2J-MC-JZLH | C113: Eli Lilly & Co. | D113: Brazil | E113: Freight | I113: Freight - Returns | M113: -29344.984 | O113: -29344.984 | P113: BSBRAZILTP | Q113: Not Applicable
B114: MK-3475-D46 | C114: Merck Sharp and Dohme LLC | D114: Brazil | E114: Freight | I114: Freight - Shipments | M114: -1757.8941 | O114: -1757.8941 | P114: BSBRAZILTP | Q114: Not Applicable
B115: 61186372NSC2002 | C115: Janssen | D115: Brazil | E115: Freight | I115: Freight - Shipments | M115: -307.23014 | O115: -307.23014 | P115: BSBRAZILTP | Q115: Not Applicable
B116: GS-US-626-6216 | C116: Gilead Sciences, Inc. | D116: Brazil | E116: Freight | I116: Freight - Shipments | M116: -2458.8287 | O116: -2458.8287 | P116: BSBRAZILTP | Q116: Not Applicable
B117: 64007957MMY3006 | C117: Janssen | D117: Brazil | E117: Freight | I117: Freight - Shipments | M117: -5892.5161 | O117: -5892.5161 | P117: BSBRAZILTP | Q117: Not Applicable
B118: J2N-OX-JZNP | C118: Eli Lilly & Co. | D118: Brazil | E118: Freight | I118: Freight - Returns | M118: -7021.7688 | O118: -7021.7688 | P118: BSBRAZILTP | Q118: Not Applicable
B119: CNTO1959UCO3004 | C119: Janssen | D119: Brazil | E119: Freight | I119: Freight - Shipments | M119: -984.8908 | O119: -984.8908 | P119: BSBRAZILTP | Q119: Not Applicable
B120: 70033093AFL3002 | C120: Janssen | D120: Brazil | E120: Freight | I120: Freight - Shipments | M120: -22981.168 | O120: -22981.168 | P120: BSBRAZILTP | Q120: Not Applicable
B121: Debio 4326-301 | C121: DebioPharm | D121: Brazil | E121: Freight | I121: Freight - Shipments | M121: -726.69116 | O121: -726.69116 | P121: BSBRAZILTP | Q121: Not Applicable
... B271: D3466C00001 | C271: Astra Zeneca | D271: Brazil | E271: Freight | I271: Freight - Shipments | M271: -612.93302 | O271: -612.93302 | P271: BSBRAZILTP | Q271: Not Applicable
B272: 20180244 | C272: Amgen, Inc. | D272: Brazil | E272: Freight | I272: Freight - Shipments | M272: -3088.5542 | O272: -3088.5542 | P272: BSBRAZILTP | Q272: Not Applicable
B273: D7630C00001 | C273: Astra Zeneca | D273: Brazil | E273: Freight | I273: Freight - Shipments | M273: -8352.3967 | O273: -8352.3967 | P273: BSBRAZILTP | Q273: Not Applicable
B274: C4391002 | C274: Pfizer | D274: Brazil | E274: Freight | I274: Freight - Shipments | M274: -2313.8725 | O274: -2313.8725 | P274: BSBRAZILTP | Q274: Not Applicable
B275: 20210004 | C275: Amgen, Inc. | D275: Brazil | E275: Freight | I275: Freight - Shipments | M275: -231.03322 | O275: -231.03322 | P275: BSBRAZILTP | Q275: Not Applicable
B276: TAS-120-205 | C276: Taiho Pharma USA | D276: Brazil | E276: Freight | I276: Freight - Shipments | M276: -289.109 | O276: -289.109 | P276: BSBRAZILTP | Q276: Not Applicable
B277: D8531C00002 | C277: Astra Zeneca | D277: Brazil | E277: Freight | I277: Freight - Shipments | M277: -1700.6443 | O277: -1700.6443 | P277: BSBRAZILTP | Q277: Not Applicable
B278: D5180C00016 | C278: Astra Zeneca | D278: Brazil | E278: Freight | I278: Freight - Shipments | M278: -420.1591 | O278: -420.1591 | P278: BSBRAZILTP | Q278: Not Applicable
B279: C4891002 | C279: Pfizer | D279: Brazil | E279: Freight | I279: Freight - Shipments | M279: -817.80914 | O279: -817.80914 | P279: BSBRAZILTP | Q279: Not Applicable
B280: D8535C00001 | C280: Astra Zeneca | D280: Brazil | E280: Freight | I280: Freight - Shipments | M280: -4306.2387 | O280: -4306.2387 | P280: BSBRAZILTP | Q280: Not Applicable
B281: 20190341 | C281: Amgen, Inc. | D281: Brazil | E281: Freight | I281: Freight - Shipments | M281: -4627.1788 | O281: -4627.1788 | P281: BSBRAZILTP | Q281: Not Applicable
B282: D7632C00001 | C282: Astra Zeneca | D282: Brazil | E282: Freight | I282: Freight - Shipments | M282: -622.99889 | O282: -622.99889 | P282: BSBRAZILTP | Q282: Not Applicable
B283: 20200041 | C283: Amgen, Inc. | D283: Brazil | E283: Freight | I283: Freight - Shipments | M283: -122.3812 | O283: -122.3812 | P283: BSBRAZILTP | Q283: Not Applicable
B284: D361DC00001 | C284: Astra Zeneca | D284: Brazil | E284: Freight | I284: Freight - Shipments | M284: -92.571241 | O284: -92.571241 | P284: BSBRAZILTP | Q284: Not Applicable
B285: 20210081 | C285: Amgen, Inc. | D285: Brazil | E285: Freight | I285: Freight - Shipments | M285: -1477.4267 | O285: -1477.4267 | P285: BSBRAZILTP | Q285: Not Applicable
B286: D6402C00012 | C286: Astra Zeneca | D286: Brazil | E286: Freight | I286: Freight - Shipments | M286: -82.144269 | O286: -82.144269 | P286: BSBRAZILTP | Q286: Not Applicable
B287: C1071032 | C287: Pfizer | D287: Brazil | E287: Freight | I287: Freight - Shipments | M287: -15034.142 | O287: -15034.142 | P287: BSBRAZILTP | Q287: Not Applicable
B288: D781PC00001 | C288: Astra Zeneca | D288: Brazil | E288: Freight | I288: Freight - Shipments | M288: -399.69361 | O288: -399.69361 | P288: BSBRAZILTP | Q288: Not Applicable
B289: D702AC00001 | C289: Astra Zeneca | D289: Brazil | E289: Freight | I289: Freight - Shipments | M289: -60.728967 | O289: -60.728967 | P289: BSBRAZILTP | Q289: Not Applicable
B290: D702BC00001 | C290: Astra Zeneca | D290: Brazil | E290: Freight | I290: Freight - Shipments | M290: -56.622517 | O290: -56.622517 | P290: BSBRAZILTP | Q290: Not Applicable
B291: D516NC00001 | C291: Astra Zeneca | D291: Brazil | E291: Freight | I291: Freight - Shipments | M291: -25.615848 | O291: -25.615848 | P291: BSBRAZILTP | Q291: Not Applicable
B292: D702FC00001 | C292: Astra Zeneca | D292: Brazil | E292: Freight | I292: Freight - Shipments | M292: -280.76179 | O292: -280.76179 | P292: BSBRAZILTP | Q292: Not Applicable
B293: C2321014 | C293: Pfizer | D293: Brazil | E293: Freight | I293: Freight - Shipments | M293: -3107.6308 | O293: -3107.6308 | P293: BSBRAZILTP | Q293: Not Applicable
B294: C2321003 | C294: Pfizer | D294: Brazil | E294: Freight | I294: Freight - Shipments | M294: -20869.899 | O294: -20869.899 | P294: BSBRAZILTP | Q294: Not Applicable
B295: 20240092 | C295: Amgen, Inc. | D295: Brazil | E295: Freight | I295: Freight - Shipments | M295: -84.123504 | O295: -84.123504 | P295: BSBRAZILTP | Q295: Not Applicable
B296: D7029C00001 | C296: Astra Zeneca | D296: Brazil | E296: Freight | I296: Freight - Shipments | M296: -39.080434 | O296: -39.080434 | P296: BSBRAZILTP | Q296: Not Applicable
B297: C5751003 | C297: Pfizer | D297: Brazil | E297: Freight | I297: Freight - Shipments | M297: -3607.9509 | O297: -3607.9509 | P297: BSBRAZILTP | Q297: Not Applicable
B298: D7960C00012 | C298: Astra Zeneca | D298: Brazil | E298: Freight | I298: Freight - Shipments | M298: -164.08265 | O298: -164.08265 | P298: BSBRAZILTP | Q298: Not Applicable
B299: D702GC00001 | C299: Astra Zeneca | D299: Brazil | E299: Freight | I299: Freight - Shipments | M299: -2628.0939 | O299: -2628.0939 | P299: BSBRAZILTP | Q299: Not Applicable
B300: C4391024 | C300: Pfizer | D300: Brazil | E300: Freight | I300: Freight - Shipments | M300: -27701.781 | O300: -27701.781 | P300: BSBRAZILTP | Q300: Not Applicable
B301: 20240178 | C301: Amgen, Inc. | D301: Brazil | E301: Freight | I301: Freight - Shipments | M301: -103.07944 | O301: -103.07944 | P301: BSBRAZILTP | Q301: Not Applicable
B302: D7960C00015 | C302: Astra Zeneca | D302: Brazil | E302: Freight | I302: Freight - Shipments | M302: -694.7001 | O302: -694.7001 | P302: BSBRAZILTP | Q302: Not Applicable
B303: 20220196 | C303: Amgen, Inc. | D303: Brazil | E303: Freight | I303: Freight - Shipments | M303: -32516.981 | O303: -32516.981 | P303: BSBRAZILTP | Q303: Not Applicable
B304: 20230227 | C304: Amgen, Inc. | D304: Brazil | E304: Freight | I304: Freight - Shipments | M304: -1184.0158 | O304: -1184.0158 | P304: BSBRAZILTP | Q304: Not Applicable
B305: 20230225 | C305: Amgen, Inc. | D305: Brazil | E305: Freight | I305: Freight - Shipments | M305: -400.2992 | O305: -400.2992 | P305: BSBRAZILTP | Q305: Not Applicable
B306: D702NC00001 | C306: Astra Zeneca | D306: Brazil | E306: Freight | I306: Freight - Shipments | M306: -91.179906 | O306: -91.179906 | P306: BSBRAZILTP | Q306: Not Applicable
B307: D7700C00003 | C307: MedImmune Inc | D307: Brazil | E307: Freight | I307: Freight - Shipments | M307: -11.857715 | O307: -11.857715 | P307: BSBRAZILTP | Q307: Not Applicable
B308: GRN163LMYF3001 | C308: Geron Corporation | D308: Brazil | E308: Freight | I308: Freight - Shipments | M308: -1850.0126 | O308: -1850.0126 | P308: BSBRAZILTP | Q308: Not Applicable
B309: GS-US-528-9023 | C309: Gilead Sciences, Inc. | D309: Brazil | E309: Freight | I309: Freight - Returns | M309: -416.04944 | O309: -416.04944 | P309: BSBRAZILTP | Q309: Not Applicable
B310: KRT-232-101 | C310: Kartos Therapeutics Inc | D310: Brazil | E310: Freight | I310: Freight - Shipments | M310: -1.7315287 | O310: -1.7315287 | P310: BSBRAZILTP | Q310: Not Applicable
B311: ALXN1720-MG-301 | C311: Alexion Pharmaceuticals Inc | D311: Brazil | E311: Freight | I311: Freight - Shipments | M311: -117.62493 | O311: -117.62493 | P311: BSBRAZILTP | Q311: Not Applicable
B312: RYZ101-301 | C312: RayzeBio Inc | D312: Brazil | E312: Freight | I312: Freight - Shipments | M312: -506.76449 | O312: -506.76449 | P312: BSBRAZILTP | Q312: Not Applicable
B313: CY 6022 | C313: Cytokinetics Incorporated | D313: Brazil | E313: Freight | I313: Freight - Shipments | M313: -67.388878 | O313: -67.388878 | P313: BSBRAZILTP | Q313: Not Applicable
...

Sheet Bra
A1: Vacio | B1: Protocol | C1: Element 4 short name | D1: Allentown / Argentina | E1: Custom 2 | H1: Vacio | I1: Line description | J1: YYYY | K1: MM | L1: CURRENCY | M1: 40 % (sin hadling) | O1: 40 % (sin hadling) | P1: Vacio | Q1: Not Applicable (solo para Allentown) | R1: Vacio | S1: Vacio | Y1: LocalAdj- Duties | Z1: ICO+NONICO
A2: grpcode | B2: el4 | C2: el4_name | D2: el4_sname | E2: name | F2: el2 | G2: el2_name | H2: el3 | I2: el3_name | J2: yr | K2: period | L2: curcode | M2: LOC AMT | N2: Rate | O2: USD AMT | P2: cmpcode | Q2: Discount Flag | R2: _ | S2: x
B3: Transfer Pricing | C3: Allentown | D3: Allentown | E3: Distribution | F3: 40700 | G3: Revenues - Third Parties | I3: Transfer Pricing | J3: 2026 | K3: 5 | L3: USD | M3: 1115806.2 | O3: 1115806.2 | P3: BSBrazilUSD | Q3: Not Applicable
B4: Transfer Pricing | C4: Allentown | D4: Allentown | E4: Duties | F4: 40700 | G4: Revenues - Third Parties | I4: Transfer Pricing | J4: 2026 | K4: 5 | L4: USD | M4: 1529489.2 | O4: 1529489.2 | P4: BSBrazilUSD | Q4: Not Applicable
B5: Transfer Pricing | C5: Allentown | D5: Allentown | E5: Freight | F5: 40700 | G5: Revenues - Third Parties | I5: Transfer Pricing | J5: 2026 | K5: 5 | L5: USD | M5: 1727743 | O5: 1727743 | P5: BSBrazilUSD | Q5: Not Applicable
B6: Transfer Pricing | C6: Allentown | D6: Allentown | E6: Packaging | F6: 40700 | G6: Revenues - Third Parties | I6: Transfer Pricing | J6: 2026 | K6: 5 | L6: USD | M6: 15291.33 | O6: 15291.33 | P6: BSBrazilUSD | Q6: Not Applicable
B7: Transfer Pricing | C7: Allentown | D7: Allentown | E7: Returns and Destructions | F7: 40700 | G7: Revenues - Third Parties | I7: Transfer Pricing | J7: 2026 | K7: 5 | L7: USD | M7: 97572.4 | O7: 97572.4 | P7: BSBrazilUSD | Q7: Not Applicable | AD7: 615737
B8: Transfer Pricing | C8: Allentown | D8: Allentown | E8: Storage | F8: 40700 | G8: Revenues - Third Parties | I8: Transfer Pricing | J8: 2026 | K8: 5 | L8: USD | M8: 533585.46 | O8: 533585.46 | P8: BSBrazilUSD | Q8: Not Applicable | AD8: 626211
B9: BGB-43395-101 | C9: BeOne | D9: Brazil | E9: Freight | I9: Freight - Returns | K9: 5 | M9: 1755.0773 | O9: 1755.0773 | P9: BSBrazilUSD | AD9: =+AD8+AD7 -> 1241948
B10: BGB-43395-101 | C10: BeOne | D10: Brazil | E10: Freight | I10: Freight - Shipments | K10: 5 | M10: 2814.7656 | O10: 2814.7656 | P10: BSBrazilUSD
B11: BGB-43395-101 | C11: BeOne | D11: Brazil | E11: Distribution | I11: Insulated shipper - Credo S22 - 12L (Leasing) | K11: 5 | M11: 174.59476 | O11: 174.59476 | P11: BSBrazilUSD
B12: BGB-43395-101 | C12: BeOne | D12: Brazil | E12: Distribution | I12: Pick and Pack (Controlled Ambient) | K12: 5 | M12: 415.52753 | O12: 415.52753 | P12: BSBrazilUSD
B13: BGB-43395-101 | C13: BeOne | D13: Brazil | E13: Distribution | I13: Project Management Fee | K13: 5 | M13: 986.90039 | O13: 986.90039 | P13: BSBrazilUSD
B14: BGB-43395-101 | C14: BeOne | D14: Brazil | E14: Returns and Destructions | I14: Reconciliation of Returns (per Hour) | K14: 5 | M14: 277.03169 | O14: 277.03169 | P14: BSBrazilUSD
B15: BGB-43395-101 | C15: BeOne | D15: Brazil | E15: Returns and Destructions | I15: Returns Receipt (per Receipt) | K15: 5 | M15: 692.57922 | O15: 692.57922 | P15: BSBrazilUSD
B16: BGB-43395-101 | C16: BeOne | D16: Brazil | E16: Storage | I16: Storage Ambient (per Shelf) | K16: 5 | M16: 2960.9112 | O16: 2960.9112 | P16: BSBrazilUSD
B17: BGB-43395-101 | C17: BeOne | D17: Brazil | E17: Storage | I17: Storage of Returns (per Pallet) | K17: 5 | M17: 1113.8066 | O17: 1113.8066 | P17: BSBrazilUSD
B18: BGB-43395-101 | C18: BeOne | D18: Brazil | E18: Distribution | I18: Temperature Monitoring Device (Ambient) | K18: 5 | M18: 77.597672 | O18: 77.597672 | P18: BSBrazilUSD
B19: BGB-Retain sample storage | C19: BeOne | D19: Brazil | E19: Storage | I19: Storage Ambient (per Shelf) | K19: 5 | M19: 528.73414 | O19: 528.73414 | P19: BSBrazilUSD
B20: BGB-58067-101 | C20: BeOne | D20: Brazil | E20: Distribution | I20: Project Management Fee | K20: 5 | M20: 888.21335 | O20: 888.21335 | P20: BSBrazilUSD
B21: BGB-58067-101 | C21: BeOne | D21: Brazil | E21: Storage | I21: Storage Ambient (per Shelf) | K21: 5 | M21: 317.24048 | O21: 317.24048 | P21: BSBrazilUSD
B22: BGB-58067-101 | C22: BeOne | D22: Brazil | E22: Storage | I22: Storage Refrigerated (per Shelf) | K22: 5 | M22: 444.10668 | O22: 444.10668 | P22: BSBrazilUSD
B23: D3251C00014 Returns and Destruction | C23: Astra Zeneca | D23: Brazil | E23: Storage | I23: Storage of Returns (per Pallet) | M23: 472.11275 | O23: 472.11275 | P23: BSBrazilUSD
B24: D9185C00001 Returns and Destruction | C24: Astra Zeneca | D24: Brazil | E24: Freight | I24: Freight - Returns | M24: 719.93938 | O24: 719.93938 | P24: BSBrazilUSD
B25: D9185C00001 Returns and Destruction | C25: Astra Zeneca | D25: Brazil | E25: Storage | I25: Storage of Returns (per Pallet) | M25: 343.01 | O25: 343.01 | P25: BSBrazilUSD
B26: D5244C00001 Returns and Destruction | C26: Astra Zeneca | D26: Brazil | E26: Storage | I26: Storage of Returns (per Pallet) | M26: 366.81992 | O26: 366.81992 | P26: BSBrazilUSD
B27: D9180C00012 Returns and Destruction | C27: Astra Zeneca | D27: Brazil | E27: Freight | I27: Freight - Returns | M27: 122.72101 | O27: 122.72101 | P27: BSBrazilUSD
B28: D9180C00012 Returns and Destruction | C28: Astra Zeneca | D28: Brazil | E28: Returns and Destructions | I28: Returns Receipt (per Receipt) | M28: 195.91208 | O28: 195.91208 | P28: BSBrazilUSD
B29: D9180C00012 Returns and Destruction | C29: Astra Zeneca | D29: Brazil | E29: Storage | I29: Storage of Returns (per Pallet) | M29: 240.70094 | O29: 240.70094 | P29: BSBrazilUSD
B30: D6972C00003 Returns and Destruction | C30: Astra Zeneca | D30: Brazil | E30: Storage | I30: Storage of Returns (per Pallet) | M30: 240.70094 | O30: 240.70094 | P30: BSBrazilUSD
B31: D6402C00012 Returns and Destruction | C31: Astra Zeneca | D31: Brazil | E31: Returns and Destructions | I31: Returns Receipt (per Receipt) | M31: 181.85976 | O31: 181.85976 | P31: BSBrazilUSD
B32: D6402C00012 Returns and Destruction | C32: Astra Zeneca | D32: Brazil | E32: Storage | I32: Storage of Returns (per Pallet) | M32: 183.40996 | O32: 183.40996 | P32: BSBrazilUSD
B33: D9180C00008 Returns and Destruction | C33: Astra Zeneca | D33: Brazil | E33: Storage | I33: Storage of Returns (per Pallet) | M33: 453.97282 | O33: 453.97282 | P33: BSBrazilUSD
B34: D9180C00004 Returns and Destruction | C34: Astra Zeneca | D34: Brazil | E34: Storage | I34: Storage of Returns (per Pallet) | M34: 366.81992 | O34: 366.81992 | P34: BSBrazilUSD
... B551: D926NC00001 | C551: Astra Zeneca | D551: Brazil | E551: Duties | I551: PTC Duties | M551: -2135.4768 | O551: -2135.4768 | P551: BSBrazilUSD
B552: 20190360 | C552: Amgen, Inc. | D552: Brazil | E552: Duties | I552: PTC Duties | M552: -2931.5887 | O552: -2931.5887 | P552: BSBrazilUSD
B553: D7020C00001 | C553: MedImmune Inc | D553: Brazil | E553: Duties | I553: PTC Duties | M553: -3111.9661 | O553: -3111.9661 | P553: BSBrazilUSD
B554: D3466C00001 | C554: Astra Zeneca | D554: Brazil | E554: Duties | I554: PTC Duties | M554: -1427.867 | O554: -1427.867 | P554: BSBrazilUSD
B555: Temperature Monitor-Global Pooling | C555: Astra Zeneca | D555: Brazil | E555: Duties | I555: PTC Duties | M555: -5680.4585 | O555: -5680.4585 | P555: BSBrazilUSD
B556: D8535C00001 | C556: Astra Zeneca | D556: Brazil | E556: Duties | I556: PTC Duties | M556: -19570.1 | O556: -19570.1 | P556: BSBrazilUSD
B557: D926QC00001 | C557: Astra Zeneca | D557: Brazil | E557: Duties | I557: PTC Duties | M557: -456.54091 | O557: -456.54091 | P557: BSBrazilUSD
B558: 20200041 | C558: Amgen, Inc. | D558: Brazil | E558: Duties | I558: PTC Duties | M558: -3030.6658 | O558: -3030.6658 | P558: BSBrazilUSD
B559: D781PC00001 | C559: Astra Zeneca | D559: Brazil | E559: Duties | I559: PTC Duties | M559: -4990.1926 | O559: -4990.1926 | P559: BSBrazilUSD
B560: 20230167 | C560: Amgen, Inc. | D560: Brazil | E560: Duties | I560: PTC Duties | M560: -26900.797 | O560: -26900.797 | P560: BSBrazilUSD
B561: D516NC00001 | C561: Astra Zeneca | D561: Brazil | E561: Duties | I561: PTC Duties | M561: -2067.3801 | O561: -2067.3801 | P561: BSBrazilUSD
B562: D7029C00001 | C562: Astra Zeneca | D562: Brazil | E562: Duties | I562: PTC Duties | M562: -423.35033 | O562: -423.35033 | P562: BSBrazilUSD
B563: 20240178 | C563: Amgen, Inc. | D563: Brazil | E563: Duties | I563: PTC Duties | M563: -2388.9704 | O563: -2388.9704 | P563: BSBrazilUSD
B564: 20220196 | C564: Amgen, Inc. | D564: Brazil | E564: Duties | I564: PTC Duties | M564: -85734.751 | O564: -85734.751 | P564: BSBrazilUSD
B565: 20240236 | C565: Amgen, Inc. | D565: Brazil | E565: Duties | I565: PTC Duties | M565: -152011.71 | O565: -152011.71 | P565: BSBrazilUSD
B566: 20240202 | C566: Amgen, Inc. | D566: Brazil | E566: Duties | I566: PTC Duties | M566: -181940.11 | O566: -181940.11 | P566: BSBrazilUSD
B567: 20240113 | C567: Amgen, Inc. | D567: Brazil | E567: Duties | I567: PTC Duties | M567: -6164.6673 | O567: -6164.6673 | P567: BSBrazilUSD
B568: GRN163LMYF3001 | C568: Geron Corporation | D568: Brazil | E568: Duties | I568: PTC Duties | M568: -16418.114 | O568: -16418.114 | P568: BSBrazilUSD
B569: KRT-232-101 | C569: Kartos Therapeutics Inc | D569: Brazil | E569: Duties | I569: PTC Duties | M569: -290.75086 | O569: -290.75086 | P569: BSBrazilUSD
B570: LP352-301 | C570: Longboard Pharmaceuticals | D570: Brazil | E570: Duties | I570: PTC Duties | M570: -5309.5595 | O570: -5309.5595 | P570: BSBrazilUSD
B571: LP352-302 | C571: Longboard Pharmaceuticals | D571: Brazil | E571: Duties | I571: PTC Duties | M571: -4868.3297 | O571: -4868.3297 | P571: BSBrazilUSD
B572: D9640C00003 | C572: MedImmune Inc | D572: Brazil | E572: Duties | I572: PTC Duties | M572: -3486.8292 | O572: -3486.8292 | P572: BSBrazilUSD
B573: V940-011 (Local) | C573: Merck Sharp and Dohme LLC | D573: Brazil | E573: Duties | I573: PTC Duties | M573: -377.5183 | O573: -377.5183 | P573: BSBrazilUSD
B574: MK-7962-038 (Local) | C574: Merck Sharp and Dohme LLC | D574: Brazil | E574: Duties | I574: PTC Duties | M574: -950.8807 | O574: -950.8807 | P574: BSBrazilUSD
B575: MK-8748-003 (Local) | C575: Merck Sharp and Dohme LLC | D575: Brazil | E575: Duties | I575: PTC Duties | M575: -1539.8691 | O575: -1539.8691 | P575: BSBrazilUSD
B576: BGB-43395-101 | C576: BeOne | D576: Brazil | E576: Freight | I576: Freight - Returns | M576: -1129.4582 | O576: -1129.4582 | P576: BSBrazilUSD
B577: I8F-MC-GPIJ (CAM) | C577: Eli Lilly & Co. | D577: Brazil | E577: Freight | I577: Freight - Shipments | M577: -287.11127 | O577: -287.11127 | P577: BSBrazilUSD
B578: J2A-MC-GZGP (CAM) | C578: Eli Lilly & Co. | D578: Brazil | E578: Freight | I578: Freight - Shipments | M578: -1.9518905 | O578: -1.9518905 | P578: BSBrazilUSD
B579: J3L-MC-EZEF (CAM) | C579: Eli Lilly & Co. | D579: Brazil | E579: Freight | I579: Freight - Shipments | M579: -40.584363 | O579: -40.584363 | P579: BSBrazilUSD
... B617: XL092-304 | C617: Exelixis, Inc. | D617: Brazil | E617: Freight | I617: Freight - Shipments | M617: -1996.7936 | O617: -1996.7936 | P617: BSBrazilUSD
B618: 996 | C618: IQVIA | D618: Brazil | E618: Freight | I618: Freight - Shipments | M618: -2099.6792 | O618: -2099.6792 | P618: BSBrazilUSD
B619: 64007957MMY3005 | C619: Janssen | D619: Brazil | E619: Freight | I619: Freight - Shipments | M619: -16275.121 | O619: -16275.121 | P619: BSBrazilUSD
B620: 61186372PANSC2001 | C620: Janssen | D620: Brazil | E620: Freight | I620: Freight - Shipments | M620: -143.59062 | O620: -143.59062 | P620: BSBrazilUSD
B621: 70033093STR3001 | C621: Janssen | D621: Brazil | E621: Freight | I621: Freight - Shipments | M621: -1549.6309 | O621: -1549.6309 | P621: BSBrazilUSD
B622: J2J-MC-JZLH | C622: Eli Lilly & Co. | D622: Brazil | E622: Freight | I622: Freight - Returns | M622: -44017.477 | O622: -44017.477 | P622: BSBrazilUSD
B623: MK-3475-D46 | C623: Merck Sharp and Dohme LLC | D623: Brazil | E623: Freight | I623: Freight - Shipments | M623: -2636.8412 | O623: -2636.8412 | P623: BSBrazilUSD
B624: 61186372NSC2002 | C624: Janssen | D624: Brazil | E624: Freight | I624: Freight - Shipments | M624: -460.8452 | O624: -460.8452 | P624: BSBrazilUSD
B625: GS-US-626-6216 | C625: Gilead Sciences, Inc. | D625: Brazil | E625: Freight | I625: Freight - Shipments | M625: -3688.243 | O625: -3688.243 | P625: BSBrazilUSD
B626: 64007957MMY3006 | C626: Janssen | D626: Brazil | E626: Freight | I626: Freight - Shipments | M626: -8838.7741 | O626: -8838.7741 | P626: BSBrazilUSD
B627: J2N-OX-JZNP | C627: Eli Lilly & Co. | D627: Brazil | E627: Freight | I627: Freight - Returns | M627: -10532.653 | O627: -10532.653 | P627: BSBrazilUSD
B628: CNTO1959UCO3004 | C628: Janssen | D628: Brazil | E628: Freight | I628: Freight - Shipments | M628: -1477.3362 | O628: -1477.3362 | P628: BSBrazilUSD
B629: 70033093AFL3002 | C629: Janssen | D629: Brazil | E629: Freight | I629: Freight - Shipments | M629: -34471.753 | O629: -34471.753 | P629: BSBrazilUSD
B630: Debio 4326-301 | C630: DebioPharm | D630: Brazil | E630: Freight | I630: Freight - Shipments | M630: -1090.0367 | O630: -1090.0367 | P630: BSBrazilUSD
... B780: D3466C00001 | C780: Astra Zeneca | D780: Brazil | E780: Freight | I780: Freight - Shipments | M780: -919.39953 | O780: -919.39953 | P780: BSBrazilUSD
B781: 20180244 | C781: Amgen, Inc. | D781: Brazil | E781: Freight | I781: Freight - Shipments | M781: -4632.8314 | O781: -4632.8314 | P781: BSBrazilUSD
B782: D7630C00001 | C782: Astra Zeneca | D782: Brazil | E782: Freight | I782: Freight - Shipments | M782: -12528.595 | O782: -12528.595 | P782: BSBrazilUSD
B783: C4391002 | C783: Pfizer | D783: Brazil | E783: Freight | I783: Freight - Shipments | M783: -3470.8087 | O783: -3470.8087 | P783: BSBrazilUSD
B784: 20210004 | C784: Amgen, Inc. | D784: Brazil | E784: Freight | I784: Freight - Shipments | M784: -346.54983 | O784: -346.54983 | P784: BSBrazilUSD
B785: TAS-120-205 | C785: Taiho Pharma USA | D785: Brazil | E785: Freight | I785: Freight - Shipments | M785: -433.6635 | O785: -433.6635 | P785: BSBrazilUSD
B786: D8531C00002 | C786: Astra Zeneca | D786: Brazil | E786: Freight | I786: Freight - Shipments | M786: -2550.9664 | O786: -2550.9664 | P786: BSBrazilUSD
B787: D5180C00016 | C787: Astra Zeneca | D787: Brazil | E787: Freight | I787: Freight - Shipments | M787: -630.23865 | O787: -630.23865 | P787: BSBrazilUSD
B788: C4891002 | C788: Pfizer | D788: Brazil | E788: Freight | I788: Freight - Shipments | M788: -1226.7137 | O788: -1226.7137 | P788: BSBrazilUSD
B789: D8535C00001 | C789: Astra Zeneca | D789: Brazil | E789: Freight | I789: Freight - Shipments | M789: -6459.3581 | O789: -6459.3581 | P789: BSBrazilUSD
B790: 20190341 | C790: Amgen, Inc. | D790: Brazil | E790: Freight | I790: Freight - Shipments | M790: -6940.7681 | O790: -6940.7681 | P790: BSBrazilUSD
B791: D7632C00001 | C791: Astra Zeneca | D791: Brazil | E791: Freight | I791: Freight - Shipments | M791: -934.49833 | O791: -934.49833 | P791: BSBrazilUSD
B792: 20200041 | C792: Amgen, Inc. | D792: Brazil | E792: Freight | I792: Freight - Shipments | M792: -183.5718 | O792: -183.5718 | P792: BSBrazilUSD
B793: D361DC00001 | C793: Astra Zeneca | D793: Brazil | E793: Freight | I793: Freight - Shipments | M793: -138.85686 | O793: -138.85686 | P793: BSBrazilUSD
B794: 20210081 | C794: Amgen, Inc. | D794: Brazil | E794: Freight | I794: Freight - Shipments | M794: -2216.14 | O794: -2216.14 | P794: BSBrazilUSD
B795: D6402C00012 | C795: Astra Zeneca | D795: Brazil | E795: Freight | I795: Freight - Shipments | M795: -123.2164 | O795: -123.2164 | P795: BSBrazilUSD
B796: C1071032 | C796: Pfizer | D796: Brazil | E796: Freight | I796: Freight - Shipments | M796: -22551.213 | O796: -22551.213 | P796: BSBrazilUSD
B797: D781PC00001 | C797: Astra Zeneca | D797: Brazil | E797: Freight | I797: Freight - Shipments | M797: -599.54041 | O797: -599.54041 | P797: BSBrazilUSD
B798: D702AC00001 | C798: Astra Zeneca | D798: Brazil | E798: Freight | I798: Freight - Shipments | M798: -91.09345 | O798: -91.09345 | P798: BSBrazilUSD
B799: D702BC00001 | C799: Astra Zeneca | D799: Brazil | E799: Freight | I799: Freight - Shipments | M799: -84.933776 | O799: -84.933776 | P799: BSBrazilUSD
B800: D516NC00001 | C800: Astra Zeneca | D800: Brazil | E800: Freight | I800: Freight - Shipments | M800: -38.423772 | O800: -38.423772 | P800: BSBrazilUSD
B801: D702FC00001 | C801: Astra Zeneca | D801: Brazil | E801: Freight | I801: Freight - Shipments | M801: -421.14269 | O801: -421.14269 | P801: BSBrazilUSD
B802: C2321014 | C802: Pfizer | D802: Brazil | E802: Freight | I802: Freight - Shipments | M802: -4661.4462 | O802: -4661.4462 | P802: BSBrazilUSD
...

Sheet Mex 
A1: Vacio | B1: Protocol | C1: Element 4 short name | D1: Allentown / Argentina | E1: Custom 2 | H1: Vacio | I1: Line description | J1: YYYY | K1: MM | L1: CURRENCY | M1: 40 % (sin hadling) | O1: 40 % (sin hadling) | P1: Vacio | Q1: Not Applicable (solo para Allentown) | R1: Vacio | S1: Vacio
A2: grpcode | B2: el4 | C2: el4_name | D2: el4_sname | E2: name | F2: el2 | G2: el2_name | H2: el3 | I2: el3_name | J2: yr | K2: period | L2: curcode | M2: LOC AMT | N2: Rate | O2: USD AMT | P2: cmpcode | Q2: Discount Flag | R2: _ | S2: x
B3: Transfer Pricing | C3: Allentown | D3: Allentown | E3: Distribution | F3: 40700 | G3: Revenues - Third Parties | I3: Transfer Pricing | J3: 2026 | K3: 5 | L3: USD | M3: 173964.22 | O3: 173964.22 | P3: BSMexico | Q3: Not Applicable
B4: Transfer Pricing | C4: Allentown | D4: Allentown | E4: Duties | F4: 40700 | G4: Revenues - Third Parties | I4: Transfer Pricing | J4: 2026 | K4: 5 | L4: USD | M4: 12575.77 | O4: 12575.77 | P4: BSMexico | Q4: Not Applicable
B5: Transfer Pricing | C5: Allentown | D5: Allentown | E5: Freight | F5: 40700 | G5: Revenues - Third Parties | I5: Transfer Pricing | J5: 2026 | K5: 5 | L5: USD | M5: 88926.07 | O5: 88926.07 | P5: BSMexico | Q5: Not Applicable
B6: Transfer Pricing | C6: Allentown | D6: Allentown | E6: Packaging | F6: 40700 | G6: Revenues - Third Parties | I6: Transfer Pricing | J6: 2026 | K6: 5 | L6: USD | M6: 69.77 | O6: 69.77 | P6: BSMexico | Q6: Not Applicable
B7: Transfer Pricing | C7: Allentown | D7: Allentown | E7: Returns and Destructions | F7: 40700 | G7: Revenues - Third Parties | I7: Transfer Pricing | J7: 2026 | K7: 5 | L7: USD | M7: 14716.71 | O7: 14716.71 | P7: BSMexico | Q7: Not Applicable
B8: Transfer Pricing | C8: Allentown | D8: Allentown | E8: Storage | F8: 40700 | G8: Revenues - Third Parties | I8: Transfer Pricing | J8: 2026 | K8: 5 | L8: USD | M8: 115435.91 | O8: 115435.91 | P8: BSMexico | Q8: Not Applicable
B9: 20307 | C9: Bayer AG (No consolidate) | D9: Mexico | E9: Storage | I9: Storage Samples (per Shelf) | J9: 2026 | K9: 5 | L9: USD | M9: 201.26 | O9: 201.26 | P9: BSMexico
B10: IMP21500 | C10: Bayer AG (No consolidate) | D10: Mexico | E10: Distribution | I10: Project Management Fee | J10: 2026 | K10: 5 | L10: USD | M10: 385.4 | O10: 385.4 | P10: BSMexico
B11: IMP21500 | C11: Bayer AG (No consolidate) | D11: Mexico | E11: Storage | I11: Storage Samples (per Shelf) | J11: 2026 | K11: 5 | L11: USD | M11: 201.26 | O11: 201.26 | P11: BSMexico
B12: IMP22518 | C12: Bayer AG (No consolidate) | D12: Mexico | E12: Storage | I12: Storage Samples (per Shelf) | J12: 2026 | K12: 5 | L12: USD | M12: 201.26 | O12: 201.26 | P12: BSMexico
B13: IMP22518 | C13: Bayer AG (No consolidate) | D13: Mexico | E13: Returns and Destructions | I13: Destruction (per Kg) | J13: 2026 | K13: 5 | L13: USD | M13: 55.02 | O13: 55.02 | P13: BSMexico
B14: IMP22518 | C14: Bayer AG (No consolidate) | D14: Mexico | E14: Returns and Destructions | I14: Destruction Setup Fee | J14: 2026 | K14: 5 | L14: USD | M14: 384.22 | O14: 384.22 | P14: BSMexico
B15: IMP22518 | C15: Bayer AG (No consolidate) | D15: Mexico | E15: Distribution | I15: Project Management Fee | J15: 2026 | K15: 5 | L15: USD | M15: 469.16 | O15: 469.16 | P15: BSMexico
B16: IMP22518 | C16: Bayer AG (No consolidate) | D16: Mexico | E16: Storage | I16: Storage Ambient (per Shelf) | J16: 2026 | K16: 5 | L16: USD | M16: 142.3 | O16: 142.3 | P16: BSMexico
B17: IMP22518 | C17: Bayer AG (No consolidate) | D17: Mexico | E17: Storage | I17: Storage of Labels Ambient (per Shelf) | J17: 2026 | K17: 5 | L17: USD | M17: 71.15 | O17: 71.15 | P17: BSMexico
B18: Lilly Admin and one-time costs | C18: Eli Lilly & Co. | D18: Mexico | E18: Distribution | I18: Administrative fee | J18: 2026 | K18: 5 | L18: USD | M18: 12264.781 | O18: 12264.781 | P18: BSMexico
B19: Lilly Admin and one-time costs | C19: Eli Lilly & Co. | D19: Mexico | E19: Storage | I19: Non-Drug Storage Ambient (per Pallet) | J19: 2026 | K19: 5 | L19: USD | M19: 6878.1354 | O19: 6878.1354 | P19: BSMexico
B20: Lilly Admin and one-time costs | C20: Eli Lilly & Co. | D20: Mexico | E20: Distribution | I20: Receipt fee Ancillaries (per Receipt_ID) | J20: 2026 | K20: 5 | L20: USD | M20: 98.1212 | O20: 98.1212 | P20: BSMexico
B21: Lilly Admin and one-time costs | C21: Eli Lilly & Co. | D21: Mexico | E21: Storage | I21: Storage Ambient (per Shelf) | J21: 2026 | K21: 5 | L21: USD | M21: 14258.283 | O21: 14258.283 | P21: BSMexico
... B455: Others | C455: Others | D455: Mexico | E455: Distribution | I455: Others | J455: 2026 | K455: 5 | L455: USD | M455: 355966.5 | O455: 355966.5 | P455: BSMexico
B456: Others | C456: Others | D456: Mexico | E456: Duties | I456: Others | J456: 2026 | K456: 5 | L456: USD | M456: 116128.3 | O456: =116128.3227405+K472 -> 116128.3 | P456: BSMexico
B457: Others | C457: Others | D457: Mexico | E457: Freight | I457: Others | J457: 2026 | K457: 5 | L457: USD | M457: 437311.7 | O457: 437311.7 | P457: BSMexico
B458: Others | C458: Others | D458: Mexico | E458: Packaging | I458: Others | J458: 2026 | K458: 5 | L458: USD | M458: 0.23 | O458: 0.23 | P458: BSMexico
B459: Others | C459: Others | D459: Mexico | E459: Returns and Destructions | I459: Others | J459: 2026 | K459: 5 | L459: USD | M459: 49455.172 | O459: 49455.172 | P459: BSMexico
B460: Others | C460: Others | D460: Mexico | E460: ClinicalSvcsOther | I460: Others | J460: 2026 | K460: 5 | L460: USD | M460: 0 | O460: 0 | P460: BSMexico
M461: =SUM(M2:M460) -> 1499254 | N461: =SUM(N2:N460) -> 0 | O461: =SUM(O2:O460) -> 1499254
G466: Row Labels | H466: Sum of USD AMT
G467: ClinicalSvcsOther | H467: 0 | I467: 70 | J467: Packaging | K467: =+I467-GETPIVOTDATA("USD AMT",$G$466,"name","Packaging") -> 0
G468: Comparator | H468: 64909 | I468: 264052 | J468: Storage | K468: =+I468-GETPIVOTDATA("USD AMT",$G$466,"name","Storage") -> 0
G469: Distribution | H469: 306865 | I469: 306865 | J469: Distributing | K469: =+I469-GETPIVOTDATA("USD AMT",$G$466,"name","Distribution") -> 0
G470: Duties | H470: 74462.023 | I470: 733893 | J470: Freight | K470: =+I470-GETPIVOTDATA("USD AMT",$G$466,"name","Freight") -> 0
G471: Freight | H471: 733893 | I471: 55003 | J471: ReturnDrug | K471: =+I471-GETPIVOTDATA("USD AMT",$G$466,"name","Returns and Destructions") -> 0
G472: Packaging | H472: 70 | I472: 74462 | J472: BSDDuty | K472: =+I472-GETPIVOTDATA("USD AMT",$G$466,"name","Duties") -> -0.022674
G473: Returns and Destructions | H473: 55003 | I473: 0 | J473: ClinicalSvcsOther | K473: =+I473-GETPIVOTDATA("USD AMT",$G$466,"name","ClinicalSvcsOther") -> 0
G474: Storage | H474: 264052 | I474: 64909 | J474: Comparator | K474: =+I474-GETPIVOTDATA("USD AMT",$G$466,"name","Comparator") -> 0
G475: Grand Total | H475: 1499254 | J475: CAM

Sheet Arg (2)
A1: BuscarV de selectable table | B1: FB Invoice | C1: Fisher reference | D1: Protocol | E1: Año | F1: Mes del año en numero | G1: Category en FB BuscarV de selectable table | H1: Service | I1: Invoiced | J1: currency | K1: convertir el valor a BS USD RATE | L1: Site | M1: Solo PO | N1: blank | O1: Sponsor tal cual FB | P1: mismo columna K | Q1: fecha emision de facturacion | W1: Ex. Rates | X1: BS
A2: CUSTOMER | B2: INVOICE_. | C2: FISHER_JOB | D2: PROTOCOL | E2: yr | F2: period | G2: PRODUCT | H2: SUB-PRODUCT | I2: DocValue | J2: DOC_CURRENCY | K2: USD Value | L2: FISHER_LOC | M2: PO. | N2: doccode | O2: el4_name | P2: Home Currency | Q2: docdate | R2: ref1 | S2: el2 | T2: el2_name | U2: el3 | W2: USD | X2: 1
A3: =+VLOOKUP(O3,'Selectable Table'!$D$2:$E$1048576,2,0) -> J & J | B3: 30723 | C3: Local Trials | D3: Materiales pool Janssen | E3: 2025 | F3: 6 | G3: =+VLOOKUP(H3,Chi!#REF!,3,0) -> #REF! | H3: Non-Drug Storage Ambient (per Pallet) | I3: 1527.5899 | J3: USD | K3: =+VLOOKUP(J3,$W$2:$X$3,2,0)*I3 -> 1527.5899 | L3: Argentina | M3: Local Trials | O3: Janssen | P3: =K3 -> 1527.5899 | Q3: 45831 | S3: 40700 | T3: Revenues - Third Parties | W3: USD | X3: 1
A4: =+VLOOKUP(O4,'Selectable Table'!$D$2:$E$1048576,2,0) -> J & J | B4: 30723 | C4: Local Trials | D4: Materiales pool Janssen | E4: 2025 | F4: 6 | G4: =+VLOOKUP(H4,Chi!#REF!,3,0) -> #REF! | H4: Receipt fee Ancillaries (per Receipt_ID) | I4: 240.0519 | J4: USD | K4: =+VLOOKUP(J4,$W$2:$X$3,2,0)*I4 -> 240.0519 | L4: Argentina | M4: Local Trials | O4: Janssen | P4: =K4 -> 240.0519 | Q4: 45831 | S4: 40700 | T4: Revenues - Third Parties | W4: EUR | X4: 1.1609
A5: =+VLOOKUP(O5,'Selectable Table'!$D$2:$E$1048576,2,0) -> J & J | B5: 30724 | C5: Local Trial | D5: 64091742PCR3001_anc_returns | E5: 2025 | F5: 6 | G5: =+VLOOKUP(H5,Chi!#REF!,3,0) -> #REF! | H5: Storage of Returns (per Pallet) | I5: 209.50545 | J5: USD | K5: =+VLOOKUP(J5,$W$2:$X$3,2,0)*I5 -> 209.50545 | L5: Argentina | M5: Local Trial | O5: Janssen | P5: =K5 -> 209.50545 | Q5: 45831 | S5: 40700 | T5: Revenues - Third Parties | W5: CHF | X5: 1.2418
A6: =+VLOOKUP(O6,'Selectable Table'!$D$2:$E$1048576,2,0) -> J & J | B6: 30725 | C6: Local Trials | D6: 56021927PCR3011_Anc_Returns | E6: 2025 | F6: 6 | G6: =+VLOOKUP(H6,Chi!#REF!,3,0) -> #REF! | H6: Non-Drug Storage Ambient (per Pallet) | I6: 218.22713 | J6: USD | K6: =+VLOOKUP(J6,$W$2:$X$3,2,0)*I6 -> 218.22713 | L6: Argentina | M6: Local Trials | O6: Janssen | P6: =K6 -> 218.22713 | Q6: 45831 | S6: 40700 | T6: Revenues - Third Parties | W6: CLP | X6: 0.00107
A7: =+VLOOKUP(O7,'Selectable Table'!$D$2:$E$1048576,2,0) -> J & J | B7: 30725 | C7: Local Trials | D7: 56021927PCR3011_Anc_Returns | E7: 2025 | F7: 6 | G7: =+VLOOKUP(H7,Chi!#REF!,3,0) -> #REF! | H7: Storage of Returns (per Pallet) | I7: 104.75272 | J7: USD | K7: =+VLOOKUP(J7,$W$2:$X$3,2,0)*I7 -> 104.75272 | L7: Argentina | M7: Local Trials | O7: Janssen | P7: =K7 -> 104.75272 | Q7: 45831 | S7: 40700 | T7: Revenues - Third Parties | W7: GBP | X7: 1.3615
A8: =+VLOOKUP(O8,'Selectable Table'!$D$2:$E$1048576,2,0) -> J & J | B8: 30726 | C8: Local Trials | D8: CNTO1959UCO3001_Anc_Returns | E8: 2025 | F8: 6 | G8: =+VLOOKUP(H8,Chi!#REF!,3,0) -> #REF! | H8: Non-Drug Storage Ambient (per Pallet) | I8: 1309.3628 | J8: USD | K8: =+VLOOKUP(J8,$W$2:$X$3,2,0)*I8 -> 1309.3628 | L8: Argentina | M8: Local Trials | O8: Janssen | P8: =K8 -> 1309.3628 | Q8: 45831 | S8: 40700 | T8: Revenues - Third Parties | W8: BRL | X8: 0.1814
A9: =+VLOOKUP(O9,'Selectable Table'!$D$2:$E$1048576,2,0) -> J & J | B9: 30726 | C9: Local Trials | D9: CNTO1959UCO3001_Anc_Returns | E9: 2025 | F9: 6 | G9: =+VLOOKUP(H9,Chi!#REF!,3,0) -> #REF! | H9: Storage of Returns (per Pallet) | I9: 523.76362 | J9: USD | K9: =+VLOOKUP(J9,$W$2:$X$3,2,0)*I9 -> 523.76362 | L9: Argentina | M9: Local Trials | O9: Janssen | P9: =K9 -> 523.76362 | Q9: 45831 | S9: 40700 | T9: Revenues - Third Parties
A10: =+VLOOKUP(O10,'Selectable Table'!$D$2:$E$1048576,2,0) -> J & J | B10: 30727 | C10: Local Trials | D10: AC-055-315_anc_returns | E10: 2025 | F10: 6 | G10: =+VLOOKUP(H10,Chi!#REF!,3,0) -> #REF! | H10: Freight - Returns | I10: 141.449 | J10: USD | K10: =+VLOOKUP(J10,$W$2:$X$3,2,0)*I10 -> 141.449 | L10: Argentina | M10: Local Trials | O10: Janssen | P10: =K10 -> 141.449 | Q10: 45831 | S10: 40700 | T10: Revenues - Third Parties
A11: =+VLOOKUP(O11,'Selectable Table'!$D$2:$E$1048576,2,0) -> J & J | B11: 30727 | C11: Local Trials | D11: AC-055-315_anc_returns | E11: 2025 | F11: 6 | G11: =+VLOOKUP(H11,Chi!#REF!,3,0) -> #REF! | H11: Non-Drug Storage Ambient (per Pallet) | I11: 218.22713 | J11: USD | K11: =+VLOOKUP(J11,$W$2:$X$3,2,0)*I11 -> 218.22713 | L11: Argentina | M11: Local Trials | O11: Janssen | P11: =K11 -> 218.22713 | Q11: 45831 | S11: 40700 | T11: Revenues - Third Parties
A12: =+VLOOKUP(O12,'Selectable Table'!$D$2:$E$1048576,2,0) -> J & J | B12: 30727 | C12: Local Trials | D12: AC-055-315_anc_returns | E12: 2025 | F12: 6 | G12: =+VLOOKUP(H12,Chi!#REF!,3,0) -> #REF! | H12: Reconciliation of Returns (per Hour) | I12: 61.103185 | J12: USD | K12: =+VLOOKUP(J12,$W$2:$X$3,2,0)*I12 -> 61.103185 | L12: Argentina | M12: Local Trials | O12: Janssen | P12: =K12 -> 61.103185 | Q12: 45831 | S12: 40700 | T12: Revenues - Third Parties
A13: =+VLOOKUP(O13,'Selectable Table'!$D$2:$E$1048576,2,0) -> J & J | B13: 30727 | C13: Local Trials | D13: AC-055-315_anc_returns | E13: 2025 | F13: 6 | G13: =+VLOOKUP(H13,Chi!#REF!,3,0) -> #REF! | H13: Returns Receipt (per Receipt) | I13: 320.78915 | J13: USD | K13: =+VLOOKUP(J13,$W$2:$X$3,2,0)*I13 -> 320.78915 | L13: Argentina | M13: Local Trials | O13: Janssen | P13: =K13 -> 320.78915 | Q13: 45831 | S13: 40700 | T13: Revenues - Third Parties
A14: =+VLOOKUP(O14,'Selectable Table'!$D$2:$E$1048576,2,0) -> J & J | B14: 30727 | C14: Local Trials | D14: AC-055-315_anc_returns | E14: 2025 | F14: 6 | G14: =+VLOOKUP(H14,Chi!#REF!,3,0) -> #REF! | H14: Storage Ambient (per Pallet) | I14: 218.22713 | J14: USD | K14: =+VLOOKUP(J14,$W$2:$X$3,2,0)*I14 -> 218.22713 | L14: Argentina | M14: Local Trials | O14: Janssen | P14: =K14 -> 218.22713 | Q14: 45831 | S14: 40700 | T14: Revenues - Third Parties
A15: =+VLOOKUP(O15,'Selectable Table'!$D$2:$E$1048576,2,0) -> J & J | B15: 30727 | C15: Local Trials | D15: AC-055-315_anc_returns | E15: 2025 | F15: 6 | G15: =+VLOOKUP(H15,Chi!#REF!,3,0) -> #REF! | H15: Storage of Returns (per Pallet) | I15: 523.76362 | J15: USD | K15: =+VLOOKUP(J15,$W$2:$X$3,2,0)*I15 -> 523.76362 | L15: Argentina | M15: Local Trials | O15: Janssen | P15: =K15 -> 523.76362 | Q15: 45831 | S15: 40700 | T15: Revenues - Third Parties
A16: =+VLOOKUP(O16,'Selectable Table'!$D$2:$E$1048576,2,0) -> J & J | B16: 30728 | C16: Local Trials | D16: 67652000PCR3002_anc_returns | E16: 2025 | F16: 6 | G16: =+VLOOKUP(H16,Chi!#REF!,3,0) -> #REF! | H16: Freight - Returns | I16: 382.5052 | J16: USD | K16: =+VLOOKUP(J16,$W$2:$X$3,2,0)*I16 -> 382.5052 | L16: Argentina | M16: Local Trials | O16: Janssen | P16: =K16 -> 382.5052 | Q16: 45831 | S16: 40700 | T16: Revenues - Third Parties
A17: =+VLOOKUP(O17,'Selectable Table'!$D$2:$E$1048576,2,0) -> J & J | B17: 30728 | C17: Local Trials | D17: 67652000PCR3002_anc_returns | E17: 2025 | F17: 6 | G17: =+VLOOKUP(H17,Chi!#REF!,3,0) -> #REF! | H17: Reconciliation of Returns (per Hour) | I17: 122.20637 | J17: USD | K17: =+VLOOKUP(J17,$W$2:$X$3,2,0)*I17 -> 122.20637 | L17: Argentina | M17: Local Trials | O17: Janssen | P17: =K17 -> 122.20637 | Q17: 45831 | S17: 40700 | T17: Revenues - Third Parties
A18: =+VLOOKUP(O18,'Selectable Table'!$D$2:$E$1048576,2,0) -> J & J | B18: 30728 | C18: Local Trials | D18: 67652000PCR3002_anc_returns | E18: 2025 | F18: 6 | G18: =+VLOOKUP(H18,Chi!#REF!,3,0) -> #REF! | H18: Returns Receipt (per Receipt) | I18: 320.78915 | J18: USD | K18: =+VLOOKUP(J18,$W$2:$X$3,2,0)*I18 -> 320.78915 | L18: Argentina | M18: Local Trials | O18: Janssen | P18: =K18 -> 320.78915 | Q18: 45831 | S18: 40700 | T18: Revenues - Third Parties
A19: =+VLOOKUP(O19,'Selectable Table'!$D$2:$E$1048576,2,0) -> J & J | B19: 30728 | C19: Local Trials | D19: 67652000PCR3002_anc_returns | E19: 2025 | F19: 6 | G19: =+VLOOKUP(H19,Chi!#REF!,3,0) -> #REF! | H19: Storage of Returns (per Pallet) | I19: 838.0218 | J19: USD | K19: =+VLOOKUP(J19,$W$2:$X$3,2,0)*I19 -> 838.0218 | L19: Argentina | M19: Local Trials | O19: Janssen | P19: =K19 -> 838.0218 | Q19: 45831 | S19: 40700 | T19: Revenues - Third Parties
A20: =+VLOOKUP(O20,'Selectable Table'!$D$2:$E$1048576,2,0) -> J & J | B20: 30729 | C20: Local Trials | D20: 73841937NSC3003_Anc_Returns | E20: 2025 | F20: 6 | G20: =+VLOOKUP(H20,Chi!#REF!,3,0) -> #REF! | H20: Non-Drug Storage Ambient (per Pallet) | I20: 218.22713 | J20: USD | K20: =+VLOOKUP(J20,$W$2:$X$3,2,0)*I20 -> 218.22713 | L20: Argentina | M20: Local Trials | O20: Janssen | P20: =K20 -> 218.22713 | Q20: 45831 | S20: 40700 | T20: Revenues - Third Parties
... A170: =+VLOOKUP(O170,'Selectable Table'!$D$2:$E$1048576,2,0) -> MERCK | B170: 30772 | C170: ARG FR# 58474 PO#: 8200873875 | D170: MK-2060-007 (Local) | E170: 2025 | F170: 6 | G170: =+VLOOKUP(H170,Chi!#REF!,3,0) -> #REF! | H170: Reconciliation of Returns (per Hour) | I170: 65.4368 | J170: USD | K170: =+VLOOKUP(J170,$W$2:$X$3,2,0)*I170 -> 65.4368 | L170: Argentina | M170: PO#: 8200873875 | O170: Merck Sharp and Dohme LLC | P170: =K170 -> 65.4368 | Q170: 45831 | S170: 40700 | T170: Revenues - Third Parties
A171: =+VLOOKUP(O171,'Selectable Table'!$D$2:$E$1048576,2,0) -> MERCK | B171: 30772 | C171: ARG FR# 58474 PO#: 8200873875 | D171: MK-2060-007 (Local) | E171: 2025 | F171: 6 | G171: Total Distribution | H171: Returns Receipt (per Receipt) | I171: 163.592 | J171: USD | K171: =+VLOOKUP(J171,$W$2:$X$3,2,0)*I171 -> 163.592 | L171: Argentina | M171: PO#: 8200873875 | O171: Merck Sharp and Dohme LLC | P171: =K171 -> 163.592 | Q171: 45831 | S171: 40700 | T171: Revenues - Third Parties
A172: =+VLOOKUP(O172,'Selectable Table'!$D$2:$E$1048576,2,0) -> MERCK | B172: 30772 | C172: ARG FR# 58474 PO#: 8200873875 | D172: MK-2060-007 (Local) | E172: 2025 | F172: 6 | G172: =+VLOOKUP(H172,Chi!#REF!,3,0) -> #REF! | H172: Storage of Returns (per Pallet) | I172: 462.8492 | J172: USD | K172: =+VLOOKUP(J172,$W$2:$X$3,2,0)*I172 -> 462.8492 | L172: Argentina | M172: PO#: 8200873875 | O172: Merck Sharp and Dohme LLC | P172: =K172 -> 462.8492 | Q172: 45831 | S172: 40700 | T172: Revenues - Third Parties
A173: =+VLOOKUP(O173,'Selectable Table'!$D$2:$E$1048576,2,0) -> MERCK | B173: 30773 | C173: FR# 58474 PO# 8200873875 | D173: MK-2140-003 (Local) | E173: 2025 | F173: 6 | G173: Total Return Drug | H173: Freight - Shipments | I173: 355.2197 | J173: USD | K173: =+VLOOKUP(J173,$W$2:$X$3,2,0)*I173 -> 355.2197 | L173: Argentina | M173: PO# 8200873875 | O173: Merck Sharp and Dohme LLC | P173: =K173 -> 355.2197 | Q173: 45831 | S173: 40700 | T173: Revenues - Third Parties
A174: =+VLOOKUP(O174,'Selectable Table'!$D$2:$E$1048576,2,0) -> MERCK | B174: 30773 | C174: FR# 58474 PO# 8200873875 | D174: MK-2140-003 (Local) | E174: 2025 | F174: 6 | G174: =+VLOOKUP(H174,Chi!#REF!,3,0) -> #REF! | H174: Reconciliation of Returns (per Hour) | I174: 65.4368 | J174: USD | K174: =+VLOOKUP(J174,$W$2:$X$3,2,0)*I174 -> 65.4368 | L174: Argentina | M174: PO# 8200873875 | O174: Merck Sharp and Dohme LLC | P174: =K174 -> 65.4368 | Q174: 45831 | S174: 40700 | T174: Revenues - Third Parties
A175: =+VLOOKUP(O175,'Selectable Table'!$D$2:$E$1048576,2,0) -> MERCK | B175: 30773 | C175: FR# 58474 PO# 8200873875 | D175: MK-2140-003 (Local) | E175: 2025 | F175: 6 | G175: =+VLOOKUP(H175,Chi!#REF!,3,0) -> #REF! | H175: Returns Receipt (per Receipt) | I175: 163.592 | J175: USD | K175: =+VLOOKUP(J175,$W$2:$X$3,2,0)*I175 -> 163.592 | L175: Argentina | M175: PO# 8200873875 | O175: Merck Sharp and Dohme LLC | P175: =K175 -> 163.592 | Q175: 45831 | S175: 40700 | T175: Revenues - Third Parties
A176: =+VLOOKUP(O176,'Selectable Table'!$D$2:$E$1048576,2,0) -> MERCK | B176: 30773 | C176: FR# 58474 PO# 8200873875 | D176: MK-2140-003 (Local) | E176: 2025 | F176: 6 | G176: Total Distribution | H176: Storage Ambient (per Pallet) | I176: 140.2269 | J176: USD | K176: =+VLOOKUP(J176,$W$2:$X$3,2,0)*I176 -> 140.2269 | L176: Argentina | M176: PO# 8200873875 | O176: Merck Sharp and Dohme LLC | P176: =K176 -> 140.2269 | Q176: 45831 | S176: 40700 | T176: Revenues - Third Parties
A177: =+VLOOKUP(O177,'Selectable Table'!$D$2:$E$1048576,2,0) -> MERCK | B177: 30773 | C177: FR# 58474 PO# 8200873875 | D177: MK-2140-003 (Local) | E177: 2025 | F177: 6 | G177: =+VLOOKUP(H177,Chi!#REF!,3,0) -> #REF! | H177: Storage of Returns (per Pallet) | I177: 115.7123 | J177: USD | K177: =+VLOOKUP(J177,$W$2:$X$3,2,0)*I177 -> 115.7123 | L177: Argentina | M177: PO# 8200873875 | O177: Merck Sharp and Dohme LLC | P177: =K177 -> 115.7123 | Q177: 45831 | S177: 40700 | T177: Revenues - Third Parties
A178: =+VLOOKUP(O178,'Selectable Table'!$D$2:$E$1048576,2,0) -> MERCK | B178: 30774 | C178: 58474 - ARG PO#8200873875 | D178: MK-1084-001 (Local) | E178: 2025 | F178: 6 | G178: =+VLOOKUP(H178,Chi!#REF!,3,0) -> #REF! | H178: Storage Ambient (per Pallet) | I178: 140.2269 | J178: USD | K178: =+VLOOKUP(J178,$W$2:$X$3,2,0)*I178 -> 140.2269 | L178: Argentina | M178: PO#8200873875 | O178: Merck Sharp and Dohme LLC | P178: =K178 -> 140.2269 | Q178: 45831 | S178: 40700 | T178: Revenues - Third Parties
A179: =+VLOOKUP(O179,'Selectable Table'!$D$2:$E$1048576,2,0) -> MERCK | B179: 30775 | C179: (ARG) PO 8200873875 | D179: MK-7684A-006 (Local) | E179: 2025 | F179: 6 | G179: =+VLOOKUP(H179,Chi!#REF!,3,0) -> #REF! | H179: Freight - Returns | I179: 395.2828 | J179: USD | K179: =+VLOOKUP(J179,$W$2:$X$3,2,0)*I179 -> 395.2828 | L179: Argentina | M179: PO 8200873875 | O179: Merck Sharp and Dohme LLC | P179: =K179 -> 395.2828 | Q179: 45831 | S179: 40700 | T179: Revenues - Third Parties
A180: =+VLOOKUP(O180,'Selectable Table'!$D$2:$E$1048576,2,0) -> MERCK | B180: 30775 | C180: (ARG) PO 8200873875 | D180: MK-7684A-006 (Local) | E180: 2025 | F180: 6 | G180: =+VLOOKUP(H180,Chi!#REF!,3,0) -> #REF! | H180: Storage Ambient (per Pallet) | I180: 560.9076 | J180: USD | K180: =+VLOOKUP(J180,$W$2:$X$3,2,0)*I180 -> 560.9076 | L180: Argentina | M180: PO 8200873875 | O180: Merck Sharp and Dohme LLC | P180: =K180 -> 560.9076 | Q180: 45831 | S180: 40700 | T180: Revenues - Third Parties
A181: =+VLOOKUP(O181,'Selectable Table'!$D$2:$E$1048576,2,0) -> MERCK | B181: 30775 | C181: (ARG) PO 8200873875 | D181: MK-7684A-006 (Local) | E181: 2025 | F181: 6 | G181: =+VLOOKUP(H181,Chi!#REF!,3,0) -> #REF! | H181: Storage of Labels Ambient (per Pallet) | I181: 115.7123 | J181: USD | K181: =+VLOOKUP(J181,$W$2:$X$3,2,0)*I181 -> 115.7123 | L181: Argentina | M181: PO 8200873875 | O181: Merck Sharp and Dohme LLC | P181: =K181 -> 115.7123 | Q181: 45831 | S181: 40700 | T181: Revenues - Third Parties
A182: =+VLOOKUP(O182,'Selectable Table'!$D$2:$E$1048576,2,0) -> MERCK | B182: 30775 | C182: (ARG) PO 8200873875 | D182: MK-7684A-006 (Local) | E182: 2025 | F182: 6 | G182: =+VLOOKUP(H182,Chi!#REF!,3,0) -> #REF! | H182: Storage of Returns (per Pallet) | I182: 231.4246 | J182: USD | K182: =+VLOOKUP(J182,$W$2:$X$3,2,0)*I182 -> 231.4246 | L182: Argentina | M182: PO 8200873875 | O182: Merck Sharp and Dohme LLC | P182: =K182 -> 231.4246 | Q182: 45831 | S182: 40700 | T182: Revenues - Third Parties
A183: =+VLOOKUP(O183,'Selectable Table'!$D$2:$E$1048576,2,0) -> MERCK | B183: 30775 | C183: (ARG) PO 8200873875 | D183: MK-7684A-006 (Local) | E183: 2025 | F183: 6 | G183: =+VLOOKUP(H183,Chi!#REF!,3,0) -> #REF! | H183: Storage Refrigerated (per Shelf) | I183: 420.6444 | J183: USD | K183: =+VLOOKUP(J183,$W$2:$X$3,2,0)*I183 -> 420.6444 | L183: Argentina | M183: PO 8200873875 | O183: Merck Sharp and Dohme LLC | P183: =K183 -> 420.6444 | Q183: 45831 | S183: 40700 | T183: Revenues - Third Parties
A184: =+VLOOKUP(O184,'Selectable Table'!$D$2:$E$1048576,2,0) -> MERCK | B184: 30776 | C184: (ARG) PO 8200873875 | D184: MK-7684A-007 (Local) | E184: 2025 | F184: 6 | G184: =+VLOOKUP(H184,Chi!#REF!,3,0) -> #REF! | H184: Freight - Returns | I184: 197.6414 | J184: USD | K184: =+VLOOKUP(J184,$W$2:$X$3,2,0)*I184 -> 197.6414 | L184: Argentina | M184: PO 8200873875 | O184: Merck Sharp and Dohme LLC | P184: =K184 -> 197.6414 | Q184: 45831 | S184: 40700 | T184: Revenues - Third Parties
A185: =+VLOOKUP(O185,'Selectable Table'!$D$2:$E$1048576,2,0) -> MERCK | B185: 30776 | C185: (ARG) PO 8200873875 | D185: MK-7684A-007 (Local) | E185: 2025 | F185: 6 | G185: =+VLOOKUP(H185,Chi!#REF!,3,0) -> #REF! | H185: Pick and Pack (Ambient) | I185: 151.9155 | J185: USD | K185: =+VLOOKUP(J185,$W$2:$X$3,2,0)*I185 -> 151.9155 | L185: Argentina | M185: PO 8200873875 | O185: Merck Sharp and Dohme LLC | P185: =K185 -> 151.9155 | Q185: 45831 | S185: 40700 | T185: Revenues - Third Parties
A186: =+VLOOKUP(O186,'Selectable Table'!$D$2:$E$1048576,2,0) -> MERCK | B186: 30776 | C186: (ARG) PO 8200873875 | D186: MK-7684A-007 (Local) | E186: 2025 | F186: 6 | G186: =+VLOOKUP(H186,Chi!#REF!,3,0) -> #REF! | H186: Reconciliation of Returns (per Hour) | I186: 65.4368 | J186: USD | K186: =+VLOOKUP(J186,$W$2:$X$3,2,0)*I186 -> 65.4368 | L186: Argentina | M186: PO 8200873875 | O186: Merck Sharp and Dohme LLC | P186: =K186 -> 65.4368 | Q186: 45831 | S186: 40700 | T186: Revenues - Third Parties
A187: =+VLOOKUP(O187,'Selectable Table'!$D$2:$E$1048576,2,0) -> MERCK | B187: 30776 | C187: (ARG) PO 8200873875 | D187: MK-7684A-007 (Local) | E187: 2025 | F187: 6 | G187: =+VLOOKUP(H187,Chi!#REF!,3,0) -> #REF! | H187: Returns Receipt (per Receipt) | I187: 163.592 | J187: USD | K187: =+VLOOKUP(J187,$W$2:$X$3,2,0)*I187 -> 163.592 | L187: Argentina | M187: PO 8200873875 | O187: Merck Sharp and Dohme LLC | P187: =K187 -> 163.592 | Q187: 45831 | S187: 40700 | T187: Revenues - Third Parties
A188: =+VLOOKUP(O188,'Selectable Table'!$D$2:$E$1048576,2,0) -> MERCK | B188: 30776 | C188: (ARG) PO 8200873875 | D188: MK-7684A-007 (Local) | E188: 2025 | F188: 6 | G188: =+VLOOKUP(H188,Chi!#REF!,3,0) -> #REF! | H188: Storage Ambient (per Pallet) | I188: 280.4538 | J188: USD | K188: =+VLOOKUP(J188,$W$2:$X$3,2,0)*I188 -> 280.4538 | L188: Argentina | M188: PO 8200873875 | O188: Merck Sharp and Dohme LLC | P188: =K188 -> 280.4538 | Q188: 45831 | S188: 40700 | T188: Revenues - Third Parties
... A211: =+VLOOKUP(O211,'Selectable Table'!$D$2:$E$1048576,2,0) -> MERCK | B211: 30782 | C211: (ARG) FR 58474 PO 8200873875 | D211: MK-7684A-010 (Local) | E211: 2025 | F211: 6 | G211: =+VLOOKUP(H211,Chi!#REF!,3,0) -> #REF! | H211: Freight - Returns | I211: 985.5329 | J211: USD | K211: =+VLOOKUP(J211,$W$2:$X$3,2,0)*I211 -> 985.5329 | L211: Argentina | M211: PO 8200873875 | O211: Merck Sharp and Dohme LLC | P211: =K211 -> 985.5329 | Q211: 45831 | S211: 40700 | T211: Revenues - Third Parties
A212: =+VLOOKUP(O212,'Selectable Table'!$D$2:$E$1048576,2,0) -> MERCK | B212: 30782 | C212: (ARG) FR 58474 PO 8200873875 | D212: MK-7684A-010 (Local) | E212: 2025 | F212: 6 | G212: Total Distribution | H212: Reconciliation of Returns (per Hour) | I212: 130.8736 | J212: USD | K212: =+VLOOKUP(J212,$W$2:$X$3,2,0)*I212 -> 130.8736 | L212: Argentina | M212: PO 8200873875 | O212: Merck Sharp and Dohme LLC | P212: =K212 -> 130.8736 | Q212: 45831 | S212: 40700 | T212: Revenues - Third Parties
A213: =+VLOOKUP(O213,'Selectable Table'!$D$2:$E$1048576,2,0) -> MERCK | B213: 30782 | C213: (ARG) FR 58474 PO 8200873875 | D213: MK-7684A-010 (Local) | E213: 2025 | F213: 6 | G213: =+VLOOKUP(H213,Chi!#REF!,3,0) -> #REF! | H213: Returns Receipt (per Receipt) | I213: 327.184 | J213: USD | K213: =+VLOOKUP(J213,$W$2:$X$3,2,0)*I213 -> 327.184 | L213: Argentina | M213: PO 8200873875 | O213: Merck Sharp and Dohme LLC | P213: =K213 -> 327.184 | Q213: 45831 | S213: 40700 | T213: Revenues - Third Parties
A214: =+VLOOKUP(O214,'Selectable Table'!$D$2:$E$1048576,2,0) -> MERCK | B214: 30782 | C214: (ARG) FR 58474 PO 8200873875 | D214: MK-7684A-010 (Local) | E214: 2025 | F214: 6 | G214: Total Distribution | H214: Storage of Returns (per Pallet) | I214: 694.2738 | J214: USD | K214: =+VLOOKUP(J214,$W$2:$X$3,2,0)*I214 -> 694.2738 | L214: Argentina | M214: PO 8200873875 | O214: Merck Sharp and Dohme LLC | P214: =K214 -> 694.2738 | Q214: 45831 | S214: 40700 | T214: Revenues - Third Parties
A215: =+VLOOKUP(O215,'Selectable Table'!$D$2:$E$1048576,2,0) -> MERCK | B215: 30783 | C215: (ARG) PO 8200873875 | D215: MK-8591A-053 (local) | E215: 2025 | F215: 6 | G215: =+VLOOKUP(H215,Chi!#REF!,3,0) -> #REF! | H215: Freight - Returns | I215: 355.2197 | J215: USD | K215: =+VLOOKUP(J215,$W$2:$X$3,2,0)*I215 -> 355.2197 | L215: Argentina | M215: PO 8200873875 | O215: Merck Sharp and Dohme LLC | P215: =K215 -> 355.2197 | Q215: 45831 | S215: 40700 | T215: Revenues - Third Parties
A216: =+VLOOKUP(O216,'Selectable Table'!$D$2:$E$1048576,2,0) -> MERCK | B216: 30783 | C216: (ARG) PO 8200873875 | D216: MK-8591A-053 (local) | E216: 2025 | F216: 6 | G216: =+VLOOKUP(H216,Chi!#REF!,3,0) -> #REF! | H216: Storage of Returns (per Pallet) | I216: 231.4246 | J216: USD | K216: =+VLOOKUP(J216,$W$2:$X$3,2,0)*I216 -> 231.4246 | L216: Argentina | M216: PO 8200873875 | O216: Merck Sharp and Dohme LLC | P216: =K216 -> 231.4246 | Q216: 45831 | S216: 40700 | T216: Revenues - Third Parties
A217: =+VLOOKUP(O217,'Selectable Table'!$D$2:$E$1048576,2,0) -> MERCK | B217: 30784 | C217: (AR) PO# 8200873875 | D217: MK-1942-008 (Local) | E217: 2025 | F217: 6 | G217: =+VLOOKUP(H217,Chi!#REF!,3,0) -> #REF! | H217: Non-Drug Storage Ambient (per Pallet) | I217: 115.7123 | J217: USD | K217: =+VLOOKUP(J217,$W$2:$X$3,2,0)*I217 -> 115.7123 | L217: Argentina | M217: PO# 8200873875 | O217: Merck Sharp and Dohme LLC | P217: =K217 -> 115.7123 | Q217: 45831 | S217: 40700 | T217: Revenues - Third Parties
A218: =+VLOOKUP(O218,'Selectable Table'!$D$2:$E$1048576,2,0) -> MERCK | B218: 30785 | C218: (ARG) PO 8200873875 | D218: MK-3475-02B (Local) | E218: 2025 | F218: 6 | G218: =+VLOOKUP(H218,Chi!#REF!,3,0) -> #REF! | H218: Storage of Returns (per Pallet) | I218: 231.4246 | J218: USD | K218: =+VLOOKUP(J218,$W$2:$X$3,2,0)*I218 -> 231.4246 | L218: Argentina | M218: PO 8200873875 | O218: Merck Sharp and Dohme LLC | P218: =K218 -> 231.4246 | Q218: 45831 | S218: 40700 | T218: Revenues - Third Parties
A219: =+VLOOKUP(O219,'Selectable Table'!$D$2:$E$1048576,2,0) -> MERCK | B219: 30786 | C219: (ARG) PO 8200873875 | D219: MK-3475-02D (Local) | E219: 2025 | F219: 6 | G219: =+VLOOKUP(H219,Chi!#REF!,3,0) -> #REF! | H219: Storage Ambient (per Pallet) | I219: 420.6807 | J219: USD | K219: =+VLOOKUP(J219,$W$2:$X$3,2,0)*I219 -> 420.6807 | L219: Argentina | M219: PO 8200873875 | O219: Merck Sharp and Dohme LLC | P219: =K219 -> 420.6807 | Q219: 45831 | S219: 40700 | T219: Revenues - Third Parties
A220: =+VLOOKUP(O220,'Selectable Table'!$D$2:$E$1048576,2,0) -> MERCK | B220: 30787 | C220: (ARG) PSG-A-1072403 PO 8200873875 | D220: MK-5475-013 (Local) | E220: 2025 | F220: 6 | G220: =+VLOOKUP(H220,Chi!#REF!,3,0) -> #REF! | H220: Storage Ambient (per Pallet) | I220: 140.2269 | J220: USD | K220: =+VLOOKUP(J220,$W$2:$X$3,2,0)*I220 -> 140.2269 | L220: Argentina | M220: PO 8200873875 | O220: Merck Sharp and Dohme LLC | P220: =K220 -> 140.2269 | Q220: 45831 | S220: 40700 | T220: Revenues - Third Parties
A221: =+VLOOKUP(O221,'Selectable Table'!$D$2:$E$1048576,2,0) -> MERCK | B221: 30787 | C221: (ARG) PSG-A-1072403 PO 8200873875 | D221: MK-5475-013 (Local) | E221: 2025 | F221: 6 | G221: =+VLOOKUP(H221,Chi!#REF!,3,0) -> #REF! | H221: Storage of Returns (per Pallet) | I221: 231.4246 | J221: USD | K221: =+VLOOKUP(J221,$W$2:$X$3,2,0)*I221 -> 231.4246 | L221: Argentina | M221: PO 8200873875 | O221: Merck Sharp and Dohme LLC | P221: =K221 -> 231.4246 | Q221: 45831 | S221: 40700 | T221: Revenues - Third Parties
A222: =+VLOOKUP(O222,'Selectable Table'!$D$2:$E$1048576,2,0) -> MERCK | B222: 30788 | C222: (ARG) PO # 8200873875 | D222: MK-1026-010 (Local) | E222: 2025 | F222: 6 | G222: =+VLOOKUP(H222,Chi!#REF!,3,0) -> #REF! | H222: Freight - Returns | I222: 157.5783 | J222: USD | K222: =+VLOOKUP(J222,$W$2:$X$3,2,0)*I222 -> 157.5783 | L222: Argentina | M222: PO # 8200873875 | O222: Merck Sharp and Dohme LLC | P222: =K222 -> 157.5783 | Q222: 45831 | S222: 40700 | T222: Revenues - Third Parties
A223: =+VLOOKUP(O223,'Selectable Table'!$D$2:$E$1048576,2,0) -> MERCK | B223: 30788 | C223: (ARG) PO # 8200873875 | D223: MK-1026-010 (Local) | E223: 2025 | F223: 6 | G223: =+VLOOKUP(H223,Chi!#REF!,3,0) -> #REF! | H223: Freight - Shipments | I223: 1972.3726 | J223: USD | K223: =+VLOOKUP(J223,$W$2:$X$3,2,0)*I223 -> 1972.3726 | L223: Argentina | M223: PO # 8200873875 | O223: Merck Sharp and Dohme LLC | P223: =K223 -> 1972.3726 | Q223: 45831 | S223: 40700 | T223: Revenues - Third Parties
A224: =+VLOOKUP(O224,'Selectable Table'!$D$2:$E$1048576,2,0) -> MERCK | B224: 30788 | C224: (ARG) PO # 8200873875 | D224: MK-1026-010 (Local) | E224: 2025 | F224: 6 | G224: =+VLOOKUP(H224,Chi!#REF!,3,0) -> #REF! | H224: Storage Ambient (per Pallet) | I224: 420.6807 | J224: USD | K224: =+VLOOKUP(J224,$W$2:$X$3,2,0)*I224 -> 420.6807 | L224: Argentina | M224: PO # 8200873875 | O224: Merck Sharp and Dohme LLC | P224: =K224 -> 420.6807 | Q224: 45831 | S224: 40700 | T224: Revenues - Third Parties
A225: =+VLOOKUP(O225,'Selectable Table'!$D$2:$E$1048576,2,0) -> MERCK | B225: 30788 | C225: (ARG) PO # 8200873875 | D225: MK-1026-010 (Local) | E225: 2025 | F225: 6 | G225: =+VLOOKUP(H225,Chi!#REF!,3,0) -> #REF! | H225: Storage of Labels Ambient (per Pallet) | I225: 115.7123 | J225: USD | K225: =+VLOOKUP(J225,$W$2:$X$3,2,0)*I225 -> 115.7123 | L225: Argentina | M225: PO # 8200873875 | O225: Merck Sharp and Dohme LLC | P225: =K225 -> 115.7123 | Q225: 45831 | S225: 40700 | T225: Revenues - Third Parties
A226: =+VLOOKUP(O226,'Selectable Table'!$D$2:$E$1048576,2,0) -> MERCK | B226: 30788 | C226: (ARG) PO # 8200873875 | D226: MK-1026-010 (Local) | E226: 2025 | F226: 6 | G226: =+VLOOKUP(H226,Chi!#REF!,3,0) -> #REF! | H226: Storage of Returns (per Pallet) | I226: 347.1369 | J226: USD | K226: =+VLOOKUP(J226,$W$2:$X$3,2,0)*I226 -> 347.1369 | L226: Argentina | M226: PO # 8200873875 | O226: Merck Sharp and Dohme LLC | P226: =K226 -> 347.1369 | Q226: 45831 | S226: 40700 | T226: Revenues - Third Parties
... A228: =+VLOOKUP(O228,'Selectable Table'!$D$2:$E$1048576,2,0) -> MERCK | B228: 30789 | C228: (ARG) PO 8200873875 | D228: V940-001 (Local) | E228: 2025 | F228: 6 | G228: =+VLOOKUP(H228,Chi!#REF!,3,0) -> #REF! | H228: Storage Ambient (per Pallet) | I228: 140.2269 | J228: USD | K228: =+VLOOKUP(J228,$W$2:$X$3,2,0)*I228 -> 140.2269 | L228: Argentina | M228: PO 8200873875 | O228: Merck Sharp and Dohme LLC | P228: =K228 -> 140.2269 | Q228: 45831 | S228: 40700 | T228: Revenues - Third Parties
A229: =+VLOOKUP(O229,'Selectable Table'!$D$2:$E$1048576,2,0) -> MERCK | B229: 30789 | C229: (ARG) PO 8200873875 | D229: V940-001 (Local) | E229: 2025 | F229: 6 | G229: Total Distribution | H229: Storage of Returns (per Pallet) | I229: 347.1369 | J229: USD | K229: =+VLOOKUP(J229,$W$2:$X$3,2,0)*I229 -> 347.1369 | L229: Argentina | M229: PO 8200873875 | O229: Merck Sharp and Dohme LLC | P229: =K229 -> 347.1369 | Q229: 45831 | S229: 40700 | T229: Revenues - Third Parties
A230: =+VLOOKUP(O230,'Selectable Table'!$D$2:$E$1048576,2,0) -> MERCK | B230: 30790 | C230: (ARG) PO 8200873875 | D230: MK-0616-015 (Local) | E230: 2025 | F230: 6 | G230: =+VLOOKUP(H230,Chi!#REF!,3,0) -> #REF! | H230: Freight - Shipments | I230: 157.5783 | J230: USD | K230: =+VLOOKUP(J230,$W$2:$X$3,2,0)*I230 -> 157.5783 | L230: Argentina | M230: PO 8200873875 | O230: Merck Sharp and Dohme LLC | P230: =K230 -> 157.5783 | Q230: 45831 | S230: 40700 | T230: Revenues - Third Parties
A231: =+VLOOKUP(O231,'Selectable Table'!$D$2:$E$1048576,2,0) -> MERCK | B231: 30790 | C231: (ARG) PO 8200873875 | D231: MK-0616-015 (Local) | E231: 2025 | F231: 6 | G231: =+VLOOKUP(H231,Chi!#REF!,3,0) -> #REF! | H231: Non-Drug Storage Ambient (per Pallet) | I231: 347.1369 | J231: USD | K231: =+VLOOKUP(J231,$W$2:$X$3,2,0)*I231 -> 347.1369 | L231: Argentina | M231: PO 8200873875 | O231: Merck Sharp and Dohme LLC | P231: =K231 -> 347.1369 | Q231: 45831 | S231: 40700 | T231: Revenues - Third Parties
A232: =+VLOOKUP(O232,'Selectable Table'!$D$2:$E$1048576,2,0) -> MERCK | B232: 30790 | C232: (ARG) PO 8200873875 | D232: MK-0616-015 (Local) | E232: 2025 | F232: 6 | G232: =+VLOOKUP(H232,Chi!#REF!,3,0) -> #REF! | H232: Storage of Returns (per Pallet) | I232: 347.1369 | J232: USD | K232: =+VLOOKUP(J232,$W$2:$X$3,2,0)*I232 -> 347.1369 | L232: Argentina | M232: PO 8200873875 | O232: Merck Sharp and Dohme LLC | P232: =K232 -> 347.1369 | Q232: 45831 | S232: 40700 | T232: Revenues - Third Parties
A233: =+VLOOKUP(O233,'Selectable Table'!$D$2:$E$1048576,2,0) -> MERCK | B233: 30791 | C233: (ARG) PO 8200873875 | D233: V940-004 (Local) | E233: 2025 | F233: 6 | G233: =+VLOOKUP(H233,Chi!#REF!,3,0) -> #REF! | H233: Freight - Returns | I233: 355.2197 | J233: USD | K233: =+VLOOKUP(J233,$W$2:$X$3,2,0)*I233 -> 355.2197 | L233: Argentina | M233: PO 8200873875 | O233: Merck Sharp and Dohme LLC | P233: =K233 -> 355.2197 | Q233: 45831 | S233: 40700 | T233: Revenues - Third Parties
A234: =+VLOOKUP(O234,'Selectable Table'!$D$2:$E$1048576,2,0) -> MERCK | B234: 30791 | C234: (ARG) PO 8200873875 | D234: V940-004 (Local) | E234: 2025 | F234: 6 | G234: =+VLOOKUP(H234,Chi!#REF!,3,0) -> #REF! | H234: Reconciliation of Returns (per Hour) | I234: 65.4368 | J234: USD | K234: =+VLOOKUP(J234,$W$2:$X$3,2,0)*I234 -> 65.4368 | L234: Argentina | M234: PO 8200873875 | O234: Merck Sharp and Dohme LLC | P234: =K234 -> 65.4368 | Q234: 45831 | S234: 40700 | T234: Revenues - Third Parties
A235: =+VLOOKUP(O235,'Selectable Table'!$D$2:$E$1048576,2,0) -> MERCK | B235: 30791 | C235: (ARG) PO 8200873875 | D235: V940-004 (Local) | E235: 2025 | F235: 6 | G235: =+VLOOKUP(H235,Chi!#REF!,3,0) -> #REF! | H235: Returns Receipt (per Receipt) | I235: 163.592 | J235: USD | K235: =+VLOOKUP(J235,$W$2:$X$3,2,0)*I235 -> 163.592 | L235: Argentina | M235: PO 8200873875 | O235: Merck Sharp and Dohme LLC | P235: =K235 -> 163.592 | Q235: 45831 | S235: 40700 | T235: Revenues - Third Parties
A236: =+VLOOKUP(O236,'Selectable Table'!$D$2:$E$1048576,2,0) -> MERCK | B236: 30791 | C236: (ARG) PO 8200873875 | D236: V940-004 (Local) | E236: 2025 | F236: 6 | G236: =+VLOOKUP(H236,Chi!#REF!,3,0) -> #REF! | H236: Storage Ambient (per Pallet) | I236: 140.2269 | J236: USD | K236: =+VLOOKUP(J236,$W$2:$X$3,2,0)*I236 -> 140.2269 | L236: Argentina | M236: PO 8200873875 | O236: Merck Sharp and Dohme LLC | P236: =K236 -> 140.2269 | Q236: 45831 | S236: 40700 | T236: Revenues - Third Parties
A237: =+VLOOKUP(O237,'Selectable Table'!$D$2:$E$1048576,2,0) -> MERCK | B237: 30791 | C237: (ARG) PO 8200873875 | D237: V940-004 (Local) | E237: 2025 | F237: 6 | G237: =+VLOOKUP(H237,Chi!#REF!,3,0) -> #REF! | H237: Storage of Returns (per Pallet) | I237: 231.4246 | J237: USD | K237: =+VLOOKUP(J237,$W$2:$X$3,2,0)*I237 -> 231.4246 | L237: Argentina | M237: PO 8200873875 | O237: Merck Sharp and Dohme LLC | P237: =K237 -> 231.4246 | Q237: 45831 | S237: 40700 | T237: Revenues - Third Parties
A238: =+VLOOKUP(O238,'Selectable Table'!$D$2:$E$1048576,2,0) -> MERCK | B238: 30792 | C238: (ARG) PO 8200873875 | D238: V940-002 (Local) | E238: 2025 | F238: 6 | G238: =+VLOOKUP(H238,Chi!#REF!,3,0) -> #REF! | H238: Freight - Returns | I238: 197.6414 | J238: USD | K238: =+VLOOKUP(J238,$W$2:$X$3,2,0)*I238 -> 197.6414 | L238: Argentina | M238: PO 8200873875 | O238: Merck Sharp and Dohme LLC | P238: =K238 -> 197.6414 | Q238: 45831 | S238: 40700 | T238: Revenues - Third Parties
A239: =+VLOOKUP(O239,'Selectable Table'!$D$2:$E$1048576,2,0) -> MERCK | B239: 30792 | C239: (ARG) PO 8200873875 | D239: V940-002 (Local) | E239: 2025 | F239: 6 | G239: =+VLOOKUP(H239,Chi!#REF!,3,0) -> #REF! | H239: Pick and Pack (Ambient) | I239: 151.9155 | J239: USD | K239: =+VLOOKUP(J239,$W$2:$X$3,2,0)*I239 -> 151.9155 | L239: Argentina | M239: PO 8200873875 | O239: Merck Sharp and Dohme LLC | P239: =K239 -> 151.9155 | Q239: 45831 | S239: 40700 | T239: Revenues - Third Parties
A240: =+VLOOKUP(O240,'Selectable Table'!$D$2:$E$1048576,2,0) -> MERCK | B240: 30792 | C240: (ARG) PO 8200873875 | D240: V940-002 (Local) | E240: 2025 | F240: 6 | G240: =+VLOOKUP(H240,Chi!#REF!,3,0) -> #REF! | H240: Reconciliation of Returns (per Hour) | I240: 65.4368 | J240: USD | K240: =+VLOOKUP(J240,$W$2:$X$3,2,0)*I240 -> 65.4368 | L240: Argentina | M240: PO 8200873875 | O240: Merck Sharp and Dohme LLC | P240: =K240 -> 65.4368 | Q240: 45831 | S240: 40700 | T240: Revenues - Third Parties
A241: =+VLOOKUP(O241,'Selectable Table'!$D$2:$E$1048576,2,0) -> MERCK | B241: 30792 | C241: (ARG) PO 8200873875 | D241: V940-002 (Local) | E241: 2025 | F241: 6 | G241: =+VLOOKUP(H241,Chi!#REF!,3,0) -> #REF! | H241: Returns Receipt (per Receipt) | I241: 163.592 | J241: USD | K241: =+VLOOKUP(J241,$W$2:$X$3,2,0)*I241 -> 163.592 | L241: Argentina | M241: PO 8200873875 | O241: Merck Sharp and Dohme LLC | P241: =K241 -> 163.592 | Q241: 45831 | S241: 40700 | T241: Revenues - Third Parties
A242: =+VLOOKUP(O242,'Selectable Table'!$D$2:$E$1048576,2,0) -> MERCK | B242: 30792 | C242: (ARG) PO 8200873875 | D242: V940-002 (Local) | E242: 2025 | F242: 6 | G242: Total Distribution | H242: Storage Ambient (per Pallet) | I242: 140.2269 | J242: USD | K242: =+VLOOKUP(J242,$W$2:$X$3,2,0)*I242 -> 140.2269 | L242: Argentina | M242: PO 8200873875 | O242: Merck Sharp and Dohme LLC | P242: =K242 -> 140.2269 | Q242: 45831 | S242: 40700 | T242: Revenues - Third Parties
A243: =+VLOOKUP(O243,'Selectable Table'!$D$2:$E$1048576,2,0) -> MERCK | B243: 30792 | C243: (ARG) PO 8200873875 | D243: V940-002 (Local) | E243: 2025 | F243: 6 | G243: =+VLOOKUP(H243,Chi!#REF!,3,0) -> #REF! | H243: Storage of Returns (per Pallet) | I243: 231.4246 | J243: USD | K243: =+VLOOKUP(J243,$W$2:$X$3,2,0)*I243 -> 231.4246 | L243: Argentina | M243: PO 8200873875 | O243: Merck Sharp and Dohme LLC | P243: =K243 -> 231.4246 | Q243: 45831 | S243: 40700 | T243: Revenues - Third Parties
A244: =+VLOOKUP(O244,'Selectable Table'!$D$2:$E$1048576,2,0) -> MERCK | B244: 30793 | C244: (ARG) PO 8200873875 | D244: MK-0616-013 (Local) | E244: 2025 | F244: 6 | G244: =+VLOOKUP(H244,Chi!#REF!,3,0) -> #REF! | H244: Reconciliation of Returns (per Hour) | I244: 65.4368 | J244: USD | K244: =+VLOOKUP(J244,$W$2:$X$3,2,0)*I244 -> 65.4368 | L244: Argentina | M244: PO 8200873875 | O244: Merck Sharp and Dohme LLC | P244: =K244 -> 65.4368 | Q244: 45831 | S244: 40700 | T244: Revenues - Third Parties
A245: =+VLOOKUP(O245,'Selectable Table'!$D$2:$E$1048576,2,0) -> MERCK | B245: 30793 | C245: (ARG) PO 8200873875 | D245: MK-0616-013 (Local) | E245: 2025 | F245: 6 | G245: =+VLOOKUP(H245,Chi!#REF!,3,0) -> #REF! | H245: Returns Receipt (per Receipt) | I245: 163.592 | J245: USD | K245: =+VLOOKUP(J245,$W$2:$X$3,2,0)*I245 -> 163.592 | L245: Argentina | M245: PO 8200873875 | O245: Merck Sharp and Dohme LLC | P245: =K245 -> 163.592 | Q245: 45831 | S245: 40700 | T245: Revenues - Third Parties
A246: =+VLOOKUP(O246,'Selectable Table'!$D$2:$E$1048576,2,0) -> MERCK | B246: 30793 | C246: (ARG) PO 8200873875 | D246: MK-0616-013 (Local) | E246: 2025 | F246: 6 | G246: =+VLOOKUP(H246,Chi!#REF!,3,0) -> #REF! | H246: Storage of Returns (per Pallet) | I246: 462.8492 | J246: USD | K246: =+VLOOKUP(J246,$W$2:$X$3,2,0)*I246 -> 462.8492 | L246: Argentina | M246: PO 8200873875 | O246: Merck Sharp and Dohme LLC | P246: =K246 -> 462.8492 | Q246: 45831 | S246: 40700 | T246: Revenues - Third Parties
A247: =+VLOOKUP(O247,'Selectable Table'!$D$2:$E$1048576,2,0) -> MERCK | B247: 30794 | C247: (ARG) PO 8200873875 | D247: MK-3475A-F11 (Local) | E247: 2025 | F247: 6 | G247: =+VLOOKUP(H247,Chi!#REF!,3,0) -> #REF! | H247: Reconciliation of Returns (per Hour) | I247: 65.4368 | J247: USD | K247: =+VLOOKUP(J247,$W$2:$X$3,2,0)*I247 -> 65.4368 | L247: Argentina | M247: PO 8200873875 | O247: Merck Sharp and Dohme LLC | P247: =K247 -> 65.4368 | Q247: 45831 | S247: 40700 | T247: Revenues - Third Parties
A248: =+VLOOKUP(O248,'Selectable Table'!$D$2:$E$1048576,2,0) -> MERCK | B248: 30794 | C248: (ARG) PO 8200873875 | D248: MK-3475A-F11 (Local) | E248: 2025 | F248: 6 | G248: =+VLOOKUP(H248,Chi!#REF!,3,0) -> #REF! | H248: Returns Receipt (per Receipt) | I248: 163.592 | J248: USD | K248: =+VLOOKUP(J248,$W$2:$X$3,2,0)*I248 -> 163.592 | L248: Argentina | M248: PO 8200873875 | O248: Merck Sharp and Dohme LLC | P248: =K248 -> 163.592 | Q248: 45831 | S248: 40700 | T248: Revenues - Third Parties
A249: =+VLOOKUP(O249,'Selectable Table'!$D$2:$E$1048576,2,0) -> MERCK | B249: 30794 | C249: (ARG) PO 8200873875 | D249: MK-3475A-F11 (Local) | E249: 2025 | F249: 6 | G249: =+VLOOKUP(H249,Chi!#REF!,3,0) -> #REF! | H249: Storage Ambient (per Pallet) | I249: 140.2269 | J249: USD | K249: =+VLOOKUP(J249,$W$2:$X$3,2,0)*I249 -> 140.2269 | L249: Argentina | M249: PO 8200873875 | O249: Merck Sharp and Dohme LLC | P249: =K249 -> 140.2269 | Q249: 45831 | S249: 40700 | T249: Revenues - Third Parties
A250: =+VLOOKUP(O250,'Selectable Table'!$D$2:$E$1048576,2,0) -> MERCK | B250: 30794 | C250: (ARG) PO 8200873875 | D250: MK-3475A-F11 (Local) | E250: 2025 | F250: 6 | G250: =+VLOOKUP(H250,Chi!#REF!,3,0) -> #REF! | H250: Storage of Returns (per Pallet) | I250: 115.7123 | J250: USD | K250: =+VLOOKUP(J250,$W$2:$X$3,2,0)*I250 -> 115.7123 | L250: Argentina | M250: PO 8200873875 | O250: Merck Sharp and Dohme LLC | P250: =K250 -> 115.7123 | Q250: 45831 | S250: 40700 | T250: Revenues - Third Parties
A251: =+VLOOKUP(O251,'Selectable Table'!$D$2:$E$1048576,2,0) -> MERCK | B251: 30795 | C251: 58474 - ARG PO#8200873875 | D251: MK-6194-007 (Local) | E251: 2025 | F251: 6 | G251: =+VLOOKUP(H251,Chi!#REF!,3,0) -> #REF! | H251: Storage Ambient (per Pallet) | I251: 140.2269 | J251: USD | K251: =+VLOOKUP(J251,$W$2:$X$3,2,0)*I251 -> 140.2269 | L251: Argentina | M251: PO#8200873875 | O251: Merck Sharp and Dohme LLC | P251: =K251 -> 140.2269 | Q251: 45831 | S251: 40700 | T251: Revenues - Third Parties
A252: =+VLOOKUP(O252,'Selectable Table'!$D$2:$E$1048576,2,0) -> MERCK | B252: 30795 | C252: 58474 - ARG PO#8200873875 | D252: MK-6194-007 (Local) | E252: 2025 | F252: 6 | G252: =+VLOOKUP(H252,Chi!#REF!,3,0) -> #REF! | H252: Storage of Returns (per Pallet) | I252: 231.4246 | J252: USD | K252: =+VLOOKUP(J252,$W$2:$X$3,2,0)*I252 -> 231.4246 | L252: Argentina | M252: PO#8200873875 | O252: Merck Sharp and Dohme LLC | P252: =K252 -> 231.4246 | Q252: 45831 | S252: 40700 | T252: Revenues - Third Parties
A253: =+VLOOKUP(O253,'Selectable Table'!$D$2:$E$1048576,2,0) -> MERCK | B253: 30796 | C253: (ARG) PO 8200873875 | D253: MK-6194-006 (Local) | E253: 2025 | F253: 6 | G253: =+VLOOKUP(H253,Chi!#REF!,3,0) -> #REF! | H253: Storage Ambient (per Pallet) | I253: 140.2269 | J253: USD | K253: =+VLOOKUP(J253,$W$2:$X$3,2,0)*I253 -> 140.2269 | L253: Argentina | M253: PO 8200873875 | O253: Merck Sharp and Dohme LLC | P253: =K253 -> 140.2269 | Q253: 45831 | S253: 40700 | T253: Revenues - Third Parties
A254: =+VLOOKUP(O254,'Selectable Table'!$D$2:$E$1048576,2,0) -> MERCK | B254: 30797 | C254: 58474 - ARG PO#8200873875 | D254: MK-7240-001 (Local) | E254: 2025 | F254: 6 | G254: =+VLOOKUP(H254,Chi!#REF!,3,0) -> #REF! | H254: Emergency Pick and Pack fee (Add per Pick and Pack) | I254: 75.9517 | J254: USD | K254: =+VLOOKUP(J254,$W$2:$X$3,2,0)*I254 -> 75.9517 | L254: Argentina | M254: PO#8200873875 | O254: Merck Sharp and Dohme LLC | P254: =K254 -> 75.9517 | Q254: 45831 | S254: 40700 | T254: Revenues - Third Parties
... A330: =+VLOOKUP(O330,'Selectable Table'!$D$2:$E$1048576,2,0) -> MERCK | B330: 30816 | C330: (ARG) PO 8200873875 | D330: MK-2140-010 (Local) | E330: 2025 | F330: 6 | G330: =+VLOOKUP(H330,Chi!#REF!,3,0) -> #REF! | H330: Freight - Shipments | I330: 4709.4168 | J330: USD | K330: =+VLOOKUP(J330,$W$2:$X$3,2,0)*I330 -> 4709.4168 | L330: Argentina | M330: PO 8200873875 | O330: Merck Sharp and Dohme LLC | P330: =K330 -> 4709.4168 | Q330: 45831 | S330: 40700 | T330: Revenues - Third Parties
A331: =+VLOOKUP(O331,'Selectable Table'!$D$2:$E$1048576,2,0) -> MERCK | B331: 30816 | C331: (ARG) PO 8200873875 | D331: MK-2140-010 (Local) | E331: 2025 | F331: 6 | G331: Total Distribution | H331: Pick and Pack (Ambient) | I331: 455.7465 | J331: USD | K331: =+VLOOKUP(J331,$W$2:$X$3,2,0)*I331 -> 455.7465 | L331: Argentina | M331: PO 8200873875 | O331: Merck Sharp and Dohme LLC | P331: =K331 -> 455.7465 | Q331: 45831 | S331: 40700 | T331: Revenues - Third Parties
A332: =+VLOOKUP(O332,'Selectable Table'!$D$2:$E$1048576,2,0) -> MERCK | B332: 30816 | C332: (ARG) PO 8200873875 | D332: MK-2140-010 (Local) | E332: 2025 | F332: 6 | G332: =+VLOOKUP(H332,Chi!#REF!,3,0) -> #REF! | H332: Pick and Pack (Controlled Ambient) | I332: 911.493 | J332: USD | K332: =+VLOOKUP(J332,$W$2:$X$3,2,0)*I332 -> 911.493 | L332: Argentina | M332: PO 8200873875 | O332: Merck Sharp and Dohme LLC | P332: =K332 -> 911.493 | Q332: 45831 | S332: 40700 | T332: Revenues - Third Parties
A333: =+VLOOKUP(O333,'Selectable Table'!$D$2:$E$1048576,2,0) -> MERCK | B333: 30816 | C333: (ARG) PO 8200873875 | D333: MK-2140-010 (Local) | E333: 2025 | F333: 6 | G333: =+VLOOKUP(H333,Chi!#REF!,3,0) -> #REF! | H333: Pick and Pack (Refrigerated) | I333: 1093.719 | J333: USD | K333: =+VLOOKUP(J333,$W$2:$X$3,2,0)*I333 -> 1093.719 | L333: Argentina | M333: PO 8200873875 | O333: Merck Sharp and Dohme LLC | P333: =K333 -> 1093.719 | Q333: 45831 | S333: 40700 | T333: Revenues - Third Parties
A334: =+VLOOKUP(O334,'Selectable Table'!$D$2:$E$1048576,2,0) -> MERCK | B334: 30816 | C334: (ARG) PO 8200873875 | D334: MK-2140-010 (Local) | E334: 2025 | F334: 6 | G334: =+VLOOKUP(H334,Chi!#REF!,3,0) -> #REF! | H334: Pick and Pack Materials | I334: 455.7465 | J334: USD | K334: =+VLOOKUP(J334,$W$2:$X$3,2,0)*I334 -> 455.7465 | L334: Argentina | M334: PO 8200873875 | O334: Merck Sharp and Dohme LLC | P334: =K334 -> 455.7465 | Q334: 45831 | S334: 40700 | T334: Revenues - Third Parties
A335: =+VLOOKUP(O335,'Selectable Table'!$D$2:$E$1048576,2,0) -> MERCK | B335: 30816 | C335: (ARG) PO 8200873875 | D335: MK-2140-010 (Local) | E335: 2025 | F335: 6 | G335: =+VLOOKUP(H335,Chi!#REF!,3,0) -> #REF! | H335: Refurbishment (per Shipper) | I335: 841.7244 | J335: USD | K335: =+VLOOKUP(J335,$W$2:$X$3,2,0)*I335 -> 841.7244 | L335: Argentina | M335: PO 8200873875 | O335: Merck Sharp and Dohme LLC | P335: =K335 -> 841.7244 | Q335: 45831 | S335: 40700 | T335: Revenues - Third Parties
A336: =+VLOOKUP(O336,'Selectable Table'!$D$2:$E$1048576,2,0) -> MERCK | B336: 30816 | C336: (ARG) PO 8200873875 | D336: MK-2140-010 (Local) | E336: 2025 | F336: 6 | G336: =+VLOOKUP(H336,Chi!#REF!,3,0) -> #REF! | H336: Storage Ambient (per Pallet) | I336: 462.8492 | J336: USD | K336: =+VLOOKUP(J336,$W$2:$X$3,2,0)*I336 -> 462.8492 | L336: Argentina | M336: PO 8200873875 | O336: Merck Sharp and Dohme LLC | P336: =K336 -> 462.8492 | Q336: 45831 | S336: 40700 | T336: Revenues - Third Parties
A337: =+VLOOKUP(O337,'Selectable Table'!$D$2:$E$1048576,2,0) -> MERCK | B337: 30816 | C337: (ARG) PO 8200873875 | D337: MK-2140-010 (Local) | E337: 2025 | F337: 6 | G337: =+VLOOKUP(H337,Chi!#REF!,3,0) -> #REF! | H337: Storage of Labels Ambient (per Pallet) | I337: 115.7123 | J337: USD | K337: =+VLOOKUP(J337,$W$2:$X$3,2,0)*I337 -> 115.7123 | L337: Argentina | M337: PO 8200873875 | O337: Merck Sharp and Dohme LLC | P337: =K337 -> 115.7123 | Q337: 45831 | S337: 40700 | T337: Revenues - Third Parties
A338: =+VLOOKUP(O338,'Selectable Table'!$D$2:$E$1048576,2,0) -> MERCK | B338: 30816 | C338: (ARG) PO 8200873875 | D338: MK-2140-010 (Local) | E338: 2025 | F338: 6 | G338: Total Distribution | H338: Storage Refrigerated (per Shelf) | I338: 630.9666 | J338: USD | K338: =+VLOOKUP(J338,$W$2:$X$3,2,0)*I338 -> 630.9666 | L338: Argentina | M338: PO 8200873875 | O338: Merck Sharp and Dohme LLC | P338: =K338 -> 630.9666 | Q338: 45831 | S338: 40700 | T338: Revenues - Third Parties
A339: =+VLOOKUP(O339,'Selectable Table'!$D$2:$E$1048576,2,0) -> MERCK | B339: 30817 | C339: (ARG) PO 8200873875 | D339: MK-2870-011 (Local) | E339: 2025 | F339: 6 | G339: =+VLOOKUP(H339,Chi!#REF!,3,0) -> #REF! | H339: Pick and Pack (Ambient) | I339: 303.831 | J339: USD | K339: =+VLOOKUP(J339,$W$2:$X$3,2,0)*I339 -> 303.831 | L339: Argentina | M339: PO 8200873875 | O339: Merck Sharp and Dohme LLC | P339: =K339 -> 303.831 | Q339: 45831 | S339: 40700 | T339: Revenues - Third Parties
A340: =+VLOOKUP(O340,'Selectable Table'!$D$2:$E$1048576,2,0) -> MERCK | B340: 30817 | C340: (ARG) PO 8200873875 | D340: MK-2870-011 (Local) | E340: 2025 | F340: 6 | G340: =+VLOOKUP(H340,Chi!#REF!,3,0) -> #REF! | H340: Pick and Pack Materials | I340: 607.662 | J340: USD | K340: =+VLOOKUP(J340,$W$2:$X$3,2,0)*I340 -> 607.662 | L340: Argentina | M340: PO 8200873875 | O340: Merck Sharp and Dohme LLC | P340: =K340 -> 607.662 | Q340: 45831 | S340: 40700 | T340: Revenues - Third Parties
A341: =+VLOOKUP(O341,'Selectable Table'!$D$2:$E$1048576,2,0) -> MERCK | B341: 30817 | C341: (ARG) PO 8200873875 | D341: MK-2870-011 (Local) | E341: 2025 | F341: 6 | G341: =+VLOOKUP(H341,Chi!#REF!,3,0) -> #REF! | H341: Receipt fee Ambient (per Receipt_ID) | I341: 151.9155 | J341: USD | K341: =+VLOOKUP(J341,$W$2:$X$3,2,0)*I341 -> 151.9155 | L341: Argentina | M341: PO 8200873875 | O341: Merck Sharp and Dohme LLC | P341: =K341 -> 151.9155 | Q341: 45831 | S341: 40700 | T341: Revenues - Third Parties
A342: =+VLOOKUP(O342,'Selectable Table'!$D$2:$E$1048576,2,0) -> MERCK | B342: 30817 | C342: (ARG) PO 8200873875 | D342: MK-2870-011 (Local) | E342: 2025 | F342: 6 | G342: =+VLOOKUP(H342,Chi!#REF!,3,0) -> #REF! | H342: Receipt fee Ancillaries (per Receipt_ID) | I342: 151.9155 | J342: USD | K342: =+VLOOKUP(J342,$W$2:$X$3,2,0)*I342 -> 151.9155 | L342: Argentina | M342: PO 8200873875 | O342: Merck Sharp and Dohme LLC | P342: =K342 -> 151.9155 | Q342: 45831 | S342: 40700 | T342: Revenues - Third Parties
A343: =+VLOOKUP(O343,'Selectable Table'!$D$2:$E$1048576,2,0) -> MERCK | B343: 30817 | C343: (ARG) PO 8200873875 | D343: MK-2870-011 (Local) | E343: 2025 | F343: 6 | G343: =+VLOOKUP(H343,Chi!#REF!,3,0) -> #REF! | H343: Storage Ambient (per Pallet) | I343: 115.7123 | J343: USD | K343: =+VLOOKUP(J343,$W$2:$X$3,2,0)*I343 -> 115.7123 | L343: Argentina | M343: PO 8200873875 | O343: Merck Sharp and Dohme LLC | P343: =K343 -> 115.7123 | Q343: 45831 | S343: 40700 | T343: Revenues - Third Parties
A344: =+VLOOKUP(O344,'Selectable Table'!$D$2:$E$1048576,2,0) -> MERCK | B344: 30818 | C344: (ARG) PO 8200873875 | D344: V940-011 (Local) | E344: 2025 | F344: 6 | G344: =+VLOOKUP(H344,Chi!#REF!,3,0) -> #REF! | H344: Freight - Shipments | I344: 121.3025 | J344: USD | K344: =+VLOOKUP(J344,$W$2:$X$3,2,0)*I344 -> 121.3025 | L344: Argentina | M344: PO 8200873875 | O344: Merck Sharp and Dohme LLC | P344: =K344 -> 121.3025 | Q344: 45831 | S344: 40700 | T344: Revenues - Third Parties
A345: =+VLOOKUP(O345,'Selectable Table'!$D$2:$E$1048576,2,0) -> MERCK | B345: 30818 | C345: (ARG) PO 8200873875 | D345: V940-011 (Local) | E345: 2025 | F345: 6 | G345: =+VLOOKUP(H345,Chi!#REF!,3,0) -> #REF! | H345: Storage Ambient (per Pallet) | I345: 115.7123 | J345: USD | K345: =+VLOOKUP(J345,$W$2:$X$3,2,0)*I345 -> 115.7123 | L345: Argentina | M345: PO 8200873875 | O345: Merck Sharp and Dohme LLC | P345: =K345 -> 115.7123 | Q345: 45831 | S345: 40700 | T345: Revenues - Third Parties
A346: =+VLOOKUP(O346,'Selectable Table'!$D$2:$E$1048576,2,0) -> MERCK | B346: 30819 | C346: (ARG) PO 8200873875 | D346: MK-2400-001 (Local) | E346: 2025 | F346: 6 | G346: =+VLOOKUP(H346,Chi!#REF!,3,0) -> #REF! | H346: Pick and Pack (Ambient) | I346: 455.7465 | J346: USD | K346: =+VLOOKUP(J346,$W$2:$X$3,2,0)*I346 -> 455.7465 | L346: Argentina | M346: PO 8200873875 | O346: Merck Sharp and Dohme LLC | P346: =K346 -> 455.7465 | Q346: 45831 | S346: 40700 | T346: Revenues - Third Parties
A347: =+VLOOKUP(O347,'Selectable Table'!$D$2:$E$1048576,2,0) -> MERCK | B347: 30819 | C347: (ARG) PO 8200873875 | D347: MK-2400-001 (Local) | E347: 2025 | F347: 6 | G347: Total Distribution | H347: Pick and Pack Materials | I347: 455.7465 | J347: USD | K347: =+VLOOKUP(J347,$W$2:$X$3,2,0)*I347 -> 455.7465 | L347: Argentina | M347: PO 8200873875 | O347: Merck Sharp and Dohme LLC | P347: =K347 -> 455.7465 | Q347: 45831 | S347: 40700 | T347: Revenues - Third Parties
...

Sheet TrasnP (2)
A1: CUSTOMER | B1: INVOICE_. | C1: FISHER_JOB | D1: PROTOCOL | E1: yr | F1: period | G1: PRODUCT | H1: SUB-PRODUCT | I1: DocValue | J1: DOC_CURRENCY | K1: USD Value | L1: FISHER_LOC | M1: PO. | N1: doccode | O1: el4_name | P1: Home Currency | Q1: docdate | R1: ref1 | S1: el2 | T1: el2_name | U1: el3 | W1: DOC_CURRENCY | X1: BS May | Z1: Sponsor de Revenue | AT1: NO TOCAR
A2: =+VLOOKUP(O2,'Selectable Table'!D:E,2,0) -> ELI LILLY | B2: 5415166 | C2: PARG57830 | D2: I5T-MC-AACO (CAM) | E2: 2025 | F2: 6 | G2: totalStorage | H2: Storage | I2: -22.932 | J2: USD | K2: =+VLOOKUP(J2,$W$2:$X$7,2,0)*I2 -> -22.932 | L2: BSLATAMTP | M2: 4200451914 | O2: ELI LILLY AND CO | P2: =K2 -> -22.932 | Q2: 45831 | S2: 40700 | T2: Revenues - Third Parties | W2: USD | X2: 1
A3: =+VLOOKUP(O3,'Selectable Table'!D:E,2,0) -> ELI LILLY | B3: 5415166 | C3: PARG57830 | D3: I5T-MC-AACO (CAM) | E3: 2025 | F3: 6 | G3: totalDistribution | H3: Distribution | I3: 3.9 | J3: USD | K3: =+VLOOKUP(J3,$W$2:$X$7,2,0)*I3 -> 3.9 | L3: BSLATAMTP | M3: 4200451914 | O3: ELI LILLY AND CO | P3: =K3 -> 3.9 | Q3: 45831 | S3: 40700 | T3: Revenues - Third Parties | W3: EUR | X3: 1.12694
A4: =+VLOOKUP(O4,'Selectable Table'!D:E,2,0) -> OTH CUST | B4: 5413135 | C4: PARG87129 | D4: J1I-MC-GZBP (CAM) | E4: 2025 | F4: 6 | G4: totalFreight | H4: Freight | I4: -840 | J4: USD | K4: =+VLOOKUP(J4,$W$2:$X$7,2,0)*I4 -> -840 | L4: BSLATAMTP | M4: E005473054 | O4: FISHER CLINICAL SERV | P4: =K4 -> -840 | Q4: 45824 | S4: 40700 | T4: Revenues - Third Parties | W4: CHF | X4: 1.20482
A5: =+VLOOKUP(O5,'Selectable Table'!D:E,2,0) -> DEBIOPHARM | B5: 5415165 | C5: PARG84773 | D5: J1I-MC-GZBP (CAM) | E5: 2025 | F5: 6 | G5: totalStorage | H5: Storage | I5: -262.74 | J5: USD | K5: =+VLOOKUP(J5,$W$2:$X$7,2,0)*I5 -> -262.74 | L5: BSLATAMTP | M5: PO-23-0179 | O5: DEBIOPHARM INTL SA | P5: =K5 -> -262.74 | Q5: 45831 | S5: 40700 | T5: Revenues - Third Parties | W5: CLP | X5: 0.00106
A6: =+VLOOKUP(O6,'Selectable Table'!D:E,2,0) -> ELI LILLY | B6: 5415166 | C6: PARG57830 | D6: J1I-MC-GZBP (CAM) | E6: 2025 | F6: 6 | G6: totalDistribution | H6: Distribution | I6: -15537.984 | J6: USD | K6: =+VLOOKUP(J6,$W$2:$X$7,2,0)*I6 -> -15537.984 | L6: BSLATAMTP | M6: 4200451914 | O6: ELI LILLY AND CO | P6: =K6 -> -15537.984 | Q6: 45831 | S6: 40700 | T6: Revenues - Third Parties | W6: GBP | X6: 1.33461
A7: =+VLOOKUP(O7,'Selectable Table'!D:E,2,0) -> ELI LILLY | B7: 5415166 | C7: PARG57830 | D7: J1I-MC-GZBP (CAM) | E7: 2025 | F7: 6 | G7: totalDistribution | H7: Distribution | I7: -441.44 | J7: USD | K7: =+VLOOKUP(J7,$W$2:$X$7,2,0)*I7 -> -441.44 | L7: BSLATAMTP | M7: 4200451914 | O7: ELI LILLY AND CO | P7: =K7 -> -441.44 | Q7: 45831 | S7: 40700 | T7: Revenues - Third Parties | W7: BRL | X7: 0.17643
A8: =+VLOOKUP(O8,'Selectable Table'!D:E,2,0) -> ELI LILLY | B8: 5415166 | C8: PARG57830 | D8: J1I-MC-GZQD (CAM) | E8: 2025 | F8: 6 | G8: totalStorage | H8: Storage | I8: -5591.32 | J8: USD | K8: =+VLOOKUP(J8,$W$2:$X$7,2,0)*I8 -> -5591.32 | L8: BSLATAMTP | M8: 4200451914 | O8: ELI LILLY AND CO | P8: =K8 -> -5591.32 | Q8: 45831 | S8: 40700 | T8: Revenues - Third Parties
A9: =+VLOOKUP(O9,'Selectable Table'!D:E,2,0) -> ELI LILLY | B9: 5415166 | C9: PARG57830 | D9: J1I-MC-GZQD (CAM) | E9: 2025 | F9: 6 | G9: totalDistribution | H9: Distribution | I9: -6936.6 | J9: USD | K9: =+VLOOKUP(J9,$W$2:$X$7,2,0)*I9 -> -6936.6 | L9: BSLATAMTP | M9: 4200451914 | O9: ELI LILLY AND CO | P9: =K9 -> -6936.6 | Q9: 45831 | S9: 40700 | T9: Revenues - Third Parties
A10: =+VLOOKUP(O10,'Selectable Table'!D:E,2,0) -> ELI LILLY | B10: 5415166 | C10: PARG57830 | D10: J1I-MC-GZQD (CAM) | E10: 2025 | F10: 6 | G10: totalDistribution | H10: Distribution | I10: -8961.232 | J10: USD | K10: =+VLOOKUP(J10,$W$2:$X$7,2,0)*I10 -> -8961.232 | L10: BSLATAMTP | M10: 4200451914 | O10: ELI LILLY AND CO | P10: =K10 -> -8961.232 | Q10: 45831 | S10: 40700 | T10: Revenues - Third Parties
A11: =+VLOOKUP(O11,'Selectable Table'!D:E,2,0) -> ELI LILLY | B11: 5415166 | C11: PARG57830 | D11: I8F-MC-GPJD (CAM) | E11: 2025 | F11: 6 | G11: totalDistribution | H11: Distribution | I11: -258.228 | J11: USD | K11: =+VLOOKUP(J11,$W$2:$X$7,2,0)*I11 -> -258.228 | L11: BSLATAMTP | M11: 4200451914 | O11: ELI LILLY AND CO | P11: =K11 -> -258.228 | Q11: 45831 | S11: 40700 | T11: Revenues - Third Parties
A12: =+VLOOKUP(O12,'Selectable Table'!D:E,2,0) -> ELI LILLY | B12: 5415166 | C12: PARG57830 | D12: I8F-MC-GPJD (CAM) | E12: 2025 | F12: 6 | G12: totalStorage | H12: Storage | I12: -209.68 | J12: USD | K12: =+VLOOKUP(J12,$W$2:$X$7,2,0)*I12 -> -209.68 | L12: BSLATAMTP | M12: 4200451914 | O12: ELI LILLY AND CO | P12: =K12 -> -209.68 | Q12: 45831 | S12: 40700 | T12: Revenues - Third Parties
A13: =+VLOOKUP(O13,'Selectable Table'!D:E,2,0) -> ELI LILLY | B13: 5415166 | C13: PARG57830 | D13: I8F-MC-GPJD (CAM) | E13: 2025 | F13: 6 | G13: totalDistribution | H13: Distribution | I13: -1898.192 | J13: USD | K13: =+VLOOKUP(J13,$W$2:$X$7,2,0)*I13 -> -1898.192 | L13: BSLATAMTP | M13: 4200451914 | O13: ELI LILLY AND CO | P13: =K13 -> -1898.192 | Q13: 45831 | S13: 40700 | T13: Revenues - Third Parties
A14: =+VLOOKUP(O14,'Selectable Table'!D:E,2,0) -> ELI LILLY | B14: 5415166 | C14: PARG57830 | D14: I8F-MC-GPJD (CAM) | E14: 2025 | F14: 6 | G14: totalDistribution | H14: Distribution | I14: -23352.176 | J14: USD | K14: =+VLOOKUP(J14,$W$2:$X$7,2,0)*I14 -> -23352.176 | L14: BSLATAMTP | M14: 4200451914 | O14: ELI LILLY AND CO | P14: =K14 -> -23352.176 | Q14: 45831 | S14: 40700 | T14: Revenues - Third Parties
A15: =+VLOOKUP(O15,'Selectable Table'!D:E,2,0) -> ELI LILLY | B15: 5415166 | C15: PARG57830 | D15: I8F-MC-GPJD (CAM) | E15: 2025 | F15: 6 | G15: totalDuties | H15: Duties | I15: -2306.48 | J15: USD | K15: =+VLOOKUP(J15,$W$2:$X$7,2,0)*I15 -> -2306.48 | L15: BSLATAMTP | M15: 4200451914 | O15: ELI LILLY AND CO | P15: =K15 -> -2306.48 | Q15: 45831 | S15: 40700 | T15: Revenues - Third Parties
A16: =+VLOOKUP(O16,'Selectable Table'!D:E,2,0) -> ELI LILLY | B16: 5415166 | C16: PARG57830 | D16: I8F-MC-GPJD (CAM) | E16: 2025 | F16: 6 | G16: totalDistribution | H16: Distribution | I16: -258.228 | J16: USD | K16: =+VLOOKUP(J16,$W$2:$X$7,2,0)*I16 -> -258.228 | L16: BSLATAMTP | M16: 4200451914 | O16: ELI LILLY AND CO | P16: =K16 -> -258.228 | Q16: 45831 | S16: 40700 | T16: Revenues - Third Parties
A17: =+VLOOKUP(O17,'Selectable Table'!D:E,2,0) -> OTH CUST | B17: 5415167 | C17: PARG44307 | D17: I8F-MC-GPJD (CAM) | E17: 2025 | F17: 6 | G17: totalDistribution | H17: Distribution | I17: -34.476 | J17: USD | K17: =+VLOOKUP(J17,$W$2:$X$7,2,0)*I17 -> -34.476 | L17: BSLATAMTP | M17: 7300837283 | O17: FISHER CLINICAL SERV | P17: =K17 -> -34.476 | Q17: 45831 | S17: 40700 | T17: Revenues - Third Parties
A18: =+VLOOKUP(O18,'Selectable Table'!D:E,2,0) -> OTH CUST | B18: 5415167 | C18: PARG44307 | D18: J2A-MC-GZPL (CAM) | E18: 2025 | F18: 6 | G18: totalDistribution | H18: Distribution | I18: -4715.952 | J18: USD | K18: =+VLOOKUP(J18,$W$2:$X$7,2,0)*I18 -> -4715.952 | L18: BSLATAMTP | M18: 7300837283 | O18: FISHER CLINICAL SERV | P18: =K18 -> -4715.952 | Q18: 45831 | S18: 40700 | T18: Revenues - Third Parties
A19: =+VLOOKUP(O19,'Selectable Table'!D:E,2,0) -> OTH CUST | B19: 5415167 | C19: PARG44307 | D19: J2A-MC-GZPL (CAM) | E19: 2025 | F19: 6 | G19: totalDuties | H19: Duties | I19: -1323.776 | J19: USD | K19: =+VLOOKUP(J19,$W$2:$X$7,2,0)*I19 -> -1323.776 | L19: BSLATAMTP | M19: 7300837283 | O19: FISHER CLINICAL SERV | P19: =K19 -> -1323.776 | Q19: 45831 | S19: 40700 | T19: Revenues - Third Parties
... A218: =+VLOOKUP(O218,'Selectable Table'!D:E,2,0) -> OTH CUST | B218: 5415384 | C218: PARG86512 | D218: MK-3475-587 | E218: 2025 | F218: 6 | G218: totalDistribution | H218: Distribution | I218: -161.856 | J218: USD | K218: =+VLOOKUP(J218,$W$2:$X$7,2,0)*I218 -> -161.856 | L218: BSLATAMTP | M218: 000308 | O218: 89bio, Inc. | P218: =K218 -> -161.856 | Q218: 45831 | S218: 40700 | T218: Revenues - Third Parties
A219: =+VLOOKUP(O219,'Selectable Table'!D:E,2,0) -> OTH CUST | B219: 5415387 | C219: PARG88105 | D219: MK-3475-587 | E219: 2025 | F219: 6 | G219: totalDistribution | H219: Distribution | I219: -1294.852 | J219: USD | K219: =+VLOOKUP(J219,$W$2:$X$7,2,0)*I219 -> -1294.852 | L219: BSLATAMTP | O219: FISHER CLINICAL SERV | P219: =K219 -> -1294.852 | Q219: 45831 | S219: 40700 | T219: Revenues - Third Parties
A220: =+VLOOKUP(O220,'Selectable Table'!D:E,2,0) -> OTH CUST | B220: 5415388 | C220: PARG83725 | D220: MK-3475-587 | E220: 2025 | F220: 6 | G220: totalDistribution | H220: Distribution | I220: -1336.088 | J220: USD | K220: =+VLOOKUP(J220,$W$2:$X$7,2,0)*I220 -> -1336.088 | L220: BSLATAMTP | M220: 9500854302 | O220: HORSHAM GBP | P220: =K220 -> -1336.088 | Q220: 45831 | S220: 40700 | T220: Revenues - Third Parties
A221: =+VLOOKUP(O221,'Selectable Table'!D:E,2,0) -> OTH CUST | B221: 5415388 | C221: PARG83725 | D221: MK-3475-587 | E221: 2025 | F221: 6 | G221: totalStorage | H221: Storage | I221: -151.624 | J221: USD | K221: =+VLOOKUP(J221,$W$2:$X$7,2,0)*I221 -> -151.624 | L221: BSLATAMTP | M221: 9500854302 | O221: HORSHAM GBP | P221: =K221 -> -151.624 | Q221: 45831 | S221: 40700 | T221: Revenues - Third Parties
A222: =+VLOOKUP(O222,'Selectable Table'!D:E,2,0) -> OTH CUST | B222: 5415390 | C222: PARG85608 | D222: MK-3475-587 | E222: 2025 | F222: 6 | G222: totalStorage | H222: Storage | I222: -330.944 | J222: USD | K222: =+VLOOKUP(J222,$W$2:$X$7,2,0)*I222 -> -330.944 | L222: BSLATAMTP | M222: 7300837279 | O222: Horizon Therapeutics | P222: =K222 -> -330.944 | Q222: 45831 | S222: 40700 | T222: Revenues - Third Parties
A223: =+VLOOKUP(O223,'Selectable Table'!D:E,2,0) -> OTH CUST | B223: 5415391 | C223: PARG83424 | D223: MK-3475-826 | E223: 2025 | F223: 6 | G223: totalStorage | H223: Storage | I223: -1137.184 | J223: USD | K223: =+VLOOKUP(J223,$W$2:$X$7,2,0)*I223 -> -1137.184 | L223: BSLATAMTP | M223: 9500854302 | O223: HORSHAM GBP | P223: =K223 -> -1137.184 | Q223: 45831 | S223: 40700 | T223: Revenues - Third Parties
A224: =+VLOOKUP(O224,'Selectable Table'!D:E,2,0) -> OTH CUST | B224: 5415392 | C224: PARG85685 | D224: MK-3475-826 | E224: 2025 | F224: 6 | G224: totalStorage | H224: Storage | I224: -59.324 | J224: USD | K224: =+VLOOKUP(J224,$W$2:$X$7,2,0)*I224 -> -59.324 | L224: BSLATAMTP | M224: C028_3900033677 | O224: Basel CHF | P224: =K224 -> -59.324 | Q224: 45831 | S224: 40700 | T224: Revenues - Third Parties
A225: =+VLOOKUP(O225,'Selectable Table'!D:E,2,0) -> OTH CUST | B225: 5415392 | C225: PARG85685 | D225: MK-7339-002 | E225: 2025 | F225: 6 | G225: totalStorage | H225: Storage | I225: -2.28 | J225: USD | K225: =+VLOOKUP(J225,$W$2:$X$7,2,0)*I225 -> -2.28 | L225: BSLATAMTP | M225: C028_3900033677 | O225: Basel CHF | P225: =K225 -> -2.28 | Q225: 45831 | S225: 40700 | T225: Revenues - Third Parties
A226: =+VLOOKUP(O226,'Selectable Table'!D:E,2,0) -> OTH CUST | B226: 5415394 | C226: PARG86954 | D226: MK-7339-002 | E226: 2025 | F226: 6 | G226: totalDistribution | H226: Distribution | I226: -156.88 | J226: USD | K226: =+VLOOKUP(J226,$W$2:$X$7,2,0)*I226 -> -156.88 | L226: BSLATAMTP | M226: 6053 | O226: FISHER - MT PROSPECT | P226: =K226 -> -156.88 | Q226: 45831 | S226: 40700 | T226: Revenues - Third Parties
A227: =+VLOOKUP(O227,'Selectable Table'!D:E,2,0) -> OTH CUST | B227: 5415394 | C227: PARG86954 | D227: MK-7339-002 | E227: 2025 | F227: 6 | G227: totalStorage | H227: Storage | I227: -392.184 | J227: USD | K227: =+VLOOKUP(J227,$W$2:$X$7,2,0)*I227 -> -392.184 | L227: BSLATAMTP | M227: 6053 | O227: FISHER - MT PROSPECT | P227: =K227 -> -392.184 | Q227: 45831 | S227: 40700 | T227: Revenues - Third Parties
A228: =+VLOOKUP(O228,'Selectable Table'!D:E,2,0) -> OTH CUST | B228: 5415395 | C228: PARG83534 | D228: MK-3475-630 | E228: 2025 | F228: 6 | G228: totalStorage | H228: Storage | I228: -149.408 | J228: USD | K228: =+VLOOKUP(J228,$W$2:$X$7,2,0)*I228 -> -149.408 | L228: BSLATAMTP | M228: 286 | O228: FISHER - BASEL | P228: =K228 -> -149.408 | Q228: 45831 | S228: 40700 | T228: Revenues - Third Parties
A229: =+VLOOKUP(O229,'Selectable Table'!D:E,2,0) -> OTH CUST | B229: 5415396 | C229: PARG84914 | D229: MK-3475-630 | E229: 2025 | F229: 6 | G229: totalDistribution | H229: Distribution | I229: -99.748 | J229: USD | K229: =+VLOOKUP(J229,$W$2:$X$7,2,0)*I229 -> -99.748 | L229: BSLATAMTP | M229: 0082549361 | O229: HORSHAM GBP | P229: =K229 -> -99.748 | Q229: 45831 | S229: 40700 | T229: Revenues - Third Parties
A230: =+VLOOKUP(O230,'Selectable Table'!D:E,2,0) -> OTH CUST | B230: 5415397 | C230: PARG87966 | D230: MK-3475-630 | E230: 2025 | F230: 6 | G230: totalDistribution | H230: Distribution | I230: -272.024 | J230: USD | K230: =+VLOOKUP(J230,$W$2:$X$7,2,0)*I230 -> -272.024 | L230: BSLATAMTP | M230: 6053 | O230: FISHER - MT PROSPECT | P230: =K230 -> -272.024 | Q230: 45831 | S230: 40700 | T230: Revenues - Third Parties
A231: =+VLOOKUP(O231,'Selectable Table'!D:E,2,0) -> OTH CUST | B231: 5415397 | C231: PARG87966 | D231: MK-3475-630 | E231: 2025 | F231: 6 | G231: totalDistribution | H231: Distribution | I231: -353.22 | J231: USD | K231: =+VLOOKUP(J231,$W$2:$X$7,2,0)*I231 -> -353.22 | L231: BSLATAMTP | M231: 6053 | O231: FISHER - MT PROSPECT | P231: =K231 -> -353.22 | Q231: 45831 | S231: 40700 | T231: Revenues - Third Parties
... A256: =+VLOOKUP(O256,'Selectable Table'!D:E,2,0) -> OTH CUST | B256: 5415424 | C256: PARG86357 | D256: MK-7339-008 | E256: 2025 | F256: 6 | G256: totalDistribution | H256: Distribution | I256: -227.44 | J256: USD | K256: =+VLOOKUP(J256,$W$2:$X$7,2,0)*I256 -> -227.44 | L256: BSLATAMTP | M256: 9500854302 | O256: HORSHAM GBP | P256: =K256 -> -227.44 | Q256: 45831 | S256: 40700 | T256: Revenues - Third Parties
A257: =+VLOOKUP(O257,'Selectable Table'!D:E,2,0) -> OTH CUST | B257: 5415425 | C257: PARG85353 | D257: MK-7339-008 | E257: 2025 | F257: 6 | G257: totalStorage | H257: Storage | I257: -224.104 | J257: USD | K257: =+VLOOKUP(J257,$W$2:$X$7,2,0)*I257 -> -224.104 | L257: BSLATAMTP | O257: Fisher AHMEDABAD | P257: =K257 -> -224.104 | Q257: 45831 | S257: 40700 | T257: Revenues - Third Parties
A258: =+VLOOKUP(O258,'Selectable Table'!D:E,2,0) -> OTH CUST | B258: 5415426 | C258: PARG85411 | D258: MK-7339-008 | E258: 2025 | F258: 6 | G258: totalStorage | H258: Storage | I258: -680.06 | J258: USD | K258: =+VLOOKUP(J258,$W$2:$X$7,2,0)*I258 -> -680.06 | L258: BSLATAMTP | M258: 400000162155 | O258: PPD Development LP | P258: =K258 -> -680.06 | Q258: 45831 | S258: 40700 | T258: Revenues - Third Parties
A259: =+VLOOKUP(O259,'Selectable Table'!D:E,2,0) -> OTH CUST | B259: 5415427 | C259: PARG86879 | D259: MK-7339-006 | E259: 2025 | F259: 6 | G259: totalFreight | H259: Freight | I259: -261.456 | J259: USD | K259: =+VLOOKUP(J259,$W$2:$X$7,2,0)*I259 -> -261.456 | L259: BSLATAMTP | M259: 4550003161 | O259: FISHER - BASEL | P259: =K259 -> -261.456 | Q259: 45831 | S259: 40700 | T259: Revenues - Third Parties
A260: =+VLOOKUP(O260,'Selectable Table'!D:E,2,0) -> OTH CUST | B260: 5415428 | C260: PARG85490 | D260: MK-7339-006 | E260: 2025 | F260: 6 | G260: totalStorage | H260: Storage | I260: -109.744 | J260: USD | K260: =+VLOOKUP(J260,$W$2:$X$7,2,0)*I260 -> -109.744 | L260: BSLATAMTP | M260: 7000068341 | O260: FISHER - MT PROSPECT | P260: =K260 -> -109.744 | Q260: 45831 | S260: 40700 | T260: Revenues - Third Parties
A261: =+VLOOKUP(O261,'Selectable Table'!D:E,2,0) -> OTH CUST | B261: 5415430 | C261: PARG85289 | D261: MK-7339-006 | E261: 2025 | F261: 6 | G261: totalDistribution | H261: Distribution | I261: -113.72 | J261: USD | K261: =+VLOOKUP(J261,$W$2:$X$7,2,0)*I261 -> -113.72 | L261: BSLATAMTP | M261: 4200500829 | O261: PSG - Memphis | P261: =K261 -> -113.72 | Q261: 45831 | S261: 40700 | T261: Revenues - Third Parties
A262: =+VLOOKUP(O262,'Selectable Table'!D:E,2,0) -> GILEAD SCI | B262: 5415432 | C262: PARG86001 | D262: MK-7339-006 | E262: 2025 | F262: 6 | G262: totalDistribution | H262: Distribution | I262: -365.824 | J262: USD | K262: =+VLOOKUP(J262,$W$2:$X$7,2,0)*I262 -> -365.824 | L262: BSLATAMTP | M262: 7000110235 | O262: GILEAD SCIENCES INC | P262: =K262 -> -365.824 | Q262: 45831 | S262: 40700 | T262: Revenues - Third Parties
A263: =+VLOOKUP(O263,'Selectable Table'!D:E,2,0) -> ASTRAZENECA | B263: 5415433 | C263: PARG88196 | D263: MK-7339-006 | E263: 2025 | F263: 6 | G263: totalDistribution | H263: Distribution | I263: -353.696 | J263: USD | K263: =+VLOOKUP(J263,$W$2:$X$7,2,0)*I263 -> -353.696 | L263: BSLATAMTP | M263: 7101376956 | O263: ASTRAZENCA | P263: =K263 -> -353.696 | Q263: 45831 | S263: 40700 | T263: Revenues - Third Parties
A264: =+VLOOKUP(O264,'Selectable Table'!D:E,2,0) -> ASTRAZENECA | B264: 5415433 | C264: PARG88196 | D264: MK-7339-006 | E264: 2025 | F264: 6 | G264: totalDistribution | H264: Distribution | I264: -252.928 | J264: USD | K264: =+VLOOKUP(J264,$W$2:$X$7,2,0)*I264 -> -252.928 | L264: BSLATAMTP | M264: 7101376956 | O264: ASTRAZENCA | P264: =K264 -> -252.928 | Q264: 45831 | S264: 40700 | T264: Revenues - Third Parties
A265: =+VLOOKUP(O265,'Selectable Table'!D:E,2,0) -> OTH CUST | B265: 5415436 | C265: PARG86352 | D265: MK-7339-006 | E265: 2025 | F265: 6 | G265: totalStorage | H265: Storage | I265: -379.06 | J265: USD | K265: =+VLOOKUP(J265,$W$2:$X$7,2,0)*I265 -> -379.06 | L265: BSLATAMTP | M265: 9500854302 | O265: HORSHAM GBP | P265: =K265 -> -379.06 | Q265: 45831 | S265: 40700 | T265: Revenues - Third Parties
A266: =+VLOOKUP(O266,'Selectable Table'!D:E,2,0) -> OTH CUST | B266: 5415439 | C266: PARG86646 | D266: MK-7339-006 | E266: 2025 | F266: 6 | G266: totalStorage | H266: Storage | I266: -653.64 | J266: USD | K266: =+VLOOKUP(J266,$W$2:$X$7,2,0)*I266 -> -653.64 | L266: BSLATAMTP | M266: 7000113634 | O266: FISHER - MT PROSPECT | P266: =K266 -> -653.64 | Q266: 45831 | S266: 40700 | T266: Revenues - Third Parties
A267: =+VLOOKUP(O267,'Selectable Table'!D:E,2,0) -> ASTRAZENECA | B267: 5415441 | C267: PARG87116 | D267: MK-3475-641 | E267: 2025 | F267: 6 | G267: totalFreight | H267: Freight | I267: -788.256 | J267: USD | K267: =+VLOOKUP(J267,$W$2:$X$7,2,0)*I267 -> -788.256 | L267: BSLATAMTP | M267: 7201343205 | O267: ASTRAZENECA(ZPG) | P267: =K267 -> -788.256 | Q267: 45831 | S267: 40700 | T267: Revenues - Third Parties
A268: =+VLOOKUP(O268,'Selectable Table'!D:E,2,0) -> ASTRAZENECA | B268: 5415441 | C268: PARG87116 | D268: MK-3475-641 | E268: 2025 | F268: 6 | G268: totalStorage | H268: Storage | I268: -86.4 | J268: USD | K268: =+VLOOKUP(J268,$W$2:$X$7,2,0)*I268 -> -86.4 | L268: BSLATAMTP | M268: 7201343205 | O268: ASTRAZENECA(ZPG) | P268: =K268 -> -86.4 | Q268: 45831 | S268: 40700 | T268: Revenues - Third Parties
A269: =+VLOOKUP(O269,'Selectable Table'!D:E,2,0) -> OTH CUST | B269: 5415442 | C269: PARG86888 | D269: MK-3475-641 | E269: 2025 | F269: 6 | G269: totalDistribution | H269: Distribution | I269: -365.824 | J269: USD | K269: =+VLOOKUP(J269,$W$2:$X$7,2,0)*I269 -> -365.824 | L269: BSLATAMTP | M269: 7000112181 | O269: FISHER - MT PROSPECT | P269: =K269 -> -365.824 | Q269: 45831 | S269: 40700 | T269: Revenues - Third Parties
... A298: =+VLOOKUP(O298,'Selectable Table'!D:E,2,0) -> OTH CUST | B298: 5415466 | C298: PARG88175 | D298: AC-055-315 | E298: 2025 | F298: 6 | G298: totalDistribution | H298: Distribution | I298: -950.188 | J298: USD | K298: =+VLOOKUP(J298,$W$2:$X$7,2,0)*I298 -> -950.188 | L298: BSLATAMTP | M298: 9500854302 | O298: HORSHAM GBP | P298: =K298 -> -950.188 | Q298: 45831 | S298: 40700 | T298: Revenues - Third Parties
A299: =+VLOOKUP(O299,'Selectable Table'!D:E,2,0) -> OTH CUST | B299: 5415469 | C299: PARG88293 | D299: AC-055-315 | E299: 2025 | F299: 6 | G299: totalStorage | H299: Storage | I299: -1020.488 | J299: USD | K299: =+VLOOKUP(J299,$W$2:$X$7,2,0)*I299 -> -1020.488 | L299: BSLATAMTP | O299: FISHER - BASEL | P299: =K299 -> -1020.488 | Q299: 45831 | S299: 40700 | T299: Revenues - Third Parties
A300: =+VLOOKUP(O300,'Selectable Table'!D:E,2,0) -> OTH CUST | B300: 5415469 | C300: PARG88293 | D300: MK-8591A-020 | E300: 2025 | F300: 6 | G300: totalStorage | H300: Storage | I300: -86.984 | J300: USD | K300: =+VLOOKUP(J300,$W$2:$X$7,2,0)*I300 -> -86.984 | L300: BSLATAMTP | O300: FISHER - BASEL | P300: =K300 -> -86.984 | Q300: 45831 | S300: 40700 | T300: Revenues - Third Parties
A301: =+VLOOKUP(O301,'Selectable Table'!D:E,2,0) -> IQVIA | B301: 5415470 | C301: PARG88093 | D301: MK-8591A-020 | E301: 2025 | F301: 6 | G301: totalStorage | H301: Storage | I301: -322.288 | J301: USD | K301: =+VLOOKUP(J301,$W$2:$X$7,2,0)*I301 -> -322.288 | L301: BSLATAMTP | M301: 298649 | O301: IQVIA RDS, Inc. | P301: =K301 -> -322.288 | Q301: 45831 | S301: 40700 | T301: Revenues - Third Parties
A302: =+VLOOKUP(O302,'Selectable Table'!D:E,2,0) -> IQVIA | B302: 5415470 | C302: PARG88093 | D302: MK-7264-042 | E302: 2025 | F302: 6 | G302: totalStorage | H302: Storage | I302: -367.348 | J302: USD | K302: =+VLOOKUP(J302,$W$2:$X$7,2,0)*I302 -> -367.348 | L302: BSLATAMTP | M302: 298649 | O302: IQVIA RDS, Inc. | P302: =K302 -> -367.348 | Q302: 45831 | S302: 40700 | T302: Revenues - Third Parties
A303: =+VLOOKUP(O303,'Selectable Table'!D:E,2,0) -> IQVIA | B303: 5415470 | C303: PARG88093 | D303: MK-7339-007 | E303: 2025 | F303: 6 | G303: totalDistribution | H303: Distribution | I303: -1007.16 | J303: USD | K303: =+VLOOKUP(J303,$W$2:$X$7,2,0)*I303 -> -1007.16 | L303: BSLATAMTP | M303: 298649 | O303: IQVIA RDS, Inc. | P303: =K303 -> -1007.16 | Q303: 45831 | S303: 40700 | T303: Revenues - Third Parties
A304: =+VLOOKUP(O304,'Selectable Table'!D:E,2,0) -> IQVIA | B304: 5415471 | C304: PARG88124 | D304: MK-7339-007 | E304: 2025 | F304: 6 | G304: totalStorage | H304: Storage | I304: -1007.16 | J304: USD | K304: =+VLOOKUP(J304,$W$2:$X$7,2,0)*I304 -> -1007.16 | L304: BSLATAMTP | M304: 304049 | O304: IQVIA RDS, Inc. | P304: =K304 -> -1007.16 | Q304: 45831 | S304: 40700 | T304: Revenues - Third Parties
A305: =+VLOOKUP(O305,'Selectable Table'!D:E,2,0) -> IQVIA | B305: 5415471 | C305: PARG88124 | D305: MK-3475-975 | E305: 2025 | F305: 6 | G305: totalStorage | H305: Storage | I305: -680.06 | J305: USD | K305: =+VLOOKUP(J305,$W$2:$X$7,2,0)*I305 -> -680.06 | L305: BSLATAMTP | M305: 304049 | O305: IQVIA RDS, Inc. | P305: =K305 -> -680.06 | Q305: 45831 | S305: 40700 | T305: Revenues - Third Parties
A306: =+VLOOKUP(O306,'Selectable Table'!D:E,2,0) -> IQVIA | B306: 5415471 | C306: PARG88124 | D306: MK-3475-975 | E306: 2025 | F306: 6 | G306: totalDistribution | H306: Distribution | I306: -353.22 | J306: USD | K306: =+VLOOKUP(J306,$W$2:$X$7,2,0)*I306 -> -353.22 | L306: BSLATAMTP | M306: 304049 | O306: IQVIA RDS, Inc. | P306: =K306 -> -353.22 | Q306: 45831 | S306: 40700 | T306: Revenues - Third Parties
A307: =+VLOOKUP(O307,'Selectable Table'!D:E,2,0) -> IQVIA | B307: 5415472 | C307: PARG88167 | D307: MK-3475-975 | E307: 2025 | F307: 6 | G307: totalStorage | H307: Storage | I307: -1007.16 | J307: USD | K307: =+VLOOKUP(J307,$W$2:$X$7,2,0)*I307 -> -1007.16 | L307: BSLATAMTP | M307: 299616 | O307: IQVIA RDS, Inc. | P307: =K307 -> -1007.16 | Q307: 45831 | S307: 40700 | T307: Revenues - Third Parties
A308: =+VLOOKUP(O308,'Selectable Table'!D:E,2,0) -> IQVIA | B308: 5415472 | C308: PARG88167 | D308: SGN22E-003 | E308: 2025 | F308: 6 | G308: totalFreight | H308: Freight | I308: -644.576 | J308: USD | K308: =+VLOOKUP(J308,$W$2:$X$7,2,0)*I308 -> -644.576 | L308: BSLATAMTP | M308: 299616 | O308: IQVIA RDS, Inc. | P308: =K308 -> -644.576 | Q308: 45831 | S308: 40700 | T308: Revenues - Third Parties
A309: =+VLOOKUP(O309,'Selectable Table'!D:E,2,0) -> IQVIA | B309: 5415472 | C309: PARG88167 | D309: SGN22E-003 | E309: 2025 | F309: 6 | G309: totalDistribution | H309: Distribution | I309: -367.348 | J309: USD | K309: =+VLOOKUP(J309,$W$2:$X$7,2,0)*I309 -> -367.348 | L309: BSLATAMTP | M309: 299616 | O309: IQVIA RDS, Inc. | P309: =K309 -> -367.348 | Q309: 45831 | S309: 40700 | T309: Revenues - Third Parties
A310: =+VLOOKUP(O310,'Selectable Table'!D:E,2,0) -> ASTRAZENECA | B310: 5415473 | C310: PARG88109 | D310: SGN22E-003 | E310: 2025 | F310: 6 | G310: totalDistribution | H310: Distribution | I310: -353.696 | J310: USD | K310: =+VLOOKUP(J310,$W$2:$X$7,2,0)*I310 -> -353.696 | L310: BSLATAMTP | M310: 7201406084 | O310: ASTRAZENECA(AMG) | P310: =K310 -> -353.696 | Q310: 45831 | S310: 40700 | T310: Revenues - Third Parties
A311: =+VLOOKUP(O311,'Selectable Table'!D:E,2,0) -> ASTRAZENECA | B311: 5415473 | C311: PARG88109 | D311: SGN22E-003 | E311: 2025 | F311: 6 | G311: totalDistribution | H311: Distribution | I311: -252.928 | J311: USD | K311: =+VLOOKUP(J311,$W$2:$X$7,2,0)*I311 -> -252.928 | L311: BSLATAMTP | M311: 7201406084 | O311: ASTRAZENECA(AMG) | P311: =K311 -> -252.928 | Q311: 45831 | S311: 40700 | T311: Revenues - Third Parties
A312: =+VLOOKUP(O312,'Selectable Table'!D:E,2,0) -> ELI LILLY | B312: 5415474 | C312: PARG88231 | D312: SGN22E-003 | E312: 2025 | F312: 6 | G312: totalStorage | H312: Storage | I312: -424.88 | J312: USD | K312: =+VLOOKUP(J312,$W$2:$X$7,2,0)*I312 -> -424.88 | L312: BSLATAMTP | M312: 4200471854 | O312: ELI LILLY AND CO | P312: =K312 -> -424.88 | Q312: 45831 | S312: 40700 | T312: Revenues - Third Parties
... A575: =+VLOOKUP(O575,'Selectable Table'!D:E,2,0) -> J & J | B575: 5415235 | C575: PARG78402 | D575: XL092-304 | E575: 2025 | F575: 6 | G575: totalFreight | H575: Freight | I575: -477.396 | J575: USD | K575: =+VLOOKUP(J575,$W$2:$X$7,2,0)*I575 -> -477.396 | L575: BSLATAMTP | M575: 994817603 | O575: Janssen R&D LLC | P575: =K575 -> -477.396 | Q575: 45831 | S575: 40700 | T575: Revenues - Third Parties
A576: =+VLOOKUP(O576,'Selectable Table'!D:E,2,0) -> OTH CUST | B576: 5415237 | C576: PARG76153 | D576: XL092-304 | E576: 2025 | F576: 6 | G576: totalDistribution | H576: Distribution | I576: -60.312 | J576: USD | K576: =+VLOOKUP(J576,$W$2:$X$7,2,0)*I576 -> -60.312 | L576: BSLATAMTP | O576: Fisher AHMEDABAD | P576: =K576 -> -60.312 | Q576: 45831 | S576: 40700 | T576: Revenues - Third Parties
A577: =+VLOOKUP(O577,'Selectable Table'!D:E,2,0) -> OTH CUST | B577: 5415237 | C577: PARG76153 | D577: XL092-304 | E577: 2025 | F577: 6 | G577: totalDistribution | H577: Distribution | I577: -688.224 | J577: USD | K577: =+VLOOKUP(J577,$W$2:$X$7,2,0)*I577 -> -688.224 | L577: BSLATAMTP | O577: Fisher AHMEDABAD | P577: =K577 -> -688.224 | Q577: 45831 | S577: 40700 | T577: Revenues - Third Parties
A578: =+VLOOKUP(O578,'Selectable Table'!D:E,2,0) -> OTH CUST | B578: 5415238 | C578: PARG76224 | D578: XL092-304 | E578: 2025 | F578: 6 | G578: totalDistribution | H578: Distribution | I578: -355.92 | J578: USD | K578: =+VLOOKUP(J578,$W$2:$X$7,2,0)*I578 -> -355.92 | L578: BSLATAMTP | M578: C028-3900028172 | O578: Basel CHF | P578: =K578 -> -355.92 | Q578: 45831 | S578: 40700 | T578: Revenues - Third Parties
A579: =+VLOOKUP(O579,'Selectable Table'!D:E,2,0) -> OTH CUST | B579: 5415238 | C579: PARG76224 | D579: XL092-304 | E579: 2025 | F579: 6 | G579: totalDistribution | H579: Distribution | I579: -22.816 | J579: USD | K579: =+VLOOKUP(J579,$W$2:$X$7,2,0)*I579 -> -22.816 | L579: BSLATAMTP | M579: C028-3900028172 | O579: Basel CHF | P579: =K579 -> -22.816 | Q579: 45831 | S579: 40700 | T579: Revenues - Third Parties
A580: =+VLOOKUP(O580,'Selectable Table'!D:E,2,0) -> OTH CUST | B580: 5415239 | C580: PARG78517 | D580: XL092-304 | E580: 2025 | F580: 6 | G580: totalDistribution | H580: Distribution | I580: -632.248 | J580: USD | K580: =+VLOOKUP(J580,$W$2:$X$7,2,0)*I580 -> -632.248 | L580: BSLATAMTP | M580: C028-3900028850 | O580: Basel CHF | P580: =K580 -> -632.248 | Q580: 45831 | S580: 40700 | T580: Revenues - Third Parties
A581: =+VLOOKUP(O581,'Selectable Table'!D:E,2,0) -> OTH CUST | B581: 5415239 | C581: PARG78517 | D581: XL092-304 | E581: 2025 | F581: 6 | G581: totalDistribution | H581: Distribution | I581: -468.3 | J581: USD | K581: =+VLOOKUP(J581,$W$2:$X$7,2,0)*I581 -> -468.3 | L581: BSLATAMTP | M581: C028-3900028850 | O581: Basel CHF | P581: =K581 -> -468.3 | Q581: 45831 | S581: 40700 | T581: Revenues - Third Parties
A582: =+VLOOKUP(O582,'Selectable Table'!D:E,2,0) -> OTH CUST | B582: 5415239 | C582: PARG78517 | D582: XL092-304 | E582: 2025 | F582: 6 | G582: totalDistribution | H582: Distribution | I582: -934.288 | J582: USD | K582: =+VLOOKUP(J582,$W$2:$X$7,2,0)*I582 -> -934.288 | L582: BSLATAMTP | M582: C028-3900028850 | O582: Basel CHF | P582: =K582 -> -934.288 | Q582: 45831 | S582: 40700 | T582: Revenues - Third Parties
A583: =+VLOOKUP(O583,'Selectable Table'!D:E,2,0) -> OTH CUST | B583: 5415240 | C583: PARG76514 | D583: XL092-304 | E583: 2025 | F583: 6 | G583: totalStorage | H583: Storage | I583: -234.148 | J583: USD | K583: =+VLOOKUP(J583,$W$2:$X$7,2,0)*I583 -> -234.148 | L583: BSLATAMTP | M583: C028-3900029141 | O583: Basel CHF | P583: =K583 -> -234.148 | Q583: 45831 | S583: 40700 | T583: Revenues - Third Parties
A584: =+VLOOKUP(O584,'Selectable Table'!D:E,2,0) -> OTH CUST | B584: 5415240 | C584: PARG76514 | D584: XL092-304 | E584: 2025 | F584: 6 | G584: totalStorage | H584: Storage | I584: -489.388 | J584: USD | K584: =+VLOOKUP(J584,$W$2:$X$7,2,0)*I584 -> -489.388 | L584: BSLATAMTP | M584: C028-3900029141 | O584: Basel CHF | P584: =K584 -> -489.388 | Q584: 45831 | S584: 40700 | T584: Revenues - Third Parties
A585: =+VLOOKUP(O585,'Selectable Table'!D:E,2,0) -> OTH CUST | B585: 5415241 | C585: PARG78814 | D585: XL092-304 | E585: 2025 | F585: 6 | G585: totalDistribution | H585: Distribution | I585: -210.748 | J585: USD | K585: =+VLOOKUP(J585,$W$2:$X$7,2,0)*I585 -> -210.748 | L585: BSLATAMTP | M585: C028-3900029088 | O585: Basel CHF | P585: =K585 -> -210.748 | Q585: 45831 | S585: 40700 | T585: Revenues - Third Parties
A586: =+VLOOKUP(O586,'Selectable Table'!D:E,2,0) -> OTH CUST | B586: 5415241 | C586: PARG78814 | D586: XL092-304 | E586: 2025 | F586: 6 | G586: totalDistribution | H586: Distribution | I586: -68.444 | J586: USD | K586: =+VLOOKUP(J586,$W$2:$X$7,2,0)*I586 -> -68.444 | L586: BSLATAMTP | M586: C028-3900029088 | O586: Basel CHF | P586: =K586 -> -68.444 | Q586: 45831 | S586: 40700 | T586: Revenues - Third Parties
A587: =+VLOOKUP(O587,'Selectable Table'!D:E,2,0) -> OTH CUST | B587: 5415242 | C587: PARG77171 | D587: 996 | E587: 2025 | F587: 6 | G587: totalDistribution | H587: Distribution | I587: -340.308 | J587: EUR | K587: =+VLOOKUP(J587,$W$2:$X$7,2,0)*I587 -> -383.5067 | L587: BSLATAMTP | M587: 7100358543-3 | O587: FISHER CLINICAL SERV | P587: =K587 -> -383.5067 | Q587: 45831 | S587: 40700 | T587: Revenues - Third Parties
A588: =+VLOOKUP(O588,'Selectable Table'!D:E,2,0) -> OTH CUST | B588: 5415243 | C588: PARG76764 | D588: 996 | E588: 2025 | F588: 6 | G588: totalDistribution | H588: Distribution | I588: -333.472 | J588: EUR | K588: =+VLOOKUP(J588,$W$2:$X$7,2,0)*I588 -> -375.80294 | L588: BSLATAMTP | M588: 9500854302 | O588: HORSHAM GBP | P588: =K588 -> -375.80294 | Q588: 45831 | S588: 40700 | T588: Revenues - Third Parties
A589: =+VLOOKUP(O589,'Selectable Table'!D:E,2,0) -> J & J | B589: 5415244 | C589: PARG76670 | D589: 996 | E589: 2025 | F589: 6 | G589: totalDistribution | H589: Distribution | I589: -210.06 | J589: EUR | K589: =+VLOOKUP(J589,$W$2:$X$7,2,0)*I589 -> -236.72502 | L589: BSLATAMTP | M589: 994817603 | O589: Janssen R&D LLC | P589: =K589 -> -236.72502 | Q589: 45831 | S589: 40700 | T589: Revenues - Third Parties
A590: =+VLOOKUP(O590,'Selectable Table'!D:E,2,0) -> OTH CUST | B590: 5415245 | C590: PARG84430 | D590: 996 | E590: 2025 | F590: 6 | G590: totalStorage | H590: Storage | I590: -120.08 | J590: EUR | K590: =+VLOOKUP(J590,$W$2:$X$7,2,0)*I590 -> -135.32296 | L590: BSLATAMTP | M590: 4201830280 | O590: ALLERGAN | P590: =K590 -> -135.32296 | Q590: 45831 | S590: 40700 | T590: Revenues - Third Parties
A591: =+VLOOKUP(O591,'Selectable Table'!D:E,2,0) -> OTH CUST | B591: 5415245 | C591: PARG84430 | D591: 996 | E591: 2025 | F591: 6 | G591: totalStorage | H591: Storage | I591: -95 | J591: EUR | K591: =+VLOOKUP(J591,$W$2:$X$7,2,0)*I591 -> -107.0593 | L591: BSLATAMTP | M591: 4201830280 | O591: ALLERGAN | P591: =K591 -> -107.0593 | Q591: 45831 | S591: 40700 | T591: Revenues - Third Parties
A592: =+VLOOKUP(O592,'Selectable Table'!D:E,2,0) -> OTH CUST | B592: 5415245 | C592: PARG84430 | D592: 996 | E592: 2025 | F592: 6 | G592: totalDistribution | H592: Distribution | I592: -478.8 | J592: EUR | K592: =+VLOOKUP(J592,$W$2:$X$7,2,0)*I592 -> -539.57887 | L592: BSLATAMTP | M592: 4201830280 | O592: ALLERGAN | P592: =K592 -> -539.57887 | Q592: 45831 | S592: 40700 | T592: Revenues - Third Parties
A593: =+VLOOKUP(O593,'Selectable Table'!D:E,2,0) -> PFIZER | B593: 5415246 | C593: PARG76752 | D593: 17000139BLC3002 | E593: 2025 | F593: 6 | G593: totalReturns and Destructions | H593: Returns and Destructions | I593: -295.4 | J593: USD | K593: =+VLOOKUP(J593,$W$2:$X$7,2,0)*I593 -> -295.4 | L593: BSLATAMTP | M593: 9500851363 | O593: PFIZER | P593: =K593 -> -295.4 | Q593: 45831 | S593: 40700 | T593: Revenues - Third Parties
A594: =+VLOOKUP(O594,'Selectable Table'!D:E,2,0) -> OTH CUST | B594: 5415247 | C594: PARG76914 | D594: 17000139BLC3002 | E594: 2025 | F594: 6 | G594: totalReturns and Destructions | H594: Returns and Destructions | I594: -192.34 | J594: USD | K594: =+VLOOKUP(J594,$W$2:$X$7,2,0)*I594 -> -192.34 | L594: BSLATAMTP | M594: 7100061271 | O594: HORSHAM GBP | P594: =K594 -> -192.34 | Q594: 45831 | S594: 40700 | T594: Revenues - Third Parties
A595: =+VLOOKUP(O595,'Selectable Table'!D:E,2,0) -> OTH CUST | B595: 5415248 | C595: PARG79647 | D595: 17000139BLC3002 | E595: 2025 | F595: 6 | G595: totalFreight | H595: Freight | I595: -702.5 | J595: USD | K595: =+VLOOKUP(J595,$W$2:$X$7,2,0)*I595 -> -702.5 | L595: BSLATAMTP | M595: C028-3900029288 | O595: Basel CHF | P595: =K595 -> -702.5 | Q595: 45831 | S595: 40700 | T595: Revenues - Third Parties
A596: =+VLOOKUP(O596,'Selectable Table'!D:E,2,0) -> OTH CUST | B596: 5415249 | C596: PARG77987 | D596: 17000139BLC3002 | E596: 2025 | F596: 6 | G596: totalDistribution | H596: Distribution | I596: -296.416 | J596: USD | K596: =+VLOOKUP(J596,$W$2:$X$7,2,0)*I596 -> -296.416 | L596: BSLATAMTP | M596: 9500854302 | O596: HORSHAM GBP | P596: =K596 -> -296.416 | Q596: 45831 | S596: 40700 | T596: Revenues - Third Parties
A597: =+VLOOKUP(O597,'Selectable Table'!D:E,2,0) -> OTH CUST | B597: 5415249 | C597: PARG77987 | D597: 17000139BLC3002 | E597: 2025 | F597: 6 | G597: totalStorage | H597: Storage | I597: -341.996 | J597: USD | K597: =+VLOOKUP(J597,$W$2:$X$7,2,0)*I597 -> -341.996 | L597: BSLATAMTP | M597: 9500854302 | O597: HORSHAM GBP | P597: =K597 -> -341.996 | Q597: 45831 | S597: 40700 | T597: Revenues - Third Parties
A598: =+VLOOKUP(O598,'Selectable Table'!D:E,2,0) -> OTH CUST | B598: 5415250 | C598: PARG80061 | D598: 17000139BLC3002 | E598: 2025 | F598: 6 | G598: totalDistribution | H598: Distribution | I598: -412.36 | J598: USD | K598: =+VLOOKUP(J598,$W$2:$X$7,2,0)*I598 -> -412.36 | L598: BSLATAMTP | M598: 5070340792 | O598: Basel Euro | P598: =K598 -> -412.36 | Q598: 45831 | S598: 40700 | T598: Revenues - Third Parties
A599: =+VLOOKUP(O599,'Selectable Table'!D:E,2,0) -> OTH CUST | B599: 5415251 | C599: PARG78264 | D599: 17000139BLC3002 | E599: 2025 | F599: 6 | G599: totalDistribution | H599: Distribution | I599: -717.56 | J599: USD | K599: =+VLOOKUP(J599,$W$2:$X$7,2,0)*I599 -> -717.56 | L599: BSLATAMTP | M599: BV-2023-3202 | O599: Basel Euro | P599: =K599 -> -717.56 | Q599: 45831 | S599: 40700 | T599: Revenues - Third Parties
A600: =+VLOOKUP(O600,'Selectable Table'!D:E,2,0) -> OTH CUST | B600: 5415251 | C600: PARG78264 | D600: 17000139BLC3002 | E600: 2025 | F600: 6 | G600: totalDistribution | H600: Distribution | I600: -71.976 | J600: USD | K600: =+VLOOKUP(J600,$W$2:$X$7,2,0)*I600 -> -71.976 | L600: BSLATAMTP | M600: BV-2023-3202 | O600: Basel Euro | P600: =K600 -> -71.976 | Q600: 45831 | S600: 40700 | T600: Revenues - Third Parties
A601: =+VLOOKUP(O601,'Selectable Table'!D:E,2,0) -> OTH CUST | B601: 5415252 | C601: PARG79154 | D601: 17000139BLC3002 | E601: 2025 | F601: 6 | G601: totalStorage | H601: Storage | I601: -124.264 | J601: USD | K601: =+VLOOKUP(J601,$W$2:$X$7,2,0)*I601 -> -124.264 | L601: BSLATAMTP | M601: 7100096548 | O601: HORSHAM GBP | P601: =K601 -> -124.264 | Q601: 45831 | S601: 40700 | T601: Revenues - Third Parties
A602: =+VLOOKUP(O602,'Selectable Table'!D:E,2,0) -> OTH CUST | B602: 5415253 | C602: PARG86268 | D602: 17000139BLC3002 | E602: 2025 | F602: 6 | G602: totalStorage | H602: Storage | I602: -341.996 | J602: USD | K602: =+VLOOKUP(J602,$W$2:$X$7,2,0)*I602 -> -341.996 | L602: BSLATAMTP | M602: 9500854302 | O602: HORSHAM GBP | P602: =K602 -> -341.996 | Q602: 45831 | S602: 40700 | T602: Revenues - Third Parties
A603: =+VLOOKUP(O603,'Selectable Table'!D:E,2,0) -> OTH CUST | B603: 5415254 | C603: PARG79834 | D603: V116-010 | E603: 2025 | F603: 6 | G603: totalStorage | H603: Storage | I603: -177.96 | J603: USD | K603: =+VLOOKUP(J603,$W$2:$X$7,2,0)*I603 -> -177.96 | L603: BSLATAMTP | M603: C028-3900029417 | O603: Basel CHF | P603: =K603 -> -177.96 | Q603: 45831 | S603: 40700 | T603: Revenues - Third Parties
A604: =+VLOOKUP(O604,'Selectable Table'!D:E,2,0) -> OTH CUST | B604: 5415255 | C604: PARG81714 | D604: D9180C00008 | E604: 2025 | F604: 6 | G604: totalDistribution | H604: Distribution | I604: -86.708 | J604: USD | K604: =+VLOOKUP(J604,$W$2:$X$7,2,0)*I604 -> -86.708 | L604: BSLATAMTP | M604: C028-3900029552 | O604: Basel CHF | P604: =K604 -> -86.708 | Q604: 45831 | S604: 40700 | T604: Revenues - Third Parties
... A665: =+VLOOKUP(O665,'Selectable Table'!D:E,2,0) -> OTH CUST | B665: 5415296 | C665: PARG82546 | D665: MK-8591A-053 | E665: 2025 | F665: 6 | G665: totalDistribution | H665: Distribution | I665: -592.88 | J665: USD | K665: =+VLOOKUP(J665,$W$2:$X$7,2,0)*I665 -> -592.88 | L665: BSLATAMTP | M665: 50574 | O665: FISHER - BASEL | P665: =K665 -> -592.88 | Q665: 45831 | S665: 40700 | T665: Revenues - Third Parties
A666: =+VLOOKUP(O666,'Selectable Table'!D:E,2,0) -> OTH CUST | B666: 5415297 | C666: PARG79750 | D666: MK-8591A-053 | E666: 2025 | F666: 6 | G666: totalDistribution | H666: Distribution | I666: -848.256 | J666: USD | K666: =+VLOOKUP(J666,$W$2:$X$7,2,0)*I666 -> -848.256 | L666: BSLATAMTP | O666: Fisher AHMEDABAD | P666: =K666 -> -848.256 | Q666: 45831 | S666: 40700 | T666: Revenues - Third Parties
A667: =+VLOOKUP(O667,'Selectable Table'!D:E,2,0) -> OTH CUST | B667: 5415298 | C667: PARG79788 | D667: MK-8591A-053 | E667: 2025 | F667: 6 | G667: totalDistribution | H667: Distribution | I667: -1509.64 | J667: USD | K667: =+VLOOKUP(J667,$W$2:$X$7,2,0)*I667 -> -1509.64 | L667: BSLATAMTP | M667: 9500851363 | O667: Seagen, Inc. | P667: =K667 -> -1509.64 | Q667: 45831 | S667: 40700 | T667: Revenues - Third Parties
A668: =+VLOOKUP(O668,'Selectable Table'!D:E,2,0) -> OTH CUST | B668: 5415298 | C668: PARG79788 | D668: MK-8591A-053 | E668: 2025 | F668: 6 | G668: totalDistribution | H668: Distribution | I668: -68.832 | J668: USD | K668: =+VLOOKUP(J668,$W$2:$X$7,2,0)*I668 -> -68.832 | L668: BSLATAMTP | M668: 9500851363 | O668: Seagen, Inc. | P668: =K668 -> -68.832 | Q668: 45831 | S668: 40700 | T668: Revenues - Third Parties
A669: =+VLOOKUP(O669,'Selectable Table'!D:E,2,0) -> OTH CUST | B669: 5415299 | C669: PARG79909 | D669: MK-8591A-053 | E669: 2025 | F669: 6 | G669: totalDistribution | H669: Distribution | I669: -682.308 | J669: USD | K669: =+VLOOKUP(J669,$W$2:$X$7,2,0)*I669 -> -682.308 | L669: BSLATAMTP | M669: 9500854302 | O669: HORSHAM GBP | P669: =K669 -> -682.308 | Q669: 45831 | S669: 40700 | T669: Revenues - Third Parties
A670: =+VLOOKUP(O670,'Selectable Table'!D:E,2,0) -> OTH CUST | B670: 5415300 | C670: PARG79780 | D670: MK-8591A-053 | E670: 2025 | F670: 6 | G670: totalStorage | H670: Storage | I670: -74.34 | J670: USD | K670: =+VLOOKUP(J670,$W$2:$X$7,2,0)*I670 -> -74.34 | L670: BSLATAMTP | M670: ALE-13509 | O670: Alector LLC | P670: =K670 -> -74.34 | Q670: 45831 | S670: 40700 | T670: Revenues - Third Parties
A671: =+VLOOKUP(O671,'Selectable Table'!D:E,2,0) -> OTH CUST | B671: 5415301 | C671: PARG80115 | D671: IgAN WA43966 (CAM) | E671: 2025 | F671: 6 | G671: totalStorage | H671: Storage | I671: -1411.968 | J671: USD | K671: =+VLOOKUP(J671,$W$2:$X$7,2,0)*I671 -> -1411.968 | L671: BSLATAMTP | M671: 20221203 | O671: MICURX PHARMACEUTICA | P671: =K671 -> -1411.968 | Q671: 45831 | S671: 40700 | T671: Revenues - Third Parties
A672: =+VLOOKUP(O672,'Selectable Table'!D:E,2,0) -> OTH CUST | B672: 5415301 | C672: PARG80115 | D672: IgAN WA43966 (CAM) | E672: 2025 | F672: 6 | G672: totalDistribution | H672: Distribution | I672: -1037.54 | J672: USD | K672: =+VLOOKUP(J672,$W$2:$X$7,2,0)*I672 -> -1037.54 | L672: BSLATAMTP | M672: 20221203 | O672: MICURX PHARMACEUTICA | P672: =K672 -> -1037.54 | Q672: 45831 | S672: 40700 | T672: Revenues - Third Parties
...

Sheet Chi
A1: Vacio | B1: Protocol | C1: Element 4 short name | D1: Allentown / Argentina | E1: Custom 2 | H1: Vacio | I1: Line description | J1: YYYY | K1: MM | L1: CURRENCY | M1: 40 % (sin hadling) | O1: 40 % (sin hadling) | P1: Vacio | Q1: Not Applicable (solo para Allentown) | R1: Vacio | S1: Vacio
A2: grpcode | B2: el4 | C2: el4_name | D2: el4_sname | E2: name | F2: el2 | G2: el2_name | H2: el3 | I2: el3_name | J2: yr | K2: period | L2: curcode | M2: LOC AMT | N2: Rate | O2: USD AMT | P2: cmpcode | Q2: Discount Flag | R2: _ | S2: x
A3: =+VLOOKUP(C3,'Selectable Table'!D:E,2,0) -> OTH CUST | B3: Transfer Pricing | C3: Allentown | D3: Allentown | E3: Distribution | F3: =+VLOOKUP(Col!C3,'Selectable Table'!O:P,2,0) -> 40700 | G3: =+VLOOKUP(F3,'Selectable Table'!P:Q,2,0) -> Revenues - Third Parties | I3: Transfer Pricing | J3: 2026 | K3: 5 | L3: USD | M3: 193458.76 | O3: 193458.76 | P3: BSChile | Q3: Not Applicable
A4: =+VLOOKUP(C4,'Selectable Table'!D:E,2,0) -> OTH CUST | B4: Transfer Pricing | C4: Allentown | D4: Allentown | E4: Freight | F4: =+VLOOKUP(Col!C4,'Selectable Table'!O:P,2,0) -> 40700 | G4: =+VLOOKUP(F4,'Selectable Table'!P:Q,2,0) -> Revenues - Third Parties | I4: Transfer Pricing | J4: 2026 | K4: 5 | L4: USD | M4: 31807.25 | O4: 31807.25 | P4: BSChile | Q4: Not Applicable
A5: =+VLOOKUP(C5,'Selectable Table'!D:E,2,0) -> OTH CUST | B5: Transfer Pricing | C5: Allentown | D5: Allentown | E5: Returns and Destructions | F5: =+VLOOKUP(Col!C5,'Selectable Table'!O:P,2,0) -> 40700 | G5: =+VLOOKUP(F5,'Selectable Table'!P:Q,2,0) -> Revenues - Third Parties | I5: Transfer Pricing | J5: 2026 | K5: 5 | L5: USD | M5: 2991.7 | O5: 2991.7 | P5: BSChile | Q5: Not Applicable
A6: =+VLOOKUP(C6,'Selectable Table'!D:E,2,0) -> OTH CUST | B6: Transfer Pricing | C6: Allentown | D6: Allentown | E6: Storage | F6: =+VLOOKUP(Col!C6,'Selectable Table'!O:P,2,0) -> 40700 | G6: =+VLOOKUP(F6,'Selectable Table'!P:Q,2,0) -> Revenues - Third Parties | I6: Transfer Pricing | J6: 2026 | K6: 5 | L6: USD | M6: 126076.03 | O6: 126076.03 | P6: BSChile | Q6: Not Applicable
A7: =+VLOOKUP(C7,'Selectable Table'!D:E,2,0) -> OTH CUST | B7: Transfer Pricing | C7: Allentown | D7: Allentown | E7: Duties | F7: =+VLOOKUP(Col!C7,'Selectable Table'!O:P,2,0) -> 40700 | G7: =+VLOOKUP(F7,'Selectable Table'!P:Q,2,0) -> Revenues - Third Parties | I7: Transfer Pricing | J7: 2026 | K7: 5 | L7: USD | M7: 12006.72 | O7: 12006.72 | P7: BSChile | Q7: Not Applicable
A8: =+VLOOKUP(C8,'Selectable Table'!D:E,2,0) -> ASTRAZENECA | B8: D3252C00002 (Local) | C8: Astra Zeneca | D8: Chile | E8: Distribution | F8: =+VLOOKUP(Col!C8,'Selectable Table'!O:P,2,0) -> 40700 | G8: =+VLOOKUP(F8,'Selectable Table'!P:Q,2,0) -> Revenues - Third Parties | I8: Project Management Fee | J8: 2026 | K8: 5 | L8: USD | M8: 376.26 | O8: 376.26 | P8: BSChile
A9: =+VLOOKUP(C9,'Selectable Table'!D:E,2,0) -> ASTRAZENECA | B9: D3252C00002 (Local) | C9: Astra Zeneca | D9: Chile | E9: Storage | F9: =+VLOOKUP(Col!C9,'Selectable Table'!O:P,2,0) -> 40700 | G9: =+VLOOKUP(F9,'Selectable Table'!P:Q,2,0) -> Revenues - Third Parties | I9: Storage Ambient (per Shelf) | J9: 2026 | K9: 5 | L9: USD | M9: 714.9 | O9: 714.9 | P9: BSChile
A10: =+VLOOKUP(C10,'Selectable Table'!D:E,2,0) -> ASTRAZENECA | B10: D361BC00001 (Local) | C10: Astra Zeneca | D10: Chile | E10: Freight | F10: =+VLOOKUP(Col!C10,'Selectable Table'!O:P,2,0) -> 40700 | G10: =+VLOOKUP(F10,'Selectable Table'!P:Q,2,0) -> Revenues - Third Parties | I10: Freight - Returns | J10: 2026 | K10: 5 | L10: USD | M10: 72.59 | O10: 72.59 | P10: BSChile | Q10: -1
A11: =+VLOOKUP(C11,'Selectable Table'!D:E,2,0) -> ASTRAZENECA | B11: D361BC00001 (Local) | C11: Astra Zeneca | D11: Chile | E11: Distribution | F11: =+VLOOKUP(Col!C11,'Selectable Table'!O:P,2,0) -> 40700 | G11: =+VLOOKUP(F11,'Selectable Table'!P:Q,2,0) -> Revenues - Third Parties | I11: Project Management Fee | J11: 2026 | K11: 5 | L11: USD | M11: 376.26 | O11: 376.26 | P11: BSChile
A12: =+VLOOKUP(C12,'Selectable Table'!D:E,2,0) -> ASTRAZENECA | B12: D361BC00001 (Local) | C12: Astra Zeneca | D12: Chile | E12: Storage | F12: =+VLOOKUP(Col!C12,'Selectable Table'!O:P,2,0) -> 40700 | G12: =+VLOOKUP(F12,'Selectable Table'!P:Q,2,0) -> Revenues - Third Parties | I12: Storage Ambient (per Shelf) | J12: 2026 | K12: 5 | L12: USD | M12: 357.45 | O12: 357.45 | P12: BSChile
A13: =+VLOOKUP(C13,'Selectable Table'!D:E,2,0) -> ASTRAZENECA | B13: D5169C00001 (Local) | C13: Astra Zeneca | D13: Chile | E13: Distribution | F13: =+VLOOKUP(Col!C13,'Selectable Table'!O:P,2,0) -> 40700 | G13: =+VLOOKUP(F13,'Selectable Table'!P:Q,2,0) -> Revenues - Third Parties | I13: Project Management Fee | J13: 2026 | K13: 5 | L13: USD | M13: 376.26 | O13: 376.26 | P13: BSChile
A14: =+VLOOKUP(C14,'Selectable Table'!D:E,2,0) -> ASTRAZENECA | B14: D5169C00001 (Local) | C14: Astra Zeneca | D14: Chile | E14: Storage | F14: =+VLOOKUP(Col!C14,'Selectable Table'!O:P,2,0) -> 40700 | G14: =+VLOOKUP(F14,'Selectable Table'!P:Q,2,0) -> Revenues - Third Parties | I14: Storage Ambient (per Shelf) | J14: 2026 | K14: 5 | L14: USD | M14: 238.3 | O14: 238.3 | P14: BSChile
A15: =+VLOOKUP(C15,'Selectable Table'!D:E,2,0) -> ASTRAZENECA | B15: D516AC00001 (Local) | C15: Astra Zeneca | D15: Chile | E15: Distribution | F15: =+VLOOKUP(Col!C15,'Selectable Table'!O:P,2,0) -> 40700 | G15: =+VLOOKUP(F15,'Selectable Table'!P:Q,2,0) -> Revenues - Third Parties | I15: Project Management Fee | J15: 2026 | K15: 5 | L15: USD | M15: 376.26 | O15: 376.26 | P15: BSChile
A16: =+VLOOKUP(C16,'Selectable Table'!D:E,2,0) -> ASTRAZENECA | B16: D516AC00001 (Local) | C16: Astra Zeneca | D16: Chile | E16: Storage | F16: =+VLOOKUP(Col!C16,'Selectable Table'!O:P,2,0) -> 40700 | G16: =+VLOOKUP(F16,'Selectable Table'!P:Q,2,0) -> Revenues - Third Parties | I16: Storage Ambient (per Shelf) | J16: 2026 | K16: 5 | L16: USD | M16: 476.6 | O16: 476.6 | P16: BSChile
A17: =+VLOOKUP(C17,'Selectable Table'!D:E,2,0) -> ASTRAZENECA | B17: D081SC00001 (Local) | C17: Astra Zeneca | D17: Chile | E17: Freight | F17: =+VLOOKUP(Col!C17,'Selectable Table'!O:P,2,0) -> 40700 | G17: =+VLOOKUP(F17,'Selectable Table'!P:Q,2,0) -> Revenues - Third Parties | I17: Freight - Shipments | J17: 2026 | K17: 5 | L17: USD | M17: 105.28 | O17: 105.28 | P17: BSChile
A18: =+VLOOKUP(C18,'Selectable Table'!D:E,2,0) -> ASTRAZENECA | B18: D081SC00001 (Local) | C18: Astra Zeneca | D18: Chile | E18: Distribution | F18: =+VLOOKUP(Col!C18,'Selectable Table'!O:P,2,0) -> 40700 | G18: =+VLOOKUP(F18,'Selectable Table'!P:Q,2,0) -> Revenues - Third Parties | I18: Project Management Fee | J18: 2026 | K18: 5 | L18: USD | M18: 376.26 | O18: 376.26 | P18: BSChile
A19: =+VLOOKUP(C19,'Selectable Table'!D:E,2,0) -> ASTRAZENECA | B19: D081SC00001 (Local) | C19: Astra Zeneca | D19: Chile | E19: Storage | F19: =+VLOOKUP(Col!C19,'Selectable Table'!O:P,2,0) -> 40700 | G19: =+VLOOKUP(F19,'Selectable Table'!P:Q,2,0) -> Revenues - Third Parties | I19: Storage Ambient (per Shelf) | J19: 2026 | K19: 5 | L19: USD | M19: 119.15 | O19: 119.15 | P19: BSChile
A20: =+VLOOKUP(C20,'Selectable Table'!D:E,2,0) -> ASTRAZENECA | B20: D9075C00001 (Local) | C20: Astra Zeneca | D20: Chile | E20: Distribution | F20: =+VLOOKUP(Col!C20,'Selectable Table'!O:P,2,0) -> 40700 | G20: =+VLOOKUP(F20,'Selectable Table'!P:Q,2,0) -> Revenues - Third Parties | I20: Administrative fee | J20: 2026 | K20: 5 | L20: USD | M20: 338.634 | O20: 338.634 | P20: BSChile
A21: =+VLOOKUP(C21,'Selectable Table'!D:E,2,0) -> ASTRAZENECA | B21: D9075C00001 (Local) | C21: Astra Zeneca | D21: Chile | E21: Distribution | F21: =+VLOOKUP(Col!C21,'Selectable Table'!O:P,2,0) -> 40700 | G21: =+VLOOKUP(F21,'Selectable Table'!P:Q,2,0) -> Revenues - Third Parties | I21: Import Services | J21: 2026 | K21: 5 | L21: USD | M21: 294 | O21: 294 | P21: BSChile
A22: =+VLOOKUP(C22,'Selectable Table'!D:E,2,0) -> ASTRAZENECA | B22: D9075C00001 (Local) | C22: Astra Zeneca | D22: Chile | E22: Distribution | F22: =+VLOOKUP(Col!C22,'Selectable Table'!O:P,2,0) -> 40700 | G22: =+VLOOKUP(F22,'Selectable Table'!P:Q,2,0) -> Revenues - Third Parties | I22: Project Management Fee | J22: 2026 | K22: 5 | L22: USD | M22: 376.26 | O22: 376.26 | P22: BSChile
... A423: =+VLOOKUP(C423,'Selectable Table'!D:E,2,0) -> OTH CUST | B423: Others | C423: Others | D423: Chile | E423: CAM | F423: =+VLOOKUP(Col!C423,'Selectable Table'!O:P,2,0) -> 40700 | G423: =+VLOOKUP(F423,'Selectable Table'!P:Q,2,0) -> Revenues - Third Parties | I423: FX Translation | J423: 2026 | K423: 5 | L423: USD | M423: -1 | O423: -1 | P423: BSChile
A424: =+VLOOKUP(C424,'Selectable Table'!D:E,2,0) -> OTH CUST | B424: Others | C424: Others | D424: Chile | E424: Comparator | F424: =+VLOOKUP(Col!C424,'Selectable Table'!O:P,2,0) -> 40700 | G424: =+VLOOKUP(F424,'Selectable Table'!P:Q,2,0) -> Revenues - Third Parties | I424: FX Translation | J424: 2026 | K424: 5 | L424: USD | M424: =-14442.1468284+399.98 -> -14042.167 | O424: =-14442.1468284+399.98 -> -14042.167 | P424: BSChile
A425: =+VLOOKUP(C425,'Selectable Table'!D:E,2,0) -> OTH CUST | B425: Others | C425: Others | D425: Chile | E425: Duties | F425: =+VLOOKUP(Col!C425,'Selectable Table'!O:P,2,0) -> 40700 | G425: =+VLOOKUP(F425,'Selectable Table'!P:Q,2,0) -> Revenues - Third Parties | I425: FX Translation | J425: 2026 | K425: 5 | L425: USD | M425: -296.85496 | O425: -296.85496 | P425: BSChile
A426: =+VLOOKUP(C426,'Selectable Table'!D:E,2,0) -> OTH CUST | B426: Others | C426: Others | D426: Chile | E426: Distribution | F426: =+VLOOKUP(Col!C426,'Selectable Table'!O:P,2,0) -> 40700 | G426: =+VLOOKUP(F426,'Selectable Table'!P:Q,2,0) -> Revenues - Third Parties | I426: FX Translation | J426: 2026 | K426: 5 | L426: USD | M426: -2149.6522 | O426: -2149.6522 | P426: BSChile
A427: =+VLOOKUP(C427,'Selectable Table'!D:E,2,0) -> OTH CUST | B427: Others | C427: Others | D427: Chile | E427: Freight | F427: =+VLOOKUP(Col!C427,'Selectable Table'!O:P,2,0) -> 40700 | G427: =+VLOOKUP(F427,'Selectable Table'!P:Q,2,0) -> Revenues - Third Parties | I427: FX Translation | J427: 2026 | K427: 5 | L427: USD | M427: -354.18304 | O427: -354.18304 | P427: BSChile
A428: =+VLOOKUP(C428,'Selectable Table'!D:E,2,0) -> OTH CUST | B428: Others | C428: Others | D428: Chile | E428: Packaging | F428: =+VLOOKUP(Col!C428,'Selectable Table'!O:P,2,0) -> 40700 | G428: =+VLOOKUP(F428,'Selectable Table'!P:Q,2,0) -> Revenues - Third Parties | I428: FX Translation | J428: 2026 | K428: 5 | L428: USD | M428: 0 | O428: 0 | P428: BSChile
A429: =+VLOOKUP(C429,'Selectable Table'!D:E,2,0) -> OTH CUST | B429: Others | C429: Others | D429: Chile | E429: Returns and Destructions | F429: =+VLOOKUP(Col!C429,'Selectable Table'!O:P,2,0) -> 40700 | G429: =+VLOOKUP(F429,'Selectable Table'!P:Q,2,0) -> Revenues - Third Parties | I429: FX Translation | J429: 2026 | K429: 5 | L429: USD | M429: -137.78757 | O429: -137.78757 | P429: BSChile
A430: =+VLOOKUP(C430,'Selectable Table'!D:E,2,0) -> OTH CUST | B430: Others | C430: Others | D430: Chile | E430: Surcharge | F430: =+VLOOKUP(Col!C430,'Selectable Table'!O:P,2,0) -> 40700 | G430: =+VLOOKUP(F430,'Selectable Table'!P:Q,2,0) -> Revenues - Third Parties | I430: FX Translation | J430: 2026 | K430: 5 | L430: USD | P430: BSChile
A431: =+VLOOKUP(C431,'Selectable Table'!D:E,2,0) -> OTH CUST | B431: Others | C431: Others | D431: Chile | E431: Storage | F431: =+VLOOKUP(Col!C431,'Selectable Table'!O:P,2,0) -> 40700 | G431: =+VLOOKUP(F431,'Selectable Table'!P:Q,2,0) -> Revenues - Third Parties | I431: FX Translation | J431: 2026 | K431: 5 | L431: USD | M431: -1492.4862 | O431: -1492.4862 | P431: BSChile
O432: =SUM(O3:O431) -> 678722.42

Sheet Col
B1: Protocol | C1: Element 4 short name | D1: Allentown / Argentina | E1: Custom 2 | H1: Vacio | I1: Line description | J1: YYYY | K1: MM | L1: CURRENCY | M1: 40 % (sin hadling) | O1: 40 % (sin hadling) | P1: Vacio | Q1: Not Applicable (solo para Allentown) | R1: Vacio | S1: Vacio
A2: grpcode | B2: el4 | C2: el4_name | D2: el4_sname | E2: name | F2: el2 | G2: el2_name | H2: el3 | I2: el3_name | J2: yr | K2: period | L2: curcode | M2: LOC AMT | N2: Rate | O2: USD AMT | P2: cmpcode | Q2: Discount Flag | R2: _ | S2: x
A3: =+VLOOKUP(C3,'Selectable Table'!D:E,2,0) -> J & J | B3: Janssen Storage of temperature monitors | C3: Janssen | D3: Colombia | E3: Storage | F3: =+VLOOKUP(Col!C3,'Selectable Table'!O:P,2,0) -> 40700 | G3: =+VLOOKUP(F3,'Selectable Table'!P:Q,2,0) -> Revenues - Third Parties | I3: Non-Drug Storage Ambient (per Shelf) | J3: 2026 | K3: 5 | L3: USD | M3: 960.70012 | N3: 1 | O3: 960.70012 | P3: BSColombia
A4: =+VLOOKUP(C4,'Selectable Table'!D:E,2,0) -> J & J | B4: Janssen Storage of temperature monitors | C4: Janssen | D4: Colombia | E4: Storage | F4: =+VLOOKUP(Col!C4,'Selectable Table'!O:P,2,0) -> 40700 | G4: =+VLOOKUP(F4,'Selectable Table'!P:Q,2,0) -> Revenues - Third Parties | I4: Non-Drug Storage Refrigerated (per Shelf) | J4: 2026 | K4: 5 | L4: USD | M4: 600.4215 | N4: 1 | O4: 600.4215 | P4: BSColombia
A5: =+VLOOKUP(C5,'Selectable Table'!D:E,2,0) -> TAKEDA | B5: TAK-390MR_205 | C5: Takeda | D5: Colombia | E5: Distribution | F5: =+VLOOKUP(Col!C5,'Selectable Table'!O:P,2,0) -> 40700 | G5: =+VLOOKUP(F5,'Selectable Table'!P:Q,2,0) -> Revenues - Third Parties | I5: Project Management Fee | J5: 2026 | K5: 5 | L5: USD | M5: 600 | N5: 1 | O5: 600 | P5: BSColombia
A6: =+VLOOKUP(C6,'Selectable Table'!D:E,2,0) -> TAKEDA | B6: TAK-390MR_205 | C6: Takeda | D6: Colombia | E6: Storage | F6: =+VLOOKUP(Col!C6,'Selectable Table'!O:P,2,0) -> 40700 | G6: =+VLOOKUP(F6,'Selectable Table'!P:Q,2,0) -> Revenues - Third Parties | I6: Storage Ambient (per Pallet) | J6: 2026 | K6: 5 | L6: USD | M6: 300 | N6: 1 | O6: 300 | P6: BSColombia
A7: =+VLOOKUP(C7,'Selectable Table'!D:E,2,0) -> TAKEDA | B7: TAK-390MR_204 | C7: Takeda | D7: Colombia | E7: Distribution | F7: =+VLOOKUP(Col!C7,'Selectable Table'!O:P,2,0) -> 40700 | G7: =+VLOOKUP(F7,'Selectable Table'!P:Q,2,0) -> Revenues - Third Parties | I7: Project Management Fee | J7: 2026 | K7: 5 | L7: USD | M7: 600 | N7: 1 | O7: 600 | P7: BSColombia
A8: =+VLOOKUP(C8,'Selectable Table'!D:E,2,0) -> TAKEDA | B8: TAK-390MR_204 | C8: Takeda | D8: Colombia | E8: Storage | F8: =+VLOOKUP(Col!C8,'Selectable Table'!O:P,2,0) -> 40700 | G8: =+VLOOKUP(F8,'Selectable Table'!P:Q,2,0) -> Revenues - Third Parties | I8: Storage Ambient (per Pallet) | J8: 2026 | K8: 5 | L8: USD | M8: 200 | N8: 1 | O8: 200 | P8: BSColombia
A9: =+VLOOKUP(C9,'Selectable Table'!D:E,2,0) -> MERCK | B9: Merck Receipt and Storage of CREDOS and TT4 | C9: Merck Sharp and Dohme LLC | D9: Colombia | E9: Storage | F9: =+VLOOKUP(Col!C9,'Selectable Table'!O:P,2,0) -> 40700 | G9: =+VLOOKUP(F9,'Selectable Table'!P:Q,2,0) -> Revenues - Third Parties | I9: Non-Drug Storage Ambient (per Pallet) | J9: 2026 | K9: 5 | L9: USD | M9: 1544.45 | N9: 1 | O9: 1544.45 | P9: BSColombia
A10: =+VLOOKUP(C10,'Selectable Table'!D:E,2,0) -> MERCK | B10: Merck Receipt and Storage of CREDOS and TT4 | C10: Merck Sharp and Dohme LLC | D10: Colombia | E10: Distribution | F10: =+VLOOKUP(Col!C10,'Selectable Table'!O:P,2,0) -> 40700 | G10: =+VLOOKUP(F10,'Selectable Table'!P:Q,2,0) -> Revenues - Third Parties | I10: Receipt fee Ancillaries (per Receipt_ID) | J10: 2026 | K10: 5 | L10: USD | M10: 3082.56 | N10: 1 | O10: 3082.56 | P10: BSColombia
A11: =+VLOOKUP(C11,'Selectable Table'!D:E,2,0) -> J & J | B11: CNTO1959CRD3001 | C11: Janssen | D11: Colombia | E11: Distribution | F11: =+VLOOKUP(Col!C11,'Selectable Table'!O:P,2,0) -> 40700 | G11: =+VLOOKUP(F11,'Selectable Table'!P:Q,2,0) -> Revenues - Third Parties | I11: Project Management Fee | J11: 2026 | K11: 5 | L11: USD | M11: 500.35125 | N11: 1 | O11: 500.35125 | P11: BSColombia
A12: =+VLOOKUP(C12,'Selectable Table'!D:E,2,0) -> J & J | B12: CNTO1959CRD3001 | C12: Janssen | D12: Colombia | E12: Distribution | F12: =+VLOOKUP(Col!C12,'Selectable Table'!O:P,2,0) -> 40700 | G12: =+VLOOKUP(F12,'Selectable Table'!P:Q,2,0) -> Revenues - Third Parties | I12: Receipt fee Refrigerated (per Receipt_ID) | J12: 2026 | K12: 5 | L12: USD | M12: 200.1405 | N12: 1 | O12: 200.1405 | P12: BSColombia
A13: =+VLOOKUP(C13,'Selectable Table'!D:E,2,0) -> J & J | B13: CNTO1959CRD3001 | C13: Janssen | D13: Colombia | E13: Storage | F13: =+VLOOKUP(Col!C13,'Selectable Table'!O:P,2,0) -> 40700 | G13: =+VLOOKUP(F13,'Selectable Table'!P:Q,2,0) -> Revenues - Third Parties | I13: Storage Refrigerated (per Shelf) | J13: 2026 | K13: 5 | L13: USD | M13: 600.4215 | N13: 1 | O13: 600.4215 | P13: BSColombia
A14: =+VLOOKUP(C14,'Selectable Table'!D:E,2,0) -> J & J | B14: AC-065A310 | C14: Janssen | D14: Colombia | E14: Distribution | F14: =+VLOOKUP(Col!C14,'Selectable Table'!O:P,2,0) -> 40700 | G14: =+VLOOKUP(F14,'Selectable Table'!P:Q,2,0) -> Revenues - Third Parties | I14: Project Management Fee | J14: 2026 | K14: 5 | L14: USD | M14: 500.35125 | N14: 1 | O14: 500.35125 | P14: BSColombia
... A499: =+VLOOKUP(C499,'Selectable Table'!D:E,2,0) -> OTH CUST | B499: Others | C499: Others | D499: Colombia | E499: Storage | F499: =+VLOOKUP(Col!C499,'Selectable Table'!O:P,2,0) -> 40700 | G499: =+VLOOKUP(F499,'Selectable Table'!P:Q,2,0) -> Revenues - Third Parties | I499: FX Translation | J499: 2026 | K499: 5 | L499: USD | M499: -344.44855 | N499: 1 | O499: -344.44855 | P499: BSColombia
O500: =SUM(O3:O499) -> 403054

Sheet Per
A1: Vacio | B1: Protocol | C1: Element 4 short name | D1: Allentown / Argentina | E1: Custom 2 | H1: Vacio | I1: Line description | J1: YYYY | K1: MM | L1: CURRENCY | M1: 40 % (sin hadling) | O1: 40 % (sin hadling) | P1: Vacio | Q1: Not Applicable (solo para Allentown) | R1: Vacio | S1: Vacio
A2: grpcode | B2: el4 | C2: el4_name | D2: el4_sname | E2: name | F2: el2 | G2: el2_name | H2: el3 | I2: el3_name | J2: yr | K2: period | L2: curcode | M2: LOC AMT | N2: Rate | O2: USD AMT | P2: cmpcode | Q2: Discount Flag | R2: _ | S2: x
B3: IMVT-1402-2801 (CAM) | C3: IMVT Corporation | D3: Peru | E3: Distribution | I3: Project Management Fee | L3: USD | M3: 1696.88 | N3: 1 | O3: 1696.88 | P3: BSPeru
B4: IMVT-1402-2801 (CAM) | C4: IMVT Corporation | D4: Peru | E4: Distribution | I4: Receipt fee Ancillaries (per Receipt_ID) | M4: 3989.88 | N4: 1 | O4: 3989.88 | P4: BSPeru
B5: IMVT-1402-2801 (CAM) | C5: IMVT Corporation | D5: Peru | E5: Distribution | I5: Setup Fee | M5: 3534.95 | N5: 1 | O5: 3534.95 | P5: BSPeru
B6: IMVT-1402-2801 (CAM) | C6: IMVT Corporation | D6: Peru | E6: Storage | I6: Storage Ambient (per Pallet) | M6: 3622.7 | N6: 1 | O6: 3622.7 | P6: BSPeru
B7: Merck Receipt and Storage of CREDOS and TT4 | C7: Merck Sharp and Dohme LLC | D7: Peru | E7: Storage | I7: Non-Drug Storage Ambient (per Pallet) | M7: 573.78 | N7: 1 | O7: 573.78 | P7: BSPeru
B8: DS8201-A-U305 | C8: Daiichi Sankyo Pharma Development | D8: Peru | E8: Distribution | I8: Project Management Fee | M8: 1200 | N8: 1 | O8: 1200 | P8: BSPeru
B9: DS8201-A-U305 | C9: Daiichi Sankyo Pharma Development | D9: Peru | E9: Storage | I9: Storage of Returns (per Pallet) | M9: 326 | N9: 1 | O9: 326 | P9: BSPeru
B10: DS8201-A-U305 | C10: Daiichi Sankyo Pharma Development | D10: Peru | E10: Storage | I10: Storage Refrigerated (per Shelf) | M10: 2100 | N10: 1 | O10: 2100 | P10: BSPeru
B11: SGNTV-003 | C11: Seattle Genetics Inc | D11: Peru | E11: Distribution | I11: Project Management Fee | M11: 1336.2438 | N11: 1 | O11: 1336.2438 | P11: BSPeru
B12: SGNTV-003 | C12: Seattle Genetics Inc | D12: Peru | E12: Storage | I12: Storage Ambient (per Pallet) | M12: 222.7091 | N12: 1 | O12: 222.7091 | P12: BSPeru
B13: SGNTV-003 | C13: Seattle Genetics Inc | D13: Peru | E13: Storage | I13: Storage of Returns (per Pallet) | M13: 167.0292 | N13: 1 | O13: 167.0292 | P13: BSPeru
B14: SGNTV-003 | C14: Seattle Genetics Inc | D14: Peru | E14: Storage | I14: Storage Refrigerated (per Shelf) | M14: 668.1168 | N14: 1 | O14: 668.1168 | P14: BSPeru
B15: D9180C00008 | C15: Astra Zeneca | D15: Peru | E15: Distribution | I15: Project Management Fee | M15: 402.36 | N15: 1 | O15: 402.36 | P15: BSPeru
... B150: D5169C00001 | C150: Astra Zeneca | D150: Peru | E150: Distribution | I150: Temperature Monitoring Device (Ambient) | M150: 37.394169 | N150: 1 | O150: 37.394169 | P150: BSPeru
B151: 20170770 | C151: Amgen, Inc. | D151: Peru | E151: Distribution | I151: Project Management Fee | M151: 775.66 | N151: 1 | O151: 775.66 | P151: BSPeru
B152: 20170770 | C152: Amgen, Inc. | D152: Peru | E152: Returns and Destructions | I152: Reconciliation of Returns (per Hour) | M152: 68.95 | N152: 1 | O152: 68.95 | P152: BSPeru
B153: 20170770 | C153: Amgen, Inc. | D153: Peru | E153: Returns and Destructions | I153: Returns Receipt (per Receipt) | M153: 172.38 | N153: 1 | O153: 172.38 | P153: BSPeru
B154: 20170770 | C154: Amgen, Inc. | D154: Peru | E154: Storage | I154: Storage of Returns (per Pallet) | M154: 389.07 | N154: 1 | O154: 389.07 | P154: BSPeru
B155: 20170770 | C155: Amgen, Inc. | D155: Peru | E155: Storage | I155: Storage Refrigerated (per Shelf) | M155: 1034.24 | N155: 1 | O155: 1034.24 | P155: BSPeru
B156: D361BC00001 | C156: Astra Zeneca | D156: Peru | E156: Freight | I156: Freight - Shipments | M156: 227.92893 | N156: 1 | O156: 227.92893 | P156: BSPeru
B157: D361BC00001 | C157: Astra Zeneca | D157: Peru | E157: Distribution | I157: Pick and Pack (Ambient) | M157: 344.24235 | N157: 1 | O157: 344.24235 | P157: BSPeru
B158: D361BC00001 | C158: Astra Zeneca | D158: Peru | E158: Distribution | I158: Project Management Fee | M158: 404.991 | N158: 1 | O158: 404.991 | P158: BSPeru
B159: D361BC00001 | C159: Astra Zeneca | D159: Peru | E159: Storage | I159: Storage Ambient (per Shelf) | M159: 1154.2243 | N159: 1 | O159: 1154.2243 | P159: BSPeru
B160: D361BC00001 | C160: Astra Zeneca | D160: Peru | E160: Distribution | I160: Temperature Monitoring Device (Ambient) | M160: 109.63106 | N160: 1 | O160: 109.63106 | P160: BSPeru
B161: D967UC00001 | C161: Astra Zeneca | D161: Peru | E161: Freight | I161: Freight - Shipments | M161: 516.01253 | N161: 1 | O161: 516.01253 | P161: BSPeru
B162: D967UC00001 | C162: Astra Zeneca | D162: Peru | E162: Distribution | I162: Insulated shipper - Credo S4 - 12L (Leasing) | M162: 1020.5233 | N162: 1 | O162: 1020.5233 | P162: BSPeru
B163: D967UC00001 | C163: Astra Zeneca | D163: Peru | E163: Distribution | I163: Pick and Pack (Refrigerated) | M163: 512.9886 | N163: 1 | O163: 512.9886 | P163: BSPeru
B164: D967UC00001 | C164: Astra Zeneca | D164: Peru | E164: Distribution | I164: Project Management Fee | M164: 404.991 | N164: 1 | O164: 404.991 | P164: BSPeru
B165: D967UC00001 | C165: Astra Zeneca | D165: Peru | E165: Storage | I165: Storage Refrigerated (per Pallet) | M165: 620.9862 | N165: 1 | O165: 620.9862 | P165: BSPeru
B166: D967UC00001 | C166: Astra Zeneca | D166: Peru | E166: Distribution | I166: Temperature Monitoring Device (Refrigerated) | M166: 146.17475 | N166: 1 | O166: 146.17475 | P166: BSPeru
B167: D9180C00004 | C167: MedImmune Inc | D167: Peru | E167: Distribution | I167: Project Management Fee | M167: 369.9 | N167: 1 | O167: 369.9 | P167: BSPeru
... B176: D9078C00001 | C176: Astra Zeneca | D176: Peru | E176: Storage | I176: Storage Refrigerated (per Pallet) | M176: 1241.9724 | N176: 1 | O176: 1241.9724 | P176: BSPeru
B177: 20210096 | C177: Amgen, Inc. | D177: Peru | E177: Distribution | I177: Project Management Fee | M177: 775.66 | N177: 1 | O177: 775.66 | P177: BSPeru
B178: 20210096 | C178: Amgen, Inc. | D178: Peru | E178: Storage | I178: Storage of Returns (per Pallet) | M178: 129.69 | N178: 1 | O178: 129.69 | P178: BSPeru
B179: D3466C00001 | C179: Astra Zeneca | D179: Peru | E179: Distribution | I179: Configuration of Temperature Monitoring Device | M179: 53.458812 | N179: 1 | O179: 53.458812 | P179: BSPeru
B180: D3466C00001 | C180: Astra Zeneca | D180: Peru | E180: Distribution | I180: Insulated shipper - Credo S22 - 12L (Leasing) | M180: 229.2924 | N180: 1 | O180: 229.2924 | P180: BSPeru
B181: D3466C00001 | C181: Astra Zeneca | D181: Peru | E181: Distribution | I181: Insulated shipper - Credo S22 - 28L (Leasing) | M181: 659.51434 | N181: 1 | O181: 659.51434 | P181: BSPeru
B182: D3466C00001 | C182: Astra Zeneca | D182: Peru | E182: Distribution | I182: Pick and Pack (Controlled Ambient) | M182: 388.58886 | N182: 1 | O182: 388.58886 | P182: BSPeru
B183: D3466C00001 | C183: Astra Zeneca | D183: Peru | E183: Distribution | I183: Project Management Fee | M183: 409.04091 | N183: 1 | O183: 409.04091 | P183: BSPeru
B184: D3466C00001 | C184: Astra Zeneca | D184: Peru | E184: Storage | I184: Storage Ambient (per Pallet) | M184: 518.11849 | N184: 1 | O184: 518.11849 | P184: BSPeru
B185: D3466C00001 | C185: Astra Zeneca | D185: Peru | E185: Freight | I185: Freight - Shipments | M185: 736.57063 | N185: 1 | O185: 736.57063 | P185: BSPeru
B186: D3466C00001 | C186: Astra Zeneca | D186: Peru | E186: Distribution | I186: Insulated shipper - Credo S4 - 12L (Leasing) | M186: 765.39249 | N186: 1 | O186: 765.39249 | P186: BSPeru
B187: D3466C00001 | C187: Astra Zeneca | D187: Peru | E187: Distribution | I187: Pick and Pack (Refrigerated) | M187: 384.74145 | N187: 1 | O187: 384.74145 | P187: BSPeru
B188: D3466C00001 | C188: Astra Zeneca | D188: Peru | E188: Storage | I188: Storage Controlled Drug - Refrigerated (per Pallet) | M188: 1552.4655 | N188: 1 | O188: 1552.4655 | P188: BSPeru
B189: Temperature Monitor-Global Pooling | C189: Astra Zeneca | D189: Peru | E189: Storage | I189: Non-Drug Storage Ambient (per Shelf) | M189: 818.08182 | N189: 1 | O189: 818.08182 | P189: BSPeru
B190: Temperature Monitor-Global Pooling | C190: Astra Zeneca | D190: Peru | E190: Distribution | I190: Receipt fee Ancillaries (per Receipt_ID) | M190: 245.42455 | N190: 1 | O190: 245.42455 | P190: BSPeru
... B205: D8535C00001 | C205: Astra Zeneca | D205: Peru | E205: Distribution | I205: Temperature Monitoring Device (Ambient) | M205: 153.24859 | N205: 1 | O205: 153.24859 | P205: BSPeru
B206: 20190341 | C206: Amgen, Inc. | D206: Peru | E206: Freight | I206: Freight - Shipments | M206: 327.12 | N206: 1 | O206: 327.12 | P206: BSPeru
B207: 20190341 | C207: Amgen, Inc. | D207: Peru | E207: Distribution | I207: Insulated shipper - Credo S22 - 12L (Leasing) | M207: 527.9 | N207: 1 | O207: 527.9 | P207: BSPeru
B208: 20190341 | C208: Amgen, Inc. | D208: Peru | E208: Distribution | I208: Insulated shipper - Credo S4 - 12L (Leasing) | M208: 750 | N208: 1 | O208: 750 | P208: BSPeru
B209: 20190341 | C209: Amgen, Inc. | D209: Peru | E209: Distribution | I209: Pick and Pack (Controlled Ambient) | M209: 413.68 | N209: 1 | O209: 413.68 | P209: BSPeru
B210: 20190341 | C210: Amgen, Inc. | D210: Peru | E210: Distribution | I210: Pick and Pack (Refrigerated) | M210: 620.52 | N210: 1 | O210: 620.52 | P210: BSPeru
B211: 20190341 | C211: Amgen, Inc. | D211: Peru | E211: Distribution | I211: Project Management Fee | M211: 775.66 | N211: 1 | O211: 775.66 | P211: BSPeru
B212: 20190341 | C212: Amgen, Inc. | D212: Peru | E212: Distribution | I212: Receipt fee Refrigerated (per Receipt_ID) | M212: 607.4 | N212: 1 | O212: 607.4 | P212: BSPeru
B213: 20190341 | C213: Amgen, Inc. | D213: Peru | E213: Storage | I213: Storage Ambient (per Pallet) | M213: 410.42 | N213: 1 | O213: 410.42 | P213: BSPeru
B214: 20190341 | C214: Amgen, Inc. | D214: Peru | E214: Storage | I214: Storage Refrigerated (per Shelf) | M214: 258.56 | N214: 1 | O214: 258.56 | P214: BSPeru
B215: 20190341 | C215: Amgen, Inc. | D215: Peru | E215: Distribution | I215: Temperature Monitoring Device (Ambient) | M215: 54.18 | N215: 1 | O215: 54.18 | P215: BSPeru
B216: 20190341 | C216: Amgen, Inc. | D216: Peru | E216: Distribution | I216: Temperature Monitoring Device (Refrigerated) | M216: 81.27 | N216: 1 | O216: 81.27 | P216: BSPeru
B217: P3-IMU-838-RMS-02 | C217: Immunic AG | D217: Peru | E217: Distribution | I217: Project Management Fee | M217: 1477.9578 | N217: 1 | O217: 1477.9578 | P217: BSPeru
B218: P3-IMU-838-RMS-02 | C218: Immunic AG | D218: Peru | E218: Storage | I218: Storage Ambient (per Pallet) | M218: 881.29247 | N218: 1 | O218: 881.29247 | P218: BSPeru
B219: D6402C00012 | C219: Astra Zeneca | D219: Peru | E219: Distribution | I219: Configuration of Temperature Monitoring Device | M219: 109.34757 | N219: 1 | O219: 109.34757 | P219: BSPeru
B220: D6402C00012 | C220: Astra Zeneca | D220: Peru | E220: Freight | I220: Freight - Shipments | M220: 303.90525 | N220: 1 | O220: 303.90525 | P220: BSPeru
B221: D6402C00012 | C221: Astra Zeneca | D221: Peru | E221: Distribution | I221: Pick and Pack (Ambient) | M221: 1032.727 | N221: 1 | O221: 1032.727 | P221: BSPeru
B222: D6402C00012 | C222: Astra Zeneca | D222: Peru | E222: Distribution | I222: Project Management Fee | M222: 404.991 | N222: 1 | O222: 404.991 | P222: BSPeru
B223: D6402C00012 | C223: Astra Zeneca | D223: Peru | E223: Storage | I223: Storage Ambient (per Pallet) | M223: 1667.2129 | N223: 1 | O223: 1667.2129 | P223: BSPeru
B224: 20220093 | C224: Amgen, Inc. | D224: Peru | E224: Distribution | I224: Project Management Fee | M224: 775.66 | N224: 1 | O224: 775.66 | P224: BSPeru
B225: 20220093 | C225: Amgen, Inc. | D225: Peru | E225: Storage | I225: Storage Refrigerated (per Shelf) | M225: 1551.36 | N225: 1 | O225: 1551.36 | P225: BSPeru
B226: D702AC00001 | C226: Astra Zeneca | D226: Peru | E226: Distribution | I226: Project Management Fee | M226: 404.991 | N226: 1 | O226: 404.991 | P226: BSPeru
B227: D702AC00001 | C227: Astra Zeneca | D227: Peru | E227: Distribution | I227: Receipt fee Ambient (per Receipt_ID) | M227: 1457.9676 | N227: 1 | O227: 1457.9676 | P227: BSPeru
B228: D702AC00001 | C228: Astra Zeneca | D228: Peru | E228: Distribution | I228: Receipt fee Refrigerated (per Receipt_ID) | M228: 1700.9622 | N228: 1 | O228: 1700.9622 | P228: BSPeru
B229: D702AC00001 | C229: Astra Zeneca | D229: Peru | E229: Distribution | I229: Setup Fee | M229: 1120.4751 | N229: 1 | O229: 1120.4751 | P229: BSPeru
B230: D702AC00001 | C230: Astra Zeneca | D230: Peru | E230: Storage | I230: Storage Ambient (per Pallet) | M230: 897.73005 | N230: 1 | O230: 897.73005 | P230: BSPeru
B231: D702AC00001 | C231: Astra Zeneca | D231: Peru | E231: Storage | I231: Storage Refrigerated (per Pallet) | M231: 931.4793 | N231: 1 | O231: 931.4793 | P231: BSPeru
B232: 20230050 | C232: Amgen, Inc. | D232: Peru | E232: Freight | I232: Freight - Shipments | M232: 1284.38 | N232: 1 | O232: 1284.38 | P232: BSPeru
B233: 20230050 | C233: Amgen, Inc. | D233: Peru | E233: Distribution | I233: Insulated shipper - Credo S4 - 12L (Leasing) | M233: 2250 | N233: 1 | O233: 2250 | P233: BSPeru
B234: 20230050 | C234: Amgen, Inc. | D234: Peru | E234: Distribution | I234: Pick and Pack (Refrigerated) | M234: 1861.56 | N234: 1 | O234: 1861.56 | P234: BSPeru
B235: 20230050 | C235: Amgen, Inc. | D235: Peru | E235: Distribution | I235: Project Management Fee | M235: 775.66 | N235: 1 | O235: 775.66 | P235: BSPeru
B236: 20230050 | C236: Amgen, Inc. | D236: Peru | E236: Storage | I236: Storage Refrigerated (per Shelf) | M236: 3361.28 | N236: 1 | O236: 3361.28 | P236: BSPeru
B237: 20230050 | C237: Amgen, Inc. | D237: Peru | E237: Distribution | I237: Temperature Monitoring Device (Refrigerated) | M237: 243.81 | N237: 1 | O237: 243.81 | P237: BSPeru
B238: D7960C00015 | C238: Astra Zeneca | D238: Peru | E238: Distribution | I238: Configuration of Temperature Monitoring Device | M238: 44.54901 | N238: 1 | O238: 44.54901 | P238: BSPeru
B239: D7960C00015 | C239: Astra Zeneca | D239: Peru | E239: Distribution | I239: Pick and Pack (Ambient) | M239: 647.64811 | N239: 1 | O239: 647.64811 | P239: BSPeru
B240: D7960C00015 | C240: Astra Zeneca | D240: Peru | E240: Distribution | I240: Project Management Fee | M240: 409.04091 | N240: 1 | O240: 409.04091 | P240: BSPeru
B241: D7960C00015 | C241: Astra Zeneca | D241: Peru | E241: Storage | I241: Storage Ambient (per Pallet) | M241: 518.11849 | N241: 1 | O241: 518.11849 | P241: BSPeru
B242: D7860C00006 | C242: Astra Zeneca | D242: Peru | E242: Distribution | I242: Project Management Fee | M242: 409.04091 | N242: 1 | O242: 409.04091 | P242: BSPeru
B243: D7860C00006 | C243: Astra Zeneca | D243: Peru | E243: Storage | I243: Storage Ambient (per Pallet) | M243: 129.52962 | N243: 1 | O243: 129.52962 | P243: BSPeru
B244: D7700C00003 | C244: MedImmune Inc | D244: Peru | E244: Distribution | I244: Insulated shipper - Credo S4 - 12L (Leasing) | M244: 1014.3135 | N244: 1 | O244: 1014.3135 | P244: BSPeru
B245: D7700C00003 | C245: MedImmune Inc | D245: Peru | E245: Distribution | I245: Pick and Pack (Refrigerated) | M245: 518.11849 | N245: 1 | O245: 518.11849 | P245: BSPeru
B246: D7700C00003 | C246: MedImmune Inc | D246: Peru | E246: Distribution | I246: Project Management Fee | M246: 409.04091 | N246: 1 | O246: 409.04091 | P246: BSPeru
B247: D7700C00003 | C247: MedImmune Inc | D247: Peru | E247: Storage | I247: Storage Refrigerated (per Pallet) | M247: 313.59803 | N247: 1 | O247: 313.59803 | P247: BSPeru
B248: D7700C00003 | C248: MedImmune Inc | D248: Peru | E248: Distribution | I248: Temperature Monitoring Device (Refrigerated) | M248: 35.639208 | N248: 1 | O248: 35.639208 | P248: BSPeru
B249: GS-US-528-9023 | C249: Gilead Sciences, Inc. | D249: Peru | E249: Freight | I249: Freight - Returns | M249: 709.1 | N249: 1 | O249: 709.1 | P249: BSPeru
... B290: Others | C290: Others | D290: Peru | E290: Comparator | I290: FX Translation | M290: 0 | N290: 1 | O290: 0 | P290: BSPeru
O291: =SUM(O3:O290) -> 240293.2

Sheet HFM (Datos)
B1: BSArgentina | C1: BSBrazilUSD | D1: BSMexico | E1: BSChile | F1: BSColombia | G1: BSPeru | H1: BrazilTP
A2: Packaging | B2: 36028 | C2: 16213 | D2: 70 | E2: 0 | F2: 0 | G2: 0
A3: Storage | B3: 508279 | C3: 537603 | D3: 264052 | E3: 168297.81 | F3: 119624 | G3: 105445
A4: Distributing | B4: 691858 | C4: 1312661 | D4: 306865 | E4: 265504.69 | F4: 187327 | G4: 112669.12
A5: Freight | B5: 529642 | C5: 1156238 | D5: 733893 | E5: 29574.183 | F5: 95331 | G5: 21258.08 | H5: 503337
A6: ReturnDrug | B6: 75325 | C6: 117230 | D6: 55003 | E6: 15946.062 | F6: 771 | G6: 921
A7: BSDDuty | B7: -498649 | C7: 642180 | D7: 74462 | E7: 29724.354 | F7: 0 | G7: 0 | H7: 844409
A8: ClinicalSvcsOther | B8: 0 | C8: 0 | D8: 0 | E8: 0 | F8: 0 | G8: 0
A9: Comparator | B9: 0 | C9: 833119 | D9: 64909 | E9: 169676.32 | F9: 0 | G9: 0
A10: CAM
A11: Revenue | B11: 1342483 | C11: 4615244 | D11: 1499254 | E11: 678722.42 | F11: 403054 | G11: 240293.2 | H11: =SUM(H2:H9) -> 1347746
B12: =+Arg!O564 -> 1342483 | C12: =+Bra!O876 -> 4615244 | D12: ='Mex '!$O$461 -> 1499254 | E12: =+Chi!O432 -> 678722.42 | F12: =Col!$O$500 -> 403054 | G12: =+Per!O291 -> 240293.2 | H12: ='Bra TP'!$O$334 -> -1347746.7 | I12: Se registra en positivo o negativo
B13: =+B11-B12 -> 8.3819032e-09 | C13: =+C11-C12 -> -1.0244548e-08 | D13: =+D11-D12 -> 3.9581209e-09 | E13: =+E11-E12 -> 1.8626451e-09 | F13: =+F11-F12 -> 0 | G13: =+G11-G12 -> 0 | H13: =+H11-H12 -> 2695492.7

Sheet Selectable Table
A1: Categoria | B1: Product Line Name | C1: Categoria | D1: Sponsor | E1: CUSTOMER | H1: Tipo de Revenue | O1: Sponsor | P1: EL2 Codes | S1: Exchange Rates | T1: Period | U1: USD | V1: EUR | W1: GBP | X1: CHF | Y1: BRL | AB1: el3_name | AC1: Discount Flag | AG1: Line description / SUB-PRODUCT | AH1: Custom 2 / PRODUCT
B2: Total Manufacturing | D2: Amgen, Inc. | E2: AMGEN | H2: Fisherbook | O2: 89bio Inc | P2: 40700 | Q2: Revenues - Third Parties | T2: 1 | U2: 1 | V2: 1.0845 | W2: 1.27 | X2: 1.1604 | Y2: 0.202 | AB2: 606 Adj mar20 | AC2: Not Applicable | AG2: Non-Drug Total Storage Ambient (per Pallet) | AH2: Total Storage
A3: Packaging | B3: Total Packaging | C3: Packaging | D3: Eledon Pharmaceuticals Inc | E3: OTH CUST | H3: Manuales | O3: AbbVie Inc. | P3: 40700 | Q3: Revenues - Third Parties | T3: 2 | U3: 1 | AB3: 606 Adjustement | AC3: Not Applicable | AG3: Total Storage Ambient (per Pallet) | AH3: Total Storage
A4: Distribution | B4: Total Distribution | C4: Distribution | D4: IQVIA | E4: IQVIA | H4: Rebate 2023 | O4: ADC Therapeutics SA | P4: 40700 | Q4: Revenues - Third Parties | T4: 3 | U4: 1 | AB4: Additional Documents to Add (per Shipment) | AG4: Total Storage of Returns (per Pallet) | AH4: Total Storage
A5: Storage | B5: Total Storage | C5: Storage | D5: Janssen | E5: J & J | H5: Surcharge | O5: Advanced Accelerator Applications International | P5: 40700 | Q5: Revenues - Third Parties | T5: 4 | U5: 1 | AB5: Additional Reports | AG5: Total Freight - Returns | AH5: Total Freight
B6: Total Tooling | D6: Merck Sharp & Dohme | E6: MERCK | H6: 606 ADJUSTMENT | O6: Akero Therapeutics | P6: 40700 | Q6: Revenues - Third Parties | T6: 5 | U6: 1 | AB6: Comparator | AC6: 1 | AG6: Reconciliation of Returns (per Hour) | AH6: Total Return Drug
B7: Total Program Management | D7: Novocure Inc | E7: OTH CUST | H7: Duties adjustment | O7: Alector LLC | P7: 40700 | Q7: Revenues - Third Parties | T7: 6 | U7: 1 | AB7: Adjustment due to services rendered between 16/02 - 29/02 | AC7: Not Applicable | AG7: Returns Receipt (per Receipt) | AH7: Total Return Drug
D8: Regeneron Pharmaceuticals Inc | E8: REGENERON | H8: 15 días | O8: Alexion Pharmaceuticals Inc | P8: 40700 | Q8: Revenues - Third Parties | T8: 7 | U8: 1 | AB8: Adjustment due to services rendered between 16/05 - 04/06 | AC8: Not Applicable | AG8: Total Freight - Shipments | AH8: Total Freight
A9: Comparator | B9: Total Comparator | C9: Comparator | D9: Regeneron Pharmaceuticals Inc | E9: REGENERON | H9: AON Insurance Charge - NC Pfizer | O9: Alnylam Pharmaceuticals | P9: 40700 | Q9: Revenues - Third Parties | T9: 8 | U9: 1 | AB9: Adjustment due to services rendered between 16/09 - 04/10 | AC9: Not Applicable | AG9: Destruction (per Kg) | AH9: Total Return Drug
B10: Total FACTS | D10: Viracta Subsidiary Inc | E10: OTH CUST | H10: FX Translation | O10: Alpine Immune Sciences Inc | P10: 40700 | Q10: Revenues - Third Parties | T10: 9 | U10: 1 | AB10: Adjustment due to services rendered between 16/09 - 30/09 | AC10: Not Applicable | AG10: Destruction Setup Fee | AH10: Total Return Drug
B11: Total Label Generation | D11: 89bio Inc | E11: OTH CUST | H11: Fisherbook Local | O11: Amgen Ancillaries | P11: 40700 | Q11: Revenues - Third Parties | T11: 10 | U11: 1 | AB11: Adjustment Estimated Revenue of the month 16/01 - 15/02 | AC11: Not Applicable | AG11: Total Storage of Labels Ambient (per Pallet) | AH11: Total Storage
A12: ReturnDrug | B12: Total Return Drug | C12: ReturnDrug | D12: 89Bio Inc. | E12: OTH CUST | H12: Fisherbook Foreign | O12: Amgen, Inc. | P12: 40700 | Q12: Revenues - Third Parties | T12: 11 | U12: 1 | AB12: Adjustment Estimated Revenue of the month 16/08 - 15/09 | AC12: Not Applicable | AG12: Receipt fee Ambient (per Receipt_ID) | AH12: Total Distribution
B13: Total Bio Services | D13: 89bio, Inc. | E13: OTH CUST | H13: LocalAdj - GNRE | O13: Arcus Biosciences Inc | P13: 40700 | Q13: Revenues - Third Parties | T13: 12 | U13: 1 | AB13: Adjustment for Adoption Nbr. 606 | AC13: Not Applicable | AG13: Pick and Pack (Controlled Ambient) | AH13: Total Distribution
A14: Freight | B14: Total Freight | C14: Freight | D14: 89bio, Inc. | E14: OTH CUST | H14: LocalAdj- Duties | O14: Argenx BVBA | P14: 40700 | Q14: Revenues - Third Parties | AB14: Administrative fee | AG14: Pick and Pack (Refrigerated) | AH14: Total Distribution
A15: Duties | B15: Total Duty | C15: Duties | D15: Abbvie | E15: OTH CUST | H15: X LocalAdj | O15: Array Biopharma Inc. | P15: 40700 | Q15: Revenues - Third Parties | AB15: Ambient Shipment High Protection | AG15: Total Storage Refrigerated (per Shelf) | AH15: Total Storage
A16: Destructions | B16: Total Return Drug | C16: Destructions | D16: AbbVie Inc. | E16: OTH CUST | O16: Astellas Pharma Europe B.V | P16: 40700 | Q16: Revenues - Third Parties | AB16: Ambient Shipment Low Protection | AG16: Pick and Pack (Ambient) | AH16: Total Distribution
A17: Returns | B17: Total Return Drug | C17: Returns | D17: Ablynx | E17: ABLYNX | O17: Astra Zeneca | P17: 40700 | Q17: Revenues - Third Parties | AB17: AoR per Receipt | AG17: Total Storage Ambient (per Shelf) | AH17: Total Storage
D18: Acceleron Pharma INC | E18: OTH CUST | O18: aTyr Pharma Inc | P18: 40700 | Q18: Revenues - Third Parties | AB18: Assembly of Kits (Refrigerated) | AG18: Labeling / Relabeling (per Label) | AH18: Total Packaging
A19: Returns and Destructions | B19: Total Return Drug | C19: Returns and Destructions | D19: ActivaCro | E19: OTH CUST | O19: Bayer AG | P19: 40700 | Q19: Revenues - Third Parties | AB19: Bayer Accrual Q3-2019 | AC19: Not Applicable | AG19: Labeling / Relabeling Set Up Fee | AH19: Total Packaging
